Workbook

Sheet Assumptions
A1: ASSUMPTIONS SHEET
A3: INCOME - HUSBAND
A4: Base Gross Salary (2026) | B4: 88397
A5: Salary Growth Rate | B5: 0.05
A6: Base Bonus (2026) | B6: 9821
A7: Bonus Growth Rate | B7: 0.05
A8: Monthly Time Account Deduction | B8: 200
A9: Bonus to Time Account % | B9: 0.35
A10: RSU Annual Grant | B10: 20000
A11: RSU Tax Rate | B11: 0.443
A12: Stock Price | B12: 210
A14: INCOME - WIFE
A15: Base Gross Salary (2026) | B15: 74348
A16: Salary Growth Rate | B16: 0.035
A17: Base Bonus (2026) | B17: 8261
A18: Bonus Growth Rate | B18: 0.035
A19: Monthly Time Account Deduction | B19: 200
A20: Bonus to Time Account % | B20: 0.35
A21: RSU Annual Grant | B21: 10000
A23: TIME ACCOUNT
A24: Starting Hours - Husband (Dec 2025) | B24: 1700
A25: Starting Hours - Wife (Dec 2025) | B25: 20
A26: Starting Hourly Rate (2026) | B26: 42.5
A27: Hourly Rate Growth | B27: 0.05
A28: Time Account Tax Haircut | B28: 0.35
A30: MORTGAGE
A31: Original Principal | B31: 431000
A32: Interest Rate | B32: 0.0389
A33: Monthly Payment | B33: 2281
A34: Max Sondertilgung (5%) | B34: 21550
A35: Start Month (Jun 2023) | B35: 1
A36: Maturity Month | B36: 120
A37: Balance after Nov 2025 | B37: 397546
A38: Sondertilgung Dec 2025 | B38: 0
A40: INVESTMENT
A41: Starting Balance (Dec 2025) | B41: 12000
A42: Annual Return | B42: 0.085
A43: Monthly Return Factor | B43: 1.006818
A44: Tax on Gains (Effective) | B44: 0.184625
A45: Monthly Salary Investment Start | B45: 1000
A46: Annual Investment Increase | B46: 200
A48: YOUTUBE
A49: Starting Gross (Jan 2026) | B49: 1000
A50: Growth per 6 months | B50: 1000
A51: Monthly Cap | B51: 20000
A52: Tax Rate | B52: 0.443
A54: HOUSE
A55: Starting Value (Dec 2025) | B55: 520000
A56: Annual Appreciation | B56: 0.015
A57: OWNSAP
A58: Husband OWNSAP % of Gross | B58: 0.1
A59: Wife OWNSAP % of Gross | B59: 0.1
A60: Company Match % | B60: 0.4
A61: Company Fixed Bonus | B61: 20
A63: SAP LOAN (HOUSE)
A64: SAP Loan Starting Balance (Jan 2026) | B64: 52500
A65: SAP Loan Monthly Principal | B65: 583.33
A66: SAP Loan End Month | B66: 120
A67: SAP Loan Start Date | B67: Jun 2023
A69: EXPENSES BUDGET
A70: Childcare | B70: 920
A71: Family Support | B71: 700
A72: Groceries + Food | B72: 500
A73: Utilities | B73: 500
A74: Car | B74: 400
A75: Shopping | B75: 200
A76: Travel & Leisure | B76: 150
A77: Insurance | B77: 120
A78: Eat Out & Food delivery | B78: 120
A79: Gifts | B79: 100
A80: Entertainment | B80: 100
A81: Health & beauty | B81: 50
... A86: Buffer | B86: 100
A87: Total Expense Budget (2026) | B87: =SUM(B70:B86) -> 4110
A88: Lifestyle Inflation % | B88: 0.03
A90: TARGETS & CAPS
A91: Cashpile Target Phase 1 | B91: 5000
A92: Cashpile Target Phase 2 | B92: 15000
A93: CMP Cap | B93: 10000
A94: Max Monthly Deficit Tolerance | B94: -1000
A95: Cashpile Replenish Months | B95: 6
A97: ALLOCATION RULES
A98: Excess to Cashpile % | B98: 0.2
A99: Excess to Investment % | B99: 0.8
A101: TAX RATES
A102: Salary Tax (effective) | B102: 0.4
A103: RSU Tax | B103: 0.443
A104: YouTube Tax | B104: 0.443
A105: Investment Gains Tax | B105: 0.184625
A107: DEBT MINIMUM PAYMENTS
A108: TF Card Minimum | B108: 300
A109: TF Attack Buffer | B109: 2000
A110: Revolut Fixed Payment | B110: 650
A111: Revolut End Year | B111: 2027
A112: Revolut End Month | B112: 8
A113: Klarna Minimum | B113: 200
A114: Nordea Minimum | B114: 100
A115: Aktia Minimum | B115: 30
A116: C3 Monthly | B116: 290
A117: C3 Quarterly Extra | B117: 2350
...

Sheet SL_Investment_Log
A1: ID | B1: Date | C1: MonthKey | D1: Amount | E1: Destination | F1: Notes | G1: Timestamp | H1: InputBy

Sheet SL_Income_Log
A1: ID | B1: MonthKey | C1: Type | D1: Amount | E1: Spender | F1: Description | G1: Timestamp | H1: InputBy

Sheet SL_Config
A1: key | B1: value
A2: discord_webhook_url | B2: https://discord.com/api/webhooks/1450509364107546636/kPJPDwRkoi90cz1lOqHhKii3rZ2mRc4ZYmfsXffNoPznLutEsphUTMqQDA_7IhUNxyGn
A3: h_discord_username | B3: hewhoremains_80685
A4: w_discord_username | B4: trang_54164
A5: timezone | B5: Europe/Berlin
A6: daily_summary_hour | B6: 21
A7: weekly_summary_day | B7: 0
A8: alert_threshold_warning | B8: 0.8
A9: alert_threshold_info | B9: 0.5
A10: gemini_api_key

Sheet SL_Patterns
A1: pattern | B1: category | C1: confidence | D1: source | E1: last_used
A2: rewe | B2: Groceries + Food | C2: high | D2: builtin | E2: 46007.515
A3: lidl | B3: Groceries + Food | C3: high | D3: builtin | E3: 46007.545
A4: edeka | B4: Groceries + Food | C4: high | D4: builtin
A5: aldi | B5: Groceries + Food | C5: high | D5: builtin
A6: penny | B6: Groceries + Food | C6: high | D6: builtin
A7: netto | B7: Groceries + Food | C7: high | D7: builtin
A8: kaufland | B8: Groceries + Food | C8: high | D8: builtin
A9: globus | B9: Groceries + Food | C9: high | D9: builtin
A10: lieferando | B10: Eat Out & Food delivery | C10: high | D10: builtin
A11: wolt | B11: Eat Out & Food delivery | C11: high | D11: builtin
A12: uber eats | B12: Eat Out & Food delivery | C12: high | D12: builtin
A13: kebab | B13: Eat Out & Food delivery | C13: high | D13: builtin
A14: döner | B14: Eat Out & Food delivery | C14: high | D14: builtin
A15: mcdonald | B15: Eat Out & Food delivery | C15: high | D15: builtin
... A62: axa | B62: Insurance | C62: high | D62: builtin

Sheet SL_Budget
A1: category | B1: Budget | C1: Month_Key | D1: Spent | E1: Remaining | F1: Percent
A2: Childcare | B2: 920 | C2: 2025-12 | D2: =SUMIFS(ShadowLedger!$D:$D,ShadowLedger!$G:$G,A2,ShadowLedger!$C:$C,">="&DATE(LEFT(SUBSTITUTE(C2,"'",""),4),MID(SUBSTITUTE(C2,"'",""),6,2),1),ShadowLedger!$C:$C,"<"&EOMONTH(DATE(LEFT(SUBSTITUTE(C2,"'",""),4),MID(SUBSTITUTE(C2,"'",""),6,2),1),0)+1) -> 913 | E2: =B2-D2 -> 7 | F2: =IF(B2>0,D2/B2,0) -> 0.9923913
A3: Family Support | B3: 700 | C3: 2025-12 | D3: =SUMIFS(ShadowLedger!$D:$D,ShadowLedger!$G:$G,A3,ShadowLedger!$C:$C,">="&DATE(LEFT(SUBSTITUTE(C3,"'",""),4),MID(SUBSTITUTE(C3,"'",""),6,2),1),ShadowLedger!$C:$C,"<"&EOMONTH(DATE(LEFT(SUBSTITUTE(C3,"'",""),4),MID(SUBSTITUTE(C3,"'",""),6,2),1),0)+1) -> 229.57 | E3: =B3-D3 -> 470.43 | F3: =IF(B3>0,D3/B3,0) -> 0.32795714
A4: Groceries + Food | B4: 500 | C4: 2025-12 | D4: =SUMIFS(ShadowLedger!$D:$D,ShadowLedger!$G:$G,A4,ShadowLedger!$C:$C,">="&DATE(LEFT(SUBSTITUTE(C4,"'",""),4),MID(SUBSTITUTE(C4,"'",""),6,2),1),ShadowLedger!$C:$C,"<"&EOMONTH(DATE(LEFT(SUBSTITUTE(C4,"'",""),4),MID(SUBSTITUTE(C4,"'",""),6,2),1),0)+1) -> 907.1 | E4: =B4-D4 -> -407.1 | F4: =IF(B4>0,D4/B4,0) -> 1.8142
A5: Utilities | B5: 500 | C5: 2025-12 | D5: =SUMIFS(ShadowLedger!$D:$D,ShadowLedger!$G:$G,A5,ShadowLedger!$C:$C,">="&DATE(LEFT(SUBSTITUTE(C5,"'",""),4),MID(SUBSTITUTE(C5,"'",""),6,2),1),ShadowLedger!$C:$C,"<"&EOMONTH(DATE(LEFT(SUBSTITUTE(C5,"'",""),4),MID(SUBSTITUTE(C5,"'",""),6,2),1),0)+1) -> 55 | E5: =B5-D5 -> 445 | F5: =IF(B5>0,D5/B5,0) -> 0.11
A6: Car | B6: 400 | C6: 2025-12 | D6: =SUMIFS(ShadowLedger!$D:$D,ShadowLedger!$G:$G,A6,ShadowLedger!$C:$C,">="&DATE(LEFT(SUBSTITUTE(C6,"'",""),4),MID(SUBSTITUTE(C6,"'",""),6,2),1),ShadowLedger!$C:$C,"<"&EOMONTH(DATE(LEFT(SUBSTITUTE(C6,"'",""),4),MID(SUBSTITUTE(C6,"'",""),6,2),1),0)+1) -> 882 | E6: =B6-D6 -> -482 | F6: =IF(B6>0,D6/B6,0) -> 2.205
A7: Shopping | B7: 200 | C7: 2025-12 | D7: =SUMIFS(ShadowLedger!$D:$D,ShadowLedger!$G:$G,A7,ShadowLedger!$C:$C,">="&DATE(LEFT(SUBSTITUTE(C7,"'",""),4),MID(SUBSTITUTE(C7,"'",""),6,2),1),ShadowLedger!$C:$C,"<"&EOMONTH(DATE(LEFT(SUBSTITUTE(C7,"'",""),4),MID(SUBSTITUTE(C7,"'",""),6,2),1),0)+1) -> 457.21 | E7: =B7-D7 -> -257.21 | F7: =IF(B7>0,D7/B7,0) -> 2.28605
A8: Travel & Leisure | B8: 150 | C8: 2025-12 | D8: =SUMIFS(ShadowLedger!$D:$D,ShadowLedger!$G:$G,A8,ShadowLedger!$C:$C,">="&DATE(LEFT(SUBSTITUTE(C8,"'",""),4),MID(SUBSTITUTE(C8,"'",""),6,2),1),ShadowLedger!$C:$C,"<"&EOMONTH(DATE(LEFT(SUBSTITUTE(C8,"'",""),4),MID(SUBSTITUTE(C8,"'",""),6,2),1),0)+1) -> 792.58 | E8: =B8-D8 -> -642.58 | F8: =IF(B8>0,D8/B8,0) -> 5.2838667
A9: Insurance | B9: 120 | C9: 2025-12 | D9: =SUMIFS(ShadowLedger!$D:$D,ShadowLedger!$G:$G,A9,ShadowLedger!$C:$C,">="&DATE(LEFT(SUBSTITUTE(C9,"'",""),4),MID(SUBSTITUTE(C9,"'",""),6,2),1),ShadowLedger!$C:$C,"<"&EOMONTH(DATE(LEFT(SUBSTITUTE(C9,"'",""),4),MID(SUBSTITUTE(C9,"'",""),6,2),1),0)+1) -> 0 | E9: =B9-D9 -> 120 | F9: =IF(B9>0,D9/B9,0) -> 0
A10: Eat Out & Food delivery | B10: 120 | C10: 2025-12 | D10: =SUMIFS(ShadowLedger!$D:$D,ShadowLedger!$G:$G,A10,ShadowLedger!$C:$C,">="&DATE(LEFT(SUBSTITUTE(C10,"'",""),4),MID(SUBSTITUTE(C10,"'",""),6,2),1),ShadowLedger!$C:$C,"<"&EOMONTH(DATE(LEFT(SUBSTITUTE(C10,"'",""),4),MID(SUBSTITUTE(C10,"'",""),6,2),1),0)+1) -> 160.5 | E10: =B10-D10 -> -40.5 | F10: =IF(B10>0,D10/B10,0) -> 1.3375
A11: Gifts | B11: 100 | C11: 2025-12 | D11: =SUMIFS(ShadowLedger!$D:$D,ShadowLedger!$G:$G,A11,ShadowLedger!$C:$C,">="&DATE(LEFT(SUBSTITUTE(C11,"'",""),4),MID(SUBSTITUTE(C11,"'",""),6,2),1),ShadowLedger!$C:$C,"<"&EOMONTH(DATE(LEFT(SUBSTITUTE(C11,"'",""),4),MID(SUBSTITUTE(C11,"'",""),6,2),1),0)+1) -> 524.45 | E11: =B11-D11 -> -424.45 | F11: =IF(B11>0,D11/B11,0) -> 5.2445
A12: Entertainment | B12: 100 | C12: 2025-12 | D12: =SUMIFS(ShadowLedger!$D:$D,ShadowLedger!$G:$G,A12,ShadowLedger!$C:$C,">="&DATE(LEFT(SUBSTITUTE(C12,"'",""),4),MID(SUBSTITUTE(C12,"'",""),6,2),1),ShadowLedger!$C:$C,"<"&EOMONTH(DATE(LEFT(SUBSTITUTE(C12,"'",""),4),MID(SUBSTITUTE(C12,"'",""),6,2),1),0)+1) -> 0 | E12: =B12-D12 -> 100 | F12: =IF(B12>0,D12/B12,0) -> 0
A13: Buffer | B13: 100 | C13: 2025-12 | D13: =SUMIFS(ShadowLedger!$D:$D,ShadowLedger!$G:$G,A13,ShadowLedger!$C:$C,">="&DATE(LEFT(SUBSTITUTE(C13,"'",""),4),MID(SUBSTITUTE(C13,"'",""),6,2),1),ShadowLedger!$C:$C,"<"&EOMONTH(DATE(LEFT(SUBSTITUTE(C13,"'",""),4),MID(SUBSTITUTE(C13,"'",""),6,2),1),0)+1) -> 67.37 | E13: =B13-D13 -> 32.63 | F13: =IF(B13>0,D13/B13,0) -> 0.6737
... A3486: Special IO | B3486: 0 | C3486: 2042-12 | D3486: =SUMIFS(ShadowLedger!$D:$D,ShadowLedger!$G:$G,A3486,ShadowLedger!$C:$C,">="&DATE(LEFT(SUBSTITUTE(C3486,"'",""),4),MID(SUBSTITUTE(C3486,"'",""),6,2),1),ShadowLedger!$C:$C,"<"&EOMONTH(DATE(LEFT(SUBSTITUTE(C3486,"'",""),4),MID(SUBSTITUTE(C3486,"'",""),6,2),1),0)+1) -> 0 | E3486: =B3486-D3486 -> 0 | F3486: =IF(B3486>0,D3486/B3486,0) -> 0

Sheet SL_Budget_Backup
A1: category | B1: monthly_budget | C1: current_spent | D1: remaining | E1: percent_used | F1: status
A2: Childcare | B2: 920 | C2: =SUMIFS(ShadowLedger!D:D,ShadowLedger!G:G,A2,ShadowLedger!O:O,TEXT(TODAY(),"YYYY-MM")) -> 913 | D2: =B2-C2 -> 7 | E2: =IF(B2>0,C2/B2,0) -> 0.9923913 | F2: =IF(E2>=1,"🔴 OVER",IF(E2>=0.8,"🟠 WARNING",IF(E2>=0.5,"🟡 INFO","🟢 OK"))) -> 🟠 WARNING
A3: Family Support | B3: 700 | C3: =SUMIFS(ShadowLedger!D:D,ShadowLedger!G:G,A3,ShadowLedger!O:O,TEXT(TODAY(),"YYYY-MM")) -> 229.57 | D3: =B3-C3 -> 470.43 | E3: =IF(B3>0,C3/B3,0) -> 0.32795714 | F3: =IF(E3>=1,"🔴 OVER",IF(E3>=0.8,"🟠 WARNING",IF(E3>=0.5,"🟡 INFO","🟢 OK"))) -> 🟢 OK
A4: Groceries + Food | B4: 500 | C4: =SUMIFS(ShadowLedger!D:D,ShadowLedger!G:G,A4,ShadowLedger!O:O,TEXT(TODAY(),"YYYY-MM")) -> 907.1 | D4: =B4-C4 -> -407.1 | E4: =IF(B4>0,C4/B4,0) -> 1.8142 | F4: =IF(E4>=1,"🔴 OVER",IF(E4>=0.8,"🟠 WARNING",IF(E4>=0.5,"🟡 INFO","🟢 OK"))) -> 🔴 OVER
A5: Utilities | B5: 500 | C5: =SUMIFS(ShadowLedger!D:D,ShadowLedger!G:G,A5,ShadowLedger!O:O,TEXT(TODAY(),"YYYY-MM")) -> 55 | D5: =B5-C5 -> 445 | E5: =IF(B5>0,C5/B5,0) -> 0.11 | F5: =IF(E5>=1,"🔴 OVER",IF(E5>=0.8,"🟠 WARNING",IF(E5>=0.5,"🟡 INFO","🟢 OK"))) -> 🟢 OK
A6: Car | B6: 400 | C6: =SUMIFS(ShadowLedger!D:D,ShadowLedger!G:G,A6,ShadowLedger!O:O,TEXT(TODAY(),"YYYY-MM")) -> 882 | D6: =B6-C6 -> -482 | E6: =IF(B6>0,C6/B6,0) -> 2.205 | F6: =IF(E6>=1,"🔴 OVER",IF(E6>=0.8,"🟠 WARNING",IF(E6>=0.5,"🟡 INFO","🟢 OK"))) -> 🔴 OVER
A7: Shopping | B7: 200 | C7: =SUMIFS(ShadowLedger!D:D,ShadowLedger!G:G,A7,ShadowLedger!O:O,TEXT(TODAY(),"YYYY-MM")) -> 457.21 | D7: =B7-C7 -> -257.21 | E7: =IF(B7>0,C7/B7,0) -> 2.28605 | F7: =IF(E7>=1,"🔴 OVER",IF(E7>=0.8,"🟠 WARNING",IF(E7>=0.5,"🟡 INFO","🟢 OK"))) -> 🔴 OVER
A8: Travel & Leisure | B8: 150 | C8: =SUMIFS(ShadowLedger!D:D,ShadowLedger!G:G,A8,ShadowLedger!O:O,TEXT(TODAY(),"YYYY-MM")) -> 792.58 | D8: =B8-C8 -> -642.58 | E8: =IF(B8>0,C8/B8,0) -> 5.2838667 | F8: =IF(E8>=1,"🔴 OVER",IF(E8>=0.8,"🟠 WARNING",IF(E8>=0.5,"🟡 INFO","🟢 OK"))) -> 🔴 OVER
A9: Insurance | B9: 120 | C9: =SUMIFS(ShadowLedger!D:D,ShadowLedger!G:G,A9,ShadowLedger!O:O,TEXT(TODAY(),"YYYY-MM")) -> 0 | D9: =B9-C9 -> 120 | E9: =IF(B9>0,C9/B9,0) -> 0 | F9: =IF(E9>=1,"🔴 OVER",IF(E9>=0.8,"🟠 WARNING",IF(E9>=0.5,"🟡 INFO","🟢 OK"))) -> 🟢 OK
A10: Eat Out & Food delivery | B10: 120 | C10: =SUMIFS(ShadowLedger!D:D,ShadowLedger!G:G,A10,ShadowLedger!O:O,TEXT(TODAY(),"YYYY-MM")) -> 160.5 | D10: =B10-C10 -> -40.5 | E10: =IF(B10>0,C10/B10,0) -> 1.3375 | F10: =IF(E10>=1,"🔴 OVER",IF(E10>=0.8,"🟠 WARNING",IF(E10>=0.5,"🟡 INFO","🟢 OK"))) -> 🔴 OVER
A11: Gifts | B11: 100 | C11: =SUMIFS(ShadowLedger!D:D,ShadowLedger!G:G,A11,ShadowLedger!O:O,TEXT(TODAY(),"YYYY-MM")) -> 524.45 | D11: =B11-C11 -> -424.45 | E11: =IF(B11>0,C11/B11,0) -> 5.2445 | F11: =IF(E11>=1,"🔴 OVER",IF(E11>=0.8,"🟠 WARNING",IF(E11>=0.5,"🟡 INFO","🟢 OK"))) -> 🔴 OVER
A12: Entertainment | B12: 100 | C12: =SUMIFS(ShadowLedger!D:D,ShadowLedger!G:G,A12,ShadowLedger!O:O,TEXT(TODAY(),"YYYY-MM")) -> 0 | D12: =B12-C12 -> 100 | E12: =IF(B12>0,C12/B12,0) -> 0 | F12: =IF(E12>=1,"🔴 OVER",IF(E12>=0.8,"🟠 WARNING",IF(E12>=0.5,"🟡 INFO","🟢 OK"))) -> 🟢 OK
A13: Buffer | B13: 100 | C13: =SUMIFS(ShadowLedger!D:D,ShadowLedger!G:G,A13,ShadowLedger!O:O,TEXT(TODAY(),"YYYY-MM")) -> 67.37 | D13: =B13-C13 -> 32.63 | E13: =IF(B13>0,C13/B13,0) -> 0.6737 | F13: =IF(E13>=1,"🔴 OVER",IF(E13>=0.8,"🟠 WARNING",IF(E13>=0.5,"🟡 INFO","🟢 OK"))) -> 🟡 INFO
... A18: Special IO | B18: 0 | C18: =SUMIFS(ShadowLedger!D:D,ShadowLedger!G:G,A18,ShadowLedger!O:O,TEXT(TODAY(),"YYYY-MM")) -> 2210.76 | D18: =B18-C18 -> -2210.76 | E18: =IF(B18>0,C18/B18,0) -> 0 | F18: =IF(E18>=1,"🔴 OVER",IF(E18>=0.8,"🟠 WARNING",IF(E18>=0.5,"🟡 INFO","🟢 OK"))) -> 🟢 OK
B19: =SUM(B2:B18) -> 4110 | C19: =SUM(C2:C18) -> 8123.14 | D19: =SUM(D2:D18) -> -4013.14 | E19: =IF(B19>0,C19/B19,0) -> 1.9764331 | F19: =IF(E19>=1,"🔴 OVER",IF(E19>=0.8,"🟠 WARNING",IF(E19>=0.5,"🟡 INFO","🟢 OK"))) -> 🔴 OVER

Sheet ShadowLedger
A1: txn_id | B1: timestamp | C1: txn_date | D1: amount | E1: merchant | F1: description | G1: category | H1: spender | I1: inputter | J1: input_method | K1: categorization | L1: reviewed | M1: review_date | N1: raw_input | O1: month_key
A2: SL-20251218-155837-073 | B2: 46009.666 | C2: 46009.666 | D2: 10 | E2: cheese in nancy | G2: Travel & Leisure | H2: H | I2: H | J2: Discord | K2: ai | L2: FALSE | N2: 10e cheese in nancy | O2: 2025-12
A3: SL-20251218-155922-024 | B3: 46009.666 | C3: 46009.666 | D3: 122 | E3: Auchan in nancy groceries | G3: Travel & Leisure | H3: H | I3: H | J3: Discord | K3: ai | L3: FALSE | N3: Auchan 122e in nancy groceries | O3: 2025-12
A4: SL-20251218-160010-992 | B4: 46009.667 | C4: 46009.667 | D4: 4.8 | E4: Toll road nancy | G4: Travel & Leisure | H4: H | I4: H | J4: Discord | K4: ai | L4: FALSE | N4: Toll road nancy 4,8e | O4: 2025-12
A5: SL-20251218-160055-896 | B5: 46009.667 | C5: 46009.667 | D5: 5.4 | E5: Bread croissant nancy | G5: Travel & Leisure | H5: H | I5: H | J5: Discord | K5: ai | L5: FALSE | N5: Bread croissant 5,4e nancy | O5: 2025-12
A6: SL-20251218-162337-739 | B6: 46009.683 | C6: 46009.683 | D6: 13.1 | E6: Cakes in nancy | G6: Travel & Leisure | H6: H | I6: H | J6: Discord | K6: ai | L6: FALSE | N6: 13,10 category: eat-out, item: cakes | O6: 2025-12
A7: SL-20251218-205454-201 | B7: 46009.871 | C7: 46009.871 | D7: 24 | E7: Carrefour, category: groceries | G7: Travel & Leisure | H7: W | I7: H | J7: Discord | K7: user | L7: TRUE | M7: 46009.871 | N7: Trang 24e carrefour, category: groceries | O7: 2025-12
A8: SL-20251218-205529-115 | B8: 46009.872 | C8: 46009.872 | D8: 14 | E8: mcdonalds eat-out | G8: Travel & Leisure | H8: W | I8: H | J8: Discord | K8: ai | L8: FALSE | N8: Trang 14e mcdonalds eat-out | O8: 2025-12
A9: SL-20251219-195059-277 | B9: 46010.827 | C9: 46010.827 | D9: 95.28 | E9: category: travel, description: groceries and gift and food, merchant: nancy | G9: Travel & Leisure | H9: H | I9: H | J9: Discord | K9: ai | L9: FALSE | N9: 95,28e category: travel, description: groceries and gift and food, merchant: nancy | O9: 2025-12
A10: SL-20251221-163635-368 | B10: 46012.692 | C10: 46011.5 | D10: 225.8 | E10: category: travel, description: nancy | G10: Travel & Leisure | H10: H | I10: H | J10: Discord | K10: ai | L10: FALSE | N10: Yesterday 225,8 category: travel, description: nancy | O10: 2025-12
A11: SL-20251221-163704-779 | B11: 46012.692 | C11: 46012.692 | D11: 10.4 | E11: category: travel, description: nancy | G11: Travel & Leisure | H11: H | I11: H | J11: Discord | K11: ai | L11: FALSE | N11: 10,4 category: travel, description: nancy | O11: 2025-12
A12: SL-20251222-124059-687 | B12: 46013.528 | C12: 46013.528 | D12: 158 | E12: mua rofu , category: gift | G12: Gifts | H12: W | I12: W | J12: Discord | K12: ai | L12: FALSE | N12: Em mua rofu 158e, category: gift | O12: 2025-12
A13: SL-20251222-124149-164 | B13: 46013.529 | C13: 46013.529 | D13: 89 | E13: mua dehner , category: | G13: Home improvement | H13: W | I13: W | J13: Discord | K13: user | L13: TRUE | M13: 46013.529 | N13: Em mua dehner 89e, category: home improvement | O13: 2025-12
A14: SL-20251222-124245-908 | B14: 46013.53 | C14: 46013.53 | D14: 19.5 | E14: lidl | G14: Groceries + Food | H14: W | I14: W | J14: Discord | K14: ai | L14: FALSE | N14: lidl 19,5e | O14: 2025-12
A15: SL-20251222-165718-674 | B15: 46013.706 | C15: 46013.706 | D15: 14 | E15: Thuoc so mui AK | G15: Health & beauty | H15: H | I15: H | J15: Discord | K15: ai | L15: FALSE | N15: Thuoc so mui AK 14e | O15: 2025-12
A16: SL-20251222-224155-982 | B16: 46013.946 | C16: 46013.946 | D16: 22 | E16: Google subscription | G16: Business & Subscription | H16: H | I16: H | J16: Discord | K16: ai | L16: FALSE | N16: Google subscription 22e | O16: 2025-12
A17: SL-20251222-224202-002 | B17: 46013.946 | C17: 46013.946 | D17: 10 | E17: Apple subscription | G17: Business & Subscription | H17: H | I17: H | J17: Discord | K17: ai | L17: FALSE | N17: Apple subscription 10e | O17: 2025-12
A18: SL-20251223-072753-126 | B18: 46014.311 | C18: 46006.5 | D18: 913 | E18: Postillion | G18: Childcare | H18: H | I18: H | J18: Discord | K18: user | L18: TRUE | M18: 46014.311 | N18: 15.12 childcare 913€ | O18: 2025-12
A19: SL-20251223-073034-927 | B19: 46014.313 | C19: 45992.5 | D19: 327.95 | E19: Donation Phú Yên | F19: 10tr | G19: Donation | H19: H | I19: H | J19: Discord | K19: user | L19: TRUE | M19: 46014.313 | N19: 327,95 donation 01.12 | O19: 2025-12
A20: SL-20251223-073036-542 | B20: 46014.313 | C20: 45992.5 | D20: 229.57 | E20: Dú | F20: 7tr | G20: Family Support | H20: H | I20: H | J20: Discord | K20: user | L20: TRUE | M20: 46014.313 | N20: 229,57 family support 01.12 | O20: 2025-12
A21: SL-20251223-075424-422 | B21: 46014.329 | C21: 45992.5 | D21: 166.41 | E21: chó mèo vn | G21: Donation | H21: W | I21: H | J21: Discord | K21: user | L21: TRUE | M21: 46014.329 | N21: trang 01.12 donation chó mèo vn 166,41€ | O21: 2025-12
A22: SL-20251223-075427-802 | B22: 46014.329 | C22: 45992.5 | D22: 5 | E22: cafe mannheim | G22: Eat Out & Food delivery | H22: W | I22: H | J22: Discord | K22: ai | L22: FALSE | N22: trang 01.12 cafe mannheim 5€ | O22: 2025-12
A23: SL-20251223-075428-173 | B23: 46014.329 | C23: 45994.5 | D23: 12 | E23: disney+ | G23: Business & Subscription | H23: W | I23: H | J23: Discord | K23: user | L23: TRUE | M23: 46014.329 | N23: trang 03.12 disney+ business & subscription 12€ | O23: 2025-12
A24: SL-20251223-075430-713 | B24: 46014.33 | C24: 45996.5 | D24: 13 | E24: bread mannheim | G24: Eat Out & Food delivery | H24: W | I24: H | J24: Discord | K24: ai | L24: FALSE | N24: trang 05.12 bread mannheim 13€ | O24: 2025-12
A25: SL-20251223-075432-200 | B25: 46014.33 | C25: 45997.5 | D25: 3 | E25: cafe karlsruhe | G25: Eat Out & Food delivery | H25: W | I25: H | J25: Discord | K25: ai | L25: FALSE | N25: trang 06.12 cafe karlsruhe 3€ | O25: 2025-12
A26: SL-20251223-075433-591 | B26: 46014.33 | C26: 46006.5 | D26: 55 | E26: internet vodafone | G26: Utilities | H26: W | I26: H | J26: Discord | K26: user | L26: TRUE | M26: 46014.33 | N26: trang 15.12 utilities internet vodafone 55€ | O26: 2025-12
A27: SL-20251223-075434-765 | B27: 46014.33 | C27: 46007.5 | D27: 450 | E27: driving lessons | G27: Car | H27: W | I27: H | J27: Discord | K27: ai | L27: FALSE | N27: trang 16.12 driving lessons 450€ | O27: 2025-12
A28: SL-20251223-075435-821 | B28: 46014.33 | C28: 46007.5 | D28: 48.5 | E28: galeria mua quà maija | G28: Gifts | H28: W | I28: H | J28: Discord | K28: user | L28: TRUE | M28: 46014.33 | N28: trang 16.12 gifts galeria mua quà maija 48,5€ | O28: 2025-12
A29: SL-20251223-075437-175 | B29: 46014.33 | C29: 46008.5 | D29: 56 | E29: zalando áo tuyết AK | G29: Shopping | H29: W | I29: H | J29: Discord | K29: user | L29: TRUE | M29: 46014.33 | N29: trang 17.12 zalando shopping áo tuyết AK 56€ | O29: 2025-12
A30: SL-20251223-075438-869 | B30: 46014.33 | C30: 45992.5 | D30: 101.83 | E30: kaufland | G30: Groceries + Food | H30: W | I30: H | J30: Discord | K30: ai | L30: FALSE | N30: trang 01.12 kaufland 101,83€ | O30: 2025-12
A31: SL-20251223-075439-754 | B31: 46014.33 | C31: 45993.5 | D31: 47 | E31: rewe | G31: Groceries + Food | H31: W | I31: H | J31: Discord | K31: ai | L31: FALSE | N31: trang 02.12 rewe 47€ | O31: 2025-12
A32: SL-20251223-075441-692 | B32: 46014.33 | C32: 45993.5 | D32: 2137.76 | E32: flight ticket VN | G32: Special IO | H32: W | I32: H | J32: Discord | K32: user | L32: TRUE | M32: 46014.33 | N32: trang 02.12 special IO flight ticket VN 2137,76€ | O32: 2025-12
A33: SL-20251223-075443-091 | B33: 46014.33 | C33: 45993.5 | D33: 73 | E33: hotel singapore | G33: Special IO | H33: W | I33: H | J33: Discord | K33: user | L33: TRUE | M33: 46014.33 | N33: trang 02.12 special IO hotel singapore 73€ | O33: 2025-12
A34: SL-20251223-075444-768 | B34: 46014.33 | C34: 45996.5 | D34: 206 | E34: globus | G34: Groceries + Food | H34: W | I34: H | J34: Discord | K34: ai | L34: FALSE | N34: trang 05.12 globus 206€ | O34: 2025-12
A35: SL-20251223-075446-089 | B35: 46014.33 | C35: 45997.5 | D35: 15 | E35: karsruhe cafe | G35: Buffer | H35: W | I35: H | J35: Discord | K35: ai | L35: FALSE | N35: trang 06.12 karsruhe cafe 15€ | O35: 2025-12
A36: SL-20251223-075446-017 | B36: 46014.33 | C36: 45999.5 | D36: 40.7 | E36: vé tàu bé phúc | G36: Travel & Leisure | H36: W | I36: H | J36: Discord | K36: user | L36: TRUE | M36: 46014.33 | N36: trang 08.12 travel & leisure vé tàu bé phúc 40,7€ | O36: 2025-12
A37: SL-20251223-075447-667 | B37: 46014.33 | C37: 46002.5 | D37: 60 | E37: penny food | G37: Groceries + Food | H37: W | I37: H | J37: Discord | K37: ai | L37: FALSE | N37: trang 11.12 penny food 60€ | O37: 2025-12
A38: SL-20251223-075448-016 | B38: 46014.33 | C38: 46006.5 | D38: 12.36 | E38: lidl | G38: Groceries + Food | H38: W | I38: H | J38: Discord | K38: ai | L38: FALSE | N38: trang 15.12 lidl 12,36€ | O38: 2025-12
A39: SL-20251223-075449-043 | B39: 46014.33 | C39: 46007.5 | D39: 142.25 | E39: zalando bé đức + biuti | G39: Gifts | H39: W | I39: H | J39: Discord | K39: user | L39: TRUE | M39: 46014.33 | N39: trang 16.12 gifts zalando bé đức + biuti 142,25€ | O39: 2025-12
A40: SL-20251223-075637-500 | B40: 46014.331 | C40: 45992.5 | D40: 392 | E40: polestar | G40: Car | H40: H | I40: H | J40: Discord | K40: user | L40: TRUE | M40: 46014.331 | N40: car polestar 392€ 01.12 | O40: 2025-12
A41: SL-20251223-080915-738 | B41: 46014.34 | C41: 46007.5 | D41: 18 | E41: maija heidelberg | G41: Gifts | H41: H | I41: H | J41: Discord | K41: user | L41: TRUE | M41: 46014.34 | N41: gifts maija 18€ heidelberg 16.12 | O41: 2025-12
A42: SL-20251223-080917-154 | B42: 46014.34 | C42: 45996.5 | D42: 10 | E42: globus | G42: Groceries + Food | H42: H | I42: H | J42: Discord | K42: ai | L42: FALSE | N42: globus 10€ 05.12 | O42: 2025-12
A43: SL-20251223-080918-708 | B43: 46014.34 | C43: 46008.5 | D43: 27 | E43: maija sending package | G43: Gifts | H43: H | I43: H | J43: Discord | K43: user | L43: TRUE | M43: 46014.34 | N43: gifts maija 27€ sending package 17.12 | O43: 2025-12
A44: SL-20251223-080919-732 | B44: 46014.34 | C44: 45992.5 | D44: 24 | E44: amazon fisher düber | G44: Home improvement | H44: H | I44: H | J44: Discord | K44: user | L44: TRUE | M44: 46014.34 | N44: home improvement amazon fisher düber 24€ 01.12 | O44: 2025-12
A45: SL-20251223-080920-010 | B45: 46014.34 | C45: 45996.5 | D45: 35 | E45: chợ đồ cũ | G45: Shopping | H45: H | I45: H | J45: Discord | K45: user | L45: TRUE | M45: 46014.34 | N45: shopping chợ đồ cũ 05.12 35€ | O45: 2025-12
A46: SL-20251223-080921-101 | B46: 46014.34 | C46: 46006.5 | D46: 18 | E46: eat out kebab | G46: Eat Out & Food delivery | H46: H | I46: H | J46: Discord | K46: ai | L46: FALSE | N46: eat out kebab 18€ 15.12 | O46: 2025-12
A47: SL-20251223-080922-381 | B47: 46014.34 | C47: 46007.5 | D47: 40 | E47: phạt xe | G47: Car | H47: H | I47: H | J47: Discord | K47: user | L47: TRUE | M47: 46014.34 | N47: car phạt xe 40€ 16.12 | O47: 2025-12
A48: SL-20251223-080923-114 | B48: 46014.34 | C48: 45992.5 | D48: 4.74 | E48: google gcp | G48: Business & Subscription | H48: H | I48: H | J48: Discord | K48: user | L48: TRUE | M48: 46014.34 | N48: business & subscription google gcp 4,74€ 01.12 | O48: 2025-12
A49: SL-20251223-080924-966 | B49: 46014.34 | C49: 45993.5 | D49: 117 | E49: action | G49: Shopping | H49: H | I49: H | J49: Discord | K49: user | L49: TRUE | M49: 46014.34 | N49: shopping action 117€ 02.12 | O49: 2025-12
A50: SL-20251223-080926-865 | B50: 46014.34 | C50: 45993.5 | D50: 20 | E50: eat out xmas market speyer | G50: Buffer | H50: H | I50: H | J50: Discord | K50: ai | L50: FALSE | N50: eat out xmas market speyer 20€ 02.12 | O50: 2025-12
A51: SL-20251223-080926-032 | B51: 46014.34 | C51: 46004.5 | D51: 42 | E51: ikea | G51: Home improvement | H51: H | I51: H | J51: Discord | K51: user | L51: TRUE | M51: 46014.34 | N51: home improvement ikea 42€ 13.12 | O51: 2025-12
A52: SL-20251223-080928-125 | B52: 46014.34 | C52: 46007.5 | D52: 25.37 | E52: groceries | G52: Buffer | H52: H | I52: H | J52: Discord | K52: ai | L52: FALSE | N52: groceries 25,37e 16.12 | O52: 2025-12
A53: SL-20251223-080929-396 | B53: 46014.34 | C53: 45992.5 | D53: 12 | E53: obi | G53: Home improvement | H53: H | I53: H | J53: Discord | K53: user | L53: TRUE | M53: 46014.34 | N53: home improvement obi 12€ 1.12 | O53: 2025-12
A54: SL-20251223-080929-392 | B54: 46014.34 | C54: 46006.5 | D54: 94 | E54: dm | G54: Health & beauty | H54: H | I54: H | J54: Discord | K54: user | L54: TRUE | M54: 46014.34 | N54: health & beauty dm 94€ 15.12 | O54: 2025-12
A55: SL-20251223-080930-779 | B55: 46014.34 | C55: 45992.5 | D55: 134 | E55: groceries + food asian store | G55: Groceries + Food | H55: H | I55: H | J55: Discord | K55: user | L55: TRUE | M55: 46014.34 | N55: groceries + food asian store 134e 01.12 | O55: 2025-12
A56: SL-20251223-080931-149 | B56: 46014.34 | C56: 45998.5 | D56: 55 | E56: cây thông | G56: Home improvement | H56: H | I56: H | J56: Discord | K56: user | L56: TRUE | M56: 46014.34 | N56: home improvement 55e 07.12 | O56: 2025-12
A57: SL-20251223-080932-711 | B57: 46014.34 | C57: 45998.5 | D57: 5 | E57: eat out cafe schwetzingen | G57: Buffer | H57: H | I57: H | J57: Discord | K57: ai | L57: FALSE | N57: eat out cafe schwetzingen 5€ 7.12 | O57: 2025-12
A58: SL-20251223-080933-337 | B58: 46014.34 | C58: 45996.5 | D58: 7.7 | E58: gửi đồ nhím | G58: Gifts | H58: H | I58: H | J58: Discord | K58: user | L58: TRUE | M58: 46014.34 | N58: gifts gửi đồ nhím 7,7€ 5.12 | O58: 2025-12
A59: SL-20251223-080934-519 | B59: 46014.34 | C59: 45997.5 | D59: 71 | E59: eat out HD with Tobi Claire | G59: Eat Out & Food delivery | H59: H | I59: H | J59: Discord | K59: ai | L59: FALSE | N59: eat out HD with Tobi Claire 6.12 71€ | O59: 2025-12
A60: SL-20251223-080936-998 | B60: 46014.34 | C60: 45995.5 | D60: 15 | E60: eat out HD ICA team | G60: Eat Out & Food delivery | H60: H | I60: H | J60: Discord | K60: ai | L60: FALSE | N60: eat out HD ICA team 4.12 15€ | O60: 2025-12
A61: SL-20251223-080937-103 | B61: 46014.34 | C61: 45997.5 | D61: 28 | E61: ZKM | G61: Travel & Leisure | H61: H | I61: H | J61: Discord | K61: user | L61: TRUE | M61: 46014.34 | N61: travel & leisure ZKM 06.12 28€ | O61: 2025-12
A62: SL-20251223-080938-260 | B62: 46014.34 | C62: 45997.5 | D62: 12 | E62: eat out xmas market | G62: Eat Out & Food delivery | H62: H | I62: H | J62: Discord | K62: ai | L62: FALSE | N62: eat out xmas market 12€ 06.12 | O62: 2025-12
A63: SL-20251223-080939-737 | B63: 46014.34 | C63: 45997.5 | D63: 15 | E63: eat out cafe | G63: Eat Out & Food delivery | H63: H | I63: H | J63: Discord | K63: ai | L63: FALSE | N63: eat out cafe 15€ 06.12 | O63: 2025-12
A64: SL-20251223-080940-702 | B64: 46014.34 | C64: 45997.5 | D64: 54 | E64: sourvenirs zkm | G64: Shopping | H64: H | I64: H | J64: Discord | K64: user | L64: TRUE | M64: 46014.34 | N64: shopping sourvenirs zkm 54€ 06.12 | O64: 2025-12
A65: SL-20251223-113349-246 | B65: 46014.482 | C65: 46014.482 | D65: 150.7 | E65: Globus | G65: Groceries + Food | H65: H | I65: H | J65: Discord | K65: ai | L65: FALSE | N65: Globus 150,70e | O65: 2025-12
A66: SL-20251223-113410-353 | B66: 46014.482 | C66: 46014.482 | D66: 63.71 | E66: Groceries + food nam kinh | G66: Groceries + Food | H66: H | I66: H | J66: Discord | K66: user | L66: TRUE | M66: 46014.482 | N66: Groceries + food nam kinh 63,71€ | O66: 2025-12
A67: SL-20251223-132640-349 | B67: 46014.56 | C67: 46014.56 | D67: 158.6 | E67: Nancy train be phuc | G67: Travel & Leisure | H67: W | I67: W | J67: Discord | K67: ai | L67: FALSE | N67: Nancy train be phuc 158,6e | O67: 2025-12
A68: SL-20251223-132641-513 | B68: 46014.56 | C68: 46014.56 | D68: 40.5 | E68: Frankfurt train be phuc | G68: Travel & Leisure | H68: W | I68: W | J68: Discord | K68: ai | L68: FALSE | N68: Frankfurt train be phuc 40,5e | O68: 2025-12
A69: SL-20251223-132845-598 | B69: 46014.562 | C69: 46014.562 | D69: 145.21 | E69: Nancy foods and | G69: Shopping | H69: W | I69: W | J69: Discord | K69: user | L69: TRUE | M69: 46014.562 | N69: Nancy foods and shopping 145,21e | O69: 2025-12
A70: SL-20251223-133110-359 | B70: 46014.563 | C70: 46014.563 | D70: 50 | E70: Giay chi ba , category: | G70: Shopping | H70: W | I70: W | J70: Discord | K70: user | L70: TRUE | M70: 46014.563 | N70: Giay chi ba 50e, category: shopping | O70: 2025-12
A71: SL-20251227-112555-794 | B71: 46018.476 | C71: 46017.5 | D71: 2 | E71: Parking speyer | G71: Buffer | H71: H | I71: H | J71: Discord | K71: ai | L71: FALSE | N71: Parking yesterday speyer 2e | O71: 2025-12
A72: SL-20251227-112604-342 | B72: 46018.476 | C72: 46017.5 | D72: 8.5 | E72: Cake speyer | G72: Eat Out & Food delivery | H72: H | I72: H | J72: Discord | K72: ai | L72: FALSE | N72: Cake yesterday speyer 8,5e | O72: 2025-12
A73: SL-20251227-134206-129 | B73: 46018.571 | C73: 46018.571 | D73: 102 | E73: Lidl | G73: Groceries + Food | H73: W | I73: W | J73: Discord | K73: ai | L73: FALSE | N73: Lidl 102e | O73: 2025-12
A74: SL-20251227-134221-427 | B74: 46018.571 | C74: 46018.571 | D74: 15.5 | E74: Dm | G74: Health & beauty | H74: W | I74: W | J74: Discord | K74: ai | L74: FALSE | N74: Dm 15,5e | O74: 2025-12
A75: SL-20251227-134526-062 | B75: 46018.573 | C75: 46018.573 | D75: 123 | E75: Qua cho Gab & Annie , category gift | G75: Gifts | H75: W | I75: W | J75: Discord | K75: ai | L75: FALSE | N75: Qua cho Gab & Annie 123e, category gift | O75: 2025-12
A76: SL-20251227-134725-225 | B76: 46018.575 | C76: 46018.575 | D76: 35 | E76: Amazon kitchen rack | G76: Home improvement | H76: W | I76: W | J76: Discord | K76: ai | L76: FALSE | N76: Amazon kitchen rack 35e | O76: 2025-12

Sheet RSU_Schedule
A1: Month | B1: Year | C1: Date | D1: H_Backlog_Shares | E1: H_NewGrant_Shares | F1: H_Total_Shares | G1: H_Gross_EUR | H1: H_Net_EUR | I1: W_Backlog_Shares | J1: W_NewGrant_Shares | K1: W_Total_Shares | L1: W_Gross_EUR | M1: W_Net_EUR | N1: Combined_Net_EUR
A2: 1 | B2: 2026 | C2: 01/2026 | D2: 0 | E2: 0 | F2: 0 | G2: 0 | H2: 0 | I2: 0 | J2: 0 | K2: 0 | L2: 0 | M2: 0 | N2: 0
A3: 2 | B3: 2026 | C3: 02/2026 | D3: 0 | E3: 0 | F3: 0 | G3: 0 | H3: 0 | I3: 0 | J3: 0 | K3: 0 | L3: 0 | M3: 0 | N3: 0
A4: 3 | B4: 2026 | C4: 03/2026 | D4: 40.94 | E4: 0 | F4: 40.94 | G4: 8597.4 | H4: 4788.75 | I4: 20.47 | J4: 0 | K4: 20.47 | L4: 4298.7 | M4: 2394.38 | N4: 7183.13
A5: 4 | B5: 2026 | C5: 04/2026 | D5: 0 | E5: 0 | F5: 0 | G5: 0 | H5: 0 | I5: 0 | J5: 0 | K5: 0 | L5: 0 | M5: 0 | N5: 0
A6: 5 | B6: 2026 | C6: 05/2026 | D6: 0 | E6: 0 | F6: 0 | G6: 0 | H6: 0 | I6: 0 | J6: 0 | K6: 0 | L6: 0 | M6: 0 | N6: 0
A7: 6 | B7: 2026 | C7: 06/2026 | D7: 25.91 | E7: 0 | F7: 25.91 | G7: 5441.1 | H7: 3030.69 | I7: 12.955 | J7: 0 | K7: 12.955 | L7: 2720.55 | M7: 1515.35 | N7: 4546.04
A8: 7 | B8: 2026 | C8: 07/2026 | D8: 0 | E8: 0 | F8: 0 | G8: 0 | H8: 0 | I8: 0 | J8: 0 | K8: 0 | L8: 0 | M8: 0 | N8: 0
A9: 8 | B9: 2026 | C9: 08/2026 | D9: 0 | E9: 0 | F9: 0 | G9: 0 | H9: 0 | I9: 0 | J9: 0 | K9: 0 | L9: 0 | M9: 0 | N9: 0
A10: 9 | B10: 2026 | C10: 09/2026 | D10: 25.91 | E10: 7.9365 | F10: 33.8465 | G10: 7107.76 | H10: 3959.02 | I10: 12.955 | J10: 3.9683 | K10: 16.9233 | L10: 3553.89 | M10: 1979.52 | N10: 5938.54
A11: 10 | B11: 2026 | C11: 10/2026 | D11: 0 | E11: 0 | F11: 0 | G11: 0 | H11: 0 | I11: 0 | J11: 0 | K11: 0 | L11: 0 | M11: 0 | N11: 0
A12: 11 | B12: 2026 | C12: 11/2026 | D12: 0 | E12: 0 | F12: 0 | G12: 0 | H12: 0 | I12: 0 | J12: 0 | K12: 0 | L12: 0 | M12: 0 | N12: 0
A13: 12 | B13: 2026 | C13: 12/2026 | D13: 25.91 | E13: 7.9365 | F13: 33.8465 | G13: 7107.76 | H13: 3959.02 | I13: 12.955 | J13: 3.9683 | K13: 16.9233 | L13: 3553.89 | M13: 1979.52 | N13: 5938.54
... A205: 12 | B205: 2042 | C205: 12/2042 | D205: 0 | E205: 23.8095 | F205: 23.8095 | G205: 4999.99 | H205: 2784.99 | I205: 0 | J205: 11.9048 | K205: 11.9048 | L205: 2500.01 | M205: 1392.51 | N205: 4177.5

Sheet Salary_Schedule
A1: Year | B1: Month | C1: H_Salary_Modifier | D1: W_Salary_Modifier | E1: H_Fixed_Monthly | F1: H_Bonus | G1: W_Fixed_Monthly | H1: W_Bonus | I1: Notes
A2: 2026 | B2: 1 | C2: 0 | D2: 0 | E2: =7366.42*(1+C2) -> 7366.42 | F2: 0 | G2: =6195.67*(1+D2) -> 6195.67 | H2: 0
A3: 2026 | B3: 2 | C3: 0 | D3: 0 | E3: =7366.42*(1+C3) -> 7366.42 | F3: 0 | G3: =6195.67*(1+D3) -> 6195.67 | H3: 0
A4: 2026 | B4: 3 | C4: 0 | D4: 0 | E4: =7366.42*(1+C4) -> 7366.42 | F4: 0 | G4: =6195.67*(1+D4) -> 6195.67 | H4: 0
A5: 2026 | B5: 4 | C5: 0 | D5: 0 | E5: =7366.42*(1+C5) -> 7366.42 | F5: =9821*(1+C5) -> 9821 | G5: =6195.67*(1+D5) -> 6195.67 | H5: =8261*(1+D5) -> 8261
A6: 2026 | B6: 5 | C6: 0 | D6: 0 | E6: =7366.42*(1+C6) -> 7366.42 | F6: 0 | G6: =6195.67*(1+D6) -> 6195.67 | H6: 0
A7: 2026 | B7: 6 | C7: 0 | D7: 0 | E7: =7366.42*(1+C7) -> 7366.42 | F7: 0 | G7: =6195.67*(1+D7) -> 6195.67 | H7: 0
A8: 2026 | B8: 7 | C8: 0 | D8: 0 | E8: =7366.42*(1+C8) -> 7366.42 | F8: 0 | G8: =6195.67*(1+D8) -> 6195.67 | H8: 0
A9: 2026 | B9: 8 | C9: 0 | D9: 0 | E9: =7366.42*(1+C9) -> 7366.42 | F9: 0 | G9: =6195.67*(1+D9) -> 6195.67 | H9: 0
A10: 2026 | B10: 9 | C10: 0 | D10: 0 | E10: =7366.42*(1+C10) -> 7366.42 | F10: 0 | G10: =6195.67*(1+D10) -> 6195.67 | H10: 0
A11: 2026 | B11: 10 | C11: 0 | D11: 0 | E11: =7366.42*(1+C11) -> 7366.42 | F11: 0 | G11: =6195.67*(1+D11) -> 6195.67 | H11: 0
A12: 2026 | B12: 11 | C12: 0 | D12: 0 | E12: =7366.42*(1+C12) -> 7366.42 | F12: 0 | G12: =6195.67*(1+D12) -> 6195.67 | H12: 0
A13: 2026 | B13: 12 | C13: 0 | D13: 0 | E13: =7366.42*(1+C13) -> 7366.42 | F13: 0 | G13: =6195.67*(1+D13) -> 6195.67 | H13: 0
A14: 2027 | B14: 1 | C14: 0 | D14: 0 | E14: =7734.74*(1+C14) -> 7734.74 | F14: 0 | G14: =6412.51*(1+D14) -> 6412.51 | H14: 0
A15: 2027 | B15: 2 | C15: 0 | D15: 0 | E15: =7734.74*(1+C15) -> 7734.74 | F15: 0 | G15: =6412.51*(1+D15) -> 6412.51 | H15: 0
A16: 2027 | B16: 3 | C16: 0 | D16: 0 | E16: =7734.74*(1+C16) -> 7734.74 | F16: 0 | G16: =6412.51*(1+D16) -> 6412.51 | H16: 0
A17: 2027 | B17: 4 | C17: 0 | D17: 0 | E17: =7734.74*(1+C17) -> 7734.74 | F17: =10312.05*(1+C17) -> 10312.05 | G17: =6412.51*(1+D17) -> 6412.51 | H17: =8550.14*(1+D17) -> 8550.14
A18: 2027 | B18: 5 | C18: 0 | D18: 0 | E18: =7734.74*(1+C18) -> 7734.74 | F18: 0 | G18: =6412.51*(1+D18) -> 6412.51 | H18: 0
A19: 2027 | B19: 6 | C19: 0 | D19: 0 | E19: =7734.74*(1+C19) -> 7734.74 | F19: 0 | G19: =6412.51*(1+D19) -> 6412.51 | H19: 0
A20: 2027 | B20: 7 | C20: 0 | D20: 0 | E20: =7734.74*(1+C20) -> 7734.74 | F20: 0 | G20: =6412.51*(1+D20) -> 6412.51 | H20: 0
A21: 2027 | B21: 8 | C21: 0 | D21: 0 | E21: =7734.74*(1+C21) -> 7734.74 | F21: 0 | G21: =6412.51*(1+D21) -> 6412.51 | H21: 0
A22: 2027 | B22: 9 | C22: 0 | D22: 0 | E22: =7734.74*(1+C22) -> 7734.74 | F22: 0 | G22: =6412.51*(1+D22) -> 6412.51 | H22: 0
A23: 2027 | B23: 10 | C23: 0 | D23: 0 | E23: =7734.74*(1+C23) -> 7734.74 | F23: 0 | G23: =6412.51*(1+D23) -> 6412.51 | H23: 0
A24: 2027 | B24: 11 | C24: 0 | D24: 0 | E24: =7734.74*(1+C24) -> 7734.74 | F24: 0 | G24: =6412.51*(1+D24) -> 6412.51 | H24: 0
A25: 2027 | B25: 12 | C25: 0 | D25: 0 | E25: =7734.74*(1+C25) -> 7734.74 | F25: 0 | G25: =6412.51*(1+D25) -> 6412.51 | H25: 0
A26: 2028 | B26: 1 | C26: 0 | D26: 0 | E26: =8121.47*(1+C26) -> 8121.47 | F26: 0 | G26: =6636.95*(1+D26) -> 6636.95 | H26: 0
A27: 2028 | B27: 2 | C27: 0 | D27: 0 | E27: =8121.47*(1+C27) -> 8121.47 | F27: 0 | G27: =6636.95*(1+D27) -> 6636.95 | H27: 0
A28: 2028 | B28: 3 | C28: 0 | D28: 0 | E28: =8121.47*(1+C28) -> 8121.47 | F28: 0 | G28: =6636.95*(1+D28) -> 6636.95 | H28: 0
A29: 2028 | B29: 4 | C29: 0 | D29: 0 | E29: =8121.47*(1+C29) -> 8121.47 | F29: =10827.65*(1+C29) -> 10827.65 | G29: =6636.95*(1+D29) -> 6636.95 | H29: =8849.39*(1+D29) -> 8849.39
A30: 2028 | B30: 5 | C30: 0 | D30: 0 | E30: =8121.47*(1+C30) -> 8121.47 | F30: 0 | G30: =6636.95*(1+D30) -> 6636.95 | H30: 0
A31: 2028 | B31: 6 | C31: 0 | D31: 0 | E31: =8121.47*(1+C31) -> 8121.47 | F31: 0 | G31: =6636.95*(1+D31) -> 6636.95 | H31: 0
A32: 2028 | B32: 7 | C32: 0 | D32: 0 | E32: =8121.47*(1+C32) -> 8121.47 | F32: 0 | G32: =6636.95*(1+D32) -> 6636.95 | H32: 0
A33: 2028 | B33: 8 | C33: 0 | D33: 0 | E33: =8121.47*(1+C33) -> 8121.47 | F33: 0 | G33: =6636.95*(1+D33) -> 6636.95 | H33: 0
A34: 2028 | B34: 9 | C34: 0 | D34: 0 | E34: =8121.47*(1+C34) -> 8121.47 | F34: 0 | G34: =6636.95*(1+D34) -> 6636.95 | H34: 0
A35: 2028 | B35: 10 | C35: 0 | D35: 0 | E35: =8121.47*(1+C35) -> 8121.47 | F35: 0 | G35: =6636.95*(1+D35) -> 6636.95 | H35: 0
A36: 2028 | B36: 11 | C36: 0 | D36: 0 | E36: =8121.47*(1+C36) -> 8121.47 | F36: 0 | G36: =6636.95*(1+D36) -> 6636.95 | H36: 0
A37: 2028 | B37: 12 | C37: 0 | D37: 0 | E37: =8121.47*(1+C37) -> 8121.47 | F37: 0 | G37: =6636.95*(1+D37) -> 6636.95 | H37: 0
A38: 2029 | B38: 1 | C38: 0 | D38: 0 | E38: =8527.55*(1+C38) -> 8527.55 | F38: 0 | G38: =6869.25*(1+D38) -> 6869.25 | H38: 0
A39: 2029 | B39: 2 | C39: 0 | D39: 0 | E39: =8527.55*(1+C39) -> 8527.55 | F39: 0 | G39: =6869.25*(1+D39) -> 6869.25 | H39: 0
A40: 2029 | B40: 3 | C40: 0 | D40: 0 | E40: =8527.55*(1+C40) -> 8527.55 | F40: 0 | G40: =6869.25*(1+D40) -> 6869.25 | H40: 0
A41: 2029 | B41: 4 | C41: 0 | D41: 0 | E41: =8527.55*(1+C41) -> 8527.55 | F41: =11369.04*(1+C41) -> 11369.04 | G41: =6869.25*(1+D41) -> 6869.25 | H41: =9159.12*(1+D41) -> 9159.12
A42: 2029 | B42: 5 | C42: 0 | D42: 0 | E42: =8527.55*(1+C42) -> 8527.55 | F42: 0 | G42: =6869.25*(1+D42) -> 6869.25 | H42: 0
A43: 2029 | B43: 6 | C43: 0 | D43: 0 | E43: =8527.55*(1+C43) -> 8527.55 | F43: 0 | G43: =6869.25*(1+D43) -> 6869.25 | H43: 0
A44: 2029 | B44: 7 | C44: 0 | D44: 0 | E44: =8527.55*(1+C44) -> 8527.55 | F44: 0 | G44: =6869.25*(1+D44) -> 6869.25 | H44: 0
A45: 2029 | B45: 8 | C45: 0 | D45: 0 | E45: =8527.55*(1+C45) -> 8527.55 | F45: 0 | G45: =6869.25*(1+D45) -> 6869.25 | H45: 0
A46: 2029 | B46: 9 | C46: 0 | D46: 0 | E46: =8527.55*(1+C46) -> 8527.55 | F46: 0 | G46: =6869.25*(1+D46) -> 6869.25 | H46: 0
A47: 2029 | B47: 10 | C47: 0 | D47: 0 | E47: =8527.55*(1+C47) -> 8527.55 | F47: 0 | G47: =6869.25*(1+D47) -> 6869.25 | H47: 0
A48: 2029 | B48: 11 | C48: 0 | D48: 0 | E48: =8527.55*(1+C48) -> 8527.55 | F48: 0 | G48: =6869.25*(1+D48) -> 6869.25 | H48: 0
A49: 2029 | B49: 12 | C49: 0 | D49: 0 | E49: =8527.55*(1+C49) -> 8527.55 | F49: 0 | G49: =6869.25*(1+D49) -> 6869.25 | H49: 0
A50: 2030 | B50: 1 | C50: 0 | D50: 0 | E50: =8953.93*(1+C50) -> 8953.93 | F50: 0 | G50: =7109.67*(1+D50) -> 7109.67 | H50: 0
A51: 2030 | B51: 2 | C51: 0 | D51: 0 | E51: =8953.93*(1+C51) -> 8953.93 | F51: 0 | G51: =7109.67*(1+D51) -> 7109.67 | H51: 0
A52: 2030 | B52: 3 | C52: 0 | D52: 0 | E52: =8953.93*(1+C52) -> 8953.93 | F52: 0 | G52: =7109.67*(1+D52) -> 7109.67 | H52: 0
A53: 2030 | B53: 4 | C53: 0 | D53: 0 | E53: =8953.93*(1+C53) -> 8953.93 | F53: =11937.49*(1+C53) -> 11937.49 | G53: =7109.67*(1+D53) -> 7109.67 | H53: =9479.69*(1+D53) -> 9479.69
A54: 2030 | B54: 5 | C54: 0 | D54: 0 | E54: =8953.93*(1+C54) -> 8953.93 | F54: 0 | G54: =7109.67*(1+D54) -> 7109.67 | H54: 0
A55: 2030 | B55: 6 | C55: 0 | D55: 0 | E55: =8953.93*(1+C55) -> 8953.93 | F55: 0 | G55: =7109.67*(1+D55) -> 7109.67 | H55: 0
A56: 2030 | B56: 7 | C56: 0 | D56: 0 | E56: =8953.93*(1+C56) -> 8953.93 | F56: 0 | G56: =7109.67*(1+D56) -> 7109.67 | H56: 0
A57: 2030 | B57: 8 | C57: 0 | D57: 0 | E57: =8953.93*(1+C57) -> 8953.93 | F57: 0 | G57: =7109.67*(1+D57) -> 7109.67 | H57: 0
A58: 2030 | B58: 9 | C58: 0 | D58: 0 | E58: =8953.93*(1+C58) -> 8953.93 | F58: 0 | G58: =7109.67*(1+D58) -> 7109.67 | H58: 0
A59: 2030 | B59: 10 | C59: 0 | D59: 0 | E59: =8953.93*(1+C59) -> 8953.93 | F59: 0 | G59: =7109.67*(1+D59) -> 7109.67 | H59: 0
A60: 2030 | B60: 11 | C60: 0 | D60: 0 | E60: =8953.93*(1+C60) -> 8953.93 | F60: 0 | G60: =7109.67*(1+D60) -> 7109.67 | H60: 0
A61: 2030 | B61: 12 | C61: 0 | D61: 0 | E61: =8953.93*(1+C61) -> 8953.93 | F61: 0 | G61: =7109.67*(1+D61) -> 7109.67 | H61: 0
A62: 2031 | B62: 1 | C62: 0 | D62: 0 | E62: =9401.62*(1+C62) -> 9401.62 | F62: 0 | G62: =7358.51*(1+D62) -> 7358.51 | H62: 0
A63: 2031 | B63: 2 | C63: 0 | D63: 0 | E63: =9401.62*(1+C63) -> 9401.62 | F63: 0 | G63: =7358.51*(1+D63) -> 7358.51 | H63: 0
A64: 2031 | B64: 3 | C64: 0 | D64: 0 | E64: =9401.62*(1+C64) -> 9401.62 | F64: 0 | G64: =7358.51*(1+D64) -> 7358.51 | H64: 0
A65: 2031 | B65: 4 | C65: 0 | D65: 0 | E65: =9401.62*(1+C65) -> 9401.62 | F65: =12534.36*(1+C65) -> 12534.36 | G65: =7358.51*(1+D65) -> 7358.51 | H65: =9811.48*(1+D65) -> 9811.48
A66: 2031 | B66: 5 | C66: 0 | D66: 0 | E66: =9401.62*(1+C66) -> 9401.62 | F66: 0 | G66: =7358.51*(1+D66) -> 7358.51 | H66: 0
A67: 2031 | B67: 6 | C67: 0 | D67: 0 | E67: =9401.62*(1+C67) -> 9401.62 | F67: 0 | G67: =7358.51*(1+D67) -> 7358.51 | H67: 0
A68: 2031 | B68: 7 | C68: 0 | D68: 0 | E68: =9401.62*(1+C68) -> 9401.62 | F68: 0 | G68: =7358.51*(1+D68) -> 7358.51 | H68: 0
A69: 2031 | B69: 8 | C69: 0 | D69: 0 | E69: =9401.62*(1+C69) -> 9401.62 | F69: 0 | G69: =7358.51*(1+D69) -> 7358.51 | H69: 0
A70: 2031 | B70: 9 | C70: 0 | D70: 0 | E70: =9401.62*(1+C70) -> 9401.62 | F70: 0 | G70: =7358.51*(1+D70) -> 7358.51 | H70: 0
A71: 2031 | B71: 10 | C71: 0 | D71: 0 | E71: =9401.62*(1+C71) -> 9401.62 | F71: 0 | G71: =7358.51*(1+D71) -> 7358.51 | H71: 0
A72: 2031 | B72: 11 | C72: 0 | D72: 0 | E72: =9401.62*(1+C72) -> 9401.62 | F72: 0 | G72: =7358.51*(1+D72) -> 7358.51 | H72: 0
A73: 2031 | B73: 12 | C73: 0 | D73: 0 | E73: =9401.62*(1+C73) -> 9401.62 | F73: 0 | G73: =7358.51*(1+D73) -> 7358.51 | H73: 0
A74: 2032 | B74: 1 | C74: 0 | D74: 0 | E74: =9871.7*(1+C74) -> 9871.7 | F74: 0 | G74: =7616.06*(1+D74) -> 7616.06 | H74: 0
A75: 2032 | B75: 2 | C75: 0 | D75: 0 | E75: =9871.7*(1+C75) -> 9871.7 | F75: 0 | G75: =7616.06*(1+D75) -> 7616.06 | H75: 0
A76: 2032 | B76: 3 | C76: 0 | D76: 0 | E76: =9871.7*(1+C76) -> 9871.7 | F76: 0 | G76: =7616.06*(1+D76) -> 7616.06 | H76: 0
A77: 2032 | B77: 4 | C77: 0 | D77: 0 | E77: =9871.7*(1+C77) -> 9871.7 | F77: =13161.08*(1+C77) -> 13161.08 | G77: =7616.06*(1+D77) -> 7616.06 | H77: =10154.88*(1+D77) -> 10154.88
A78: 2032 | B78: 5 | C78: 0 | D78: 0 | E78: =9871.7*(1+C78) -> 9871.7 | F78: 0 | G78: =7616.06*(1+D78) -> 7616.06 | H78: 0
A79: 2032 | B79: 6 | C79: 0 | D79: 0 | E79: =9871.7*(1+C79) -> 9871.7 | F79: 0 | G79: =7616.06*(1+D79) -> 7616.06 | H79: 0
A80: 2032 | B80: 7 | C80: 0 | D80: 0 | E80: =9871.7*(1+C80) -> 9871.7 | F80: 0 | G80: =7616.06*(1+D80) -> 7616.06 | H80: 0
A81: 2032 | B81: 8 | C81: 0 | D81: 0 | E81: =9871.7*(1+C81) -> 9871.7 | F81: 0 | G81: =7616.06*(1+D81) -> 7616.06 | H81: 0
A82: 2032 | B82: 9 | C82: 0 | D82: 0 | E82: =9871.7*(1+C82) -> 9871.7 | F82: 0 | G82: =7616.06*(1+D82) -> 7616.06 | H82: 0
A83: 2032 | B83: 10 | C83: 0 | D83: 0 | E83: =9871.7*(1+C83) -> 9871.7 | F83: 0 | G83: =7616.06*(1+D83) -> 7616.06 | H83: 0
A84: 2032 | B84: 11 | C84: 0 | D84: 0 | E84: =9871.7*(1+C84) -> 9871.7 | F84: 0 | G84: =7616.06*(1+D84) -> 7616.06 | H84: 0
A85: 2032 | B85: 12 | C85: 0 | D85: 0 | E85: =9871.7*(1+C85) -> 9871.7 | F85: 0 | G85: =7616.06*(1+D85) -> 7616.06 | H85: 0
A86: 2033 | B86: 1 | C86: 0 | D86: 0 | E86: =10365.29*(1+C86) -> 10365.29 | F86: 0 | G86: =7882.62*(1+D86) -> 7882.62 | H86: 0
A87: 2033 | B87: 2 | C87: 0 | D87: 0 | E87: =10365.29*(1+C87) -> 10365.29 | F87: 0 | G87: =7882.62*(1+D87) -> 7882.62 | H87: 0
A88: 2033 | B88: 3 | C88: 0 | D88: 0 | E88: =10365.29*(1+C88) -> 10365.29 | F88: 0 | G88: =7882.62*(1+D88) -> 7882.62 | H88: 0
A89: 2033 | B89: 4 | C89: 0 | D89: 0 | E89: =10365.29*(1+C89) -> 10365.29 | F89: =13819.13*(1+C89) -> 13819.13 | G89: =7882.62*(1+D89) -> 7882.62 | H89: =10510.3*(1+D89) -> 10510.3
A90: 2033 | B90: 5 | C90: 0 | D90: 0 | E90: =10365.29*(1+C90) -> 10365.29 | F90: 0 | G90: =7882.62*(1+D90) -> 7882.62 | H90: 0
A91: 2033 | B91: 6 | C91: 0 | D91: 0 | E91: =10365.29*(1+C91) -> 10365.29 | F91: 0 | G91: =7882.62*(1+D91) -> 7882.62 | H91: 0
A92: 2033 | B92: 7 | C92: 0 | D92: 0 | E92: =10365.29*(1+C92) -> 10365.29 | F92: 0 | G92: =7882.62*(1+D92) -> 7882.62 | H92: 0
A93: 2033 | B93: 8 | C93: 0 | D93: 0 | E93: =10365.29*(1+C93) -> 10365.29 | F93: 0 | G93: =7882.62*(1+D93) -> 7882.62 | H93: 0
A94: 2033 | B94: 9 | C94: 0 | D94: 0 | E94: =10365.29*(1+C94) -> 10365.29 | F94: 0 | G94: =7882.62*(1+D94) -> 7882.62 | H94: 0
A95: 2033 | B95: 10 | C95: 0 | D95: 0 | E95: =10365.29*(1+C95) -> 10365.29 | F95: 0 | G95: =7882.62*(1+D95) -> 7882.62 | H95: 0
A96: 2033 | B96: 11 | C96: 0 | D96: 0 | E96: =10365.29*(1+C96) -> 10365.29 | F96: 0 | G96: =7882.62*(1+D96) -> 7882.62 | H96: 0
A97: 2033 | B97: 12 | C97: 0 | D97: 0 | E97: =10365.29*(1+C97) -> 10365.29 | F97: 0 | G97: =7882.62*(1+D97) -> 7882.62 | H97: 0
A98: 2034 | B98: 1 | C98: 0 | D98: 0 | E98: =10883.55*(1+C98) -> 10883.55 | F98: 0 | G98: =8158.51*(1+D98) -> 8158.51 | H98: 0
A99: 2034 | B99: 2 | C99: 0 | D99: 0 | E99: =10883.55*(1+C99) -> 10883.55 | F99: 0 | G99: =8158.51*(1+D99) -> 8158.51 | H99: 0
A100: 2034 | B100: 3 | C100: 0 | D100: 0 | E100: =10883.55*(1+C100) -> 10883.55 | F100: 0 | G100: =8158.51*(1+D100) -> 8158.51 | H100: 0
...

Sheet Debt_Register
A1: Debt_Name | B1: Owner | C1: Starting_Balance | D1: APR | E1: Min_Payment | F1: Payment_Type | G1: End_Date | H1: Attack_Priority
A2: TF Credit Card | B2: H | C2: 9200 | D2: 0.22 | E2: 300 | F2: Attack | G2: ASAP | H2: 1
A3: DB Overdraft | B3: H | C3: 2000 | D3: 0.13 | E3: 0 | F3: Attack | G3: Plan | H3: 2
A4: Revolut Loan | B4: H | C4: 12350 | D4: 0.0595 | E4: 650 | F4: Fixed | G4: Aug 2027
A5: C3 Family Loan | B5: H | C5: 10000 | D5: 0 | E5: 290 | F5: Fixed | G5: ~2028
A6: Scalable Credit | B6: H | C6: 5500 | D6: 0.033 | E6: 0 | F6: Low | G6: -
A7: Klarna | B7: W | C7: 2000 | D7: 0.14 | E7: 200 | F7: Attack | G7: Plan | H7: 3
A8: Nordea Card | B8: W | C8: 2000 | D8: 0.13 | E8: 100 | F8: Attack | G8: Plan | H8: 4
A9: Aktia Card | B9: W | C9: 440 | D9: 0.13 | E9: 30 | F9: Attack | G9: Plan | H9: 5
A10: Student Loan | B10: W | C10: 11000 | D10: 0.032 | E10: 200 | F10: Fixed | G10: ~2030
A11: IKEA Card | B11: W | C11: 2500 | D11: 0 | E11: 132 | F11: Fixed | G11: Jul 2027
A12: N26 Overdraft | B12: W | C12: 360 | D12: 0 | E12: 90 | F12: Fixed | G12: Apr 2026
A13: SAP Loan | B13: H+W | C13: 52500 | D13: 0 | E13: 583.33 | F13: Fixed | G13: Jun 2033
A14: AK Payback (Son) | B14: H+W | C14: 5000 | D14: 0 | E14: 0 | F14: Future | G14: TBD
A15: SUMMARY
A16: Total High-APR (>10%) | B16: =SUMIF(D2:D12,">0.1",C2:C12) -> 15640
A17: Total Fixed Payment | B17: =SUMIF(F2:F12,"Fixed",C2:C12) -> 36210
A18: Total Low Priority | B18: =SUMIF(F2:F12,"Low",C2:C12) -> 5500
A19: Monthly Minimums | B19: =SUM(E2:E12) -> 1992
A20: TOTAL DEBT | B20: =SUM(C2:C13) -> 109850

Sheet Monthly_Model_v4
A1: Month | B1: Year | C1: Date | D1: Income_From | E1: Month_Type | F1: H_Gross_Salary | G1: H_TA_Ded | H1: H_OWNSAP_Ded | I1: H_Gross_Bonus | J1: H_Bonus_TA | K1: H_Taxable | L1: H_Net_Salary | M1: H_RSU_Net | N1: W_Gross_Salary | O1: W_TA_Ded | P1: W_OWNSAP_Ded | Q1: W_Gross_Bonus | R1: W_Bonus_TA | S1: W_Taxable | T1: W_Net_Salary | U1: W_RSU_Net | V1: H_OWNSAP_Val | W1: W_OWNSAP_Val | X1: OWNSAP_Total | Y1: H_SAP_TaxedAdv | Z1: H_SAPLoan_Pmt | AA1: H_SAPLoan_Bal | AB1: W_SAP_TaxedAdv | AC1: W_SAPLoan_Pmt | AD1: W_SAPLoan_Bal | AE1: SAP_Loan_Pmt | AF1: SAP_Loan_Bal | AG1: YT_Gross | AH1: YT_Tax_Res | AI1: YT_Net | AJ1: Other_Fam_Net_Inc | AK1: CMP_Carry | AL1: CMP_Inflow | AM1: CMP_Available | AN1: CMP_End | AO1: Mort_Begin | AP1: Mort_Pmt | AQ1: Mort_Int | AR1: Mort_Princ | AS1: Sondertilg | AT1: Mort_End | AU1: D_TF_Pmt | AV1: D_TF_Bal | AW1: D_Klarna_Pmt | AX1: D_Klarna_Bal | AY1: D_Nordea_Pmt | AZ1: D_Nordea_Bal | BA1: D_DB_Pmt | BB1: D_DB_Bal | BC1: D_Aktia_Pmt | BD1: D_Aktia_Bal | BE1: D_HighAPR_Total | BF1: D_Scalable_Pmt | BG1: D_Scalable_Bal | BH1: D_AK_Pmt | BI1: D_AK_Bal | BJ1: D_Revolut_Pmt | BK1: D_C3_Pmt | BL1: D_Student_Pmt | BM1: D_IKEA_Pmt | BN1: D_N26_Pmt | BO1: D_Fixed_Total | BP1: Exp_Budget | BQ1: Exp_Alloc | BR1: Inv_Begin | BS1: Inv_OWNSAP | BT1: Inv_Excess | BU1: Inv_Growth | BV1: Inv_End | BW1: Cash_Begin | BX1: Cash_Add | BY1: Cash_End | BZ1: TaxRes_Beg | CA1: TaxRes_Add | CB1: TaxRes_End | CC1: H_TA_Hrs | CD1: W_TA_Hrs | CE1: NW_Invest | CF1: NW_House | CG1: NW_Mortgage | CH1: NW_Debt | CI1: NW_TA | CJ1: NW_Total
A2: 1 | B2: 2026 | C2: 01/2026 | D2: 12/2025 | E2: =IF(I2>0,"FAT_BONUS",IF(M2+U2>0,"FAT_RSU","LEAN")) -> LEAN | F2: =Salary_Schedule!E2 -> 7366.42 | G2: =Assumptions!$B$8 -> 200 | H2: =F2*Assumptions!$B$58 -> 736.642 | I2: =Salary_Schedule!F2 -> 0 | J2: =I2*Assumptions!$B$9 -> 0 | K2: =F2-G2-H2+I2-J2 -> 6429.778 | L2: =IF(COUNTIFS(SL_Income_Log!$B:$B,TEXT(B2,"0000")&"-"&TEXT(A2,"00"),SL_Income_Log!$C:$C,"salary",SL_Income_Log!$E:$E,"H")>0,SUMIFS(SL_Income_Log!$D:$D,SL_Income_Log!$B:$B,TEXT(B2,"0000")&"-"&TEXT(A2,"00"),SL_Income_Log!$C:$C,"salary",SL_Income_Log!$E:$E,"H"),K2*(1-Assumptions!$B$102)-Z2-Y2) -> 3487.4468 | M2: =0 -> 0 | N2: =Salary_Schedule!G2 -> 6195.67 | O2: =Assumptions!$B$19 -> 200 | P2: =N2*Assumptions!$B$59 -> 619.567 | Q2: =Salary_Schedule!H2 -> 0 | R2: =Q2*Assumptions!$B$20 -> 0 | S2: =N2-O2-P2+Q2-R2 -> 5376.103 | T2: =IF(COUNTIFS(SL_Income_Log!$B:$B,TEXT(B2,"0000")&"-"&TEXT(A2,"00"),SL_Income_Log!$C:$C,"salary",SL_Income_Log!$E:$E,"W")>0,SUMIFS(SL_Income_Log!$D:$D,SL_Income_Log!$B:$B,TEXT(B2,"0000")&"-"&TEXT(A2,"00"),SL_Income_Log!$C:$C,"salary",SL_Income_Log!$E:$E,"W"),S2*(1-Assumptions!$B$102)-AC2-AB2) -> 2855.2418 | U2: =0 -> 0 | V2: =H2*(1+Assumptions!$B$60)+Assumptions!$B$61 -> 1051.2988 | W2: =P2*(1+Assumptions!$B$60)+Assumptions!$B$61 -> 887.3938 | X2: =V2+W2 -> 1938.6926 | Y2: 78.75 | Z2: 291.67 | AA2: =26250-Z2 -> 25958.33 | AB2: 78.75 | AC2: 291.67 | AD2: =26250-AC2 -> 25958.33 | AE2: =Z2+AC2 -> 583.34 | AF2: =AA2+AD2 -> 51916.66 | AG2: =IF(COUNTIFS(SL_Income_Log!$B:$B,TEXT(B2,"0000")&"-"&TEXT(A2,"00"),SL_Income_Log!$C:$C,"youtube")>0,SUMIFS(SL_Income_Log!$D:$D,SL_Income_Log!$B:$B,TEXT(B2,"0000")&"-"&TEXT(A2,"00"),SL_Income_Log!$C:$C,"youtube"),MIN(Assumptions!$B$49+FLOOR((ROW()-2)/6,1)*Assumptions!$B$50,Assumptions!$B$51)) -> 1000 | AH2: =AG2*Assumptions!$B$104 -> 443 | AI2: =AG2-AH2 -> 557 | AJ2: =SUMIFS(SL_Income_Log!$D:$D,SL_Income_Log!$B:$B,TEXT(B2,"0000")&"-"&TEXT(A2,"00"),SL_Income_Log!$C:$C,"other") -> 0 | AK2: =0 -> 0 | AL2: =L2+M2+T2+U2+AI2+AJ2+IF((Debt_Register!$C$2+Debt_Register!$C$6+Debt_Register!$C$7+Debt_Register!$C$8+Debt_Register!$C$9)>5,X2,0) -> 8838.3812 | AM2: =AK2+AL2 -> 8838.3812 | AN2: =MAX(Assumptions!$B$94,MIN(Assumptions!$B$93,AM2-AP2-BE2-BO2-BQ2-Y2-Z2-AB2-AC2)) -> -740.84 | AO2: =Assumptions!$B$37-Assumptions!$B$38 -> 397546 | AP2: =IF(AO2>0,Assumptions!$B$33,0) -> 2281 | AQ2: =AO2*Assumptions!$B$32/12 -> 1288.7116 | AR2: =AP2-AQ2 -> 992.28838 | AS2: 0 | AT2: =MAX(0,AO2-AR2-AS2) -> 396553.71 | AU2: =IF(Debt_Register!$C$2>0,MIN(Debt_Register!$C$2,MAX(300,AM2-AP2-BO2-BQ2-AW2-AY2-BA2-BC2)),0) -> 585.3812 | AV2: =MAX(0,Debt_Register!$C$2-AU2) -> 8614.6188 | AW2: =IF(Debt_Register!$C$7>0,MIN(250,Debt_Register!$C$7),0) -> 250 | AX2: =MAX(0,Debt_Register!$C$7-AW2) -> 1750 | AY2: =IF(Debt_Register!$C$8>0,MIN(200,Debt_Register!$C$8),0) -> 200 | AZ2: =MAX(0,Debt_Register!$C$8-AY2) -> 1800 | BA2: =IF(AND(Debt_Register!$C$2<5,Debt_Register!$C$6>0),MIN(Debt_Register!$C$6,MAX(0,AM2-AP2-BO2-BQ2-AW2-AY2-BC2)),0) -> 0 | BB2: =MAX(0,Debt_Register!$C$6-BA2) -> 5500 | BC2: =IF(Debt_Register!$C$9>0,MIN(50,Debt_Register!$C$9),0) -> 50 | BD2: =MAX(0,Debt_Register!$C$9-BC2) -> 390 | BE2: =AU2+AW2+AY2+BA2+BC2 -> 1085.3812 | BF2: 0 | BG2: 5500 | BH2: 0 | BI2: 5000 | BJ2: =IF(OR(B2<Assumptions!$B$111,AND(B2=Assumptions!$B$111,A2<=Assumptions!$B$112)),Assumptions!$B$110,0) -> 650 | BK2: =MIN(Assumptions!$B$116+IF(OR(A2=4,A2=10),Assumptions!$B$117,0),10000) -> 290 | BL2: =IF(OR(B2<2030,AND(B2=2030,A2<8)),Assumptions!$B$118,IF(AND(B2=2030,A2=8),MOD(11000,200),0)) -> 200 | BM2: =IF(OR(B2<Assumptions!$B$120,AND(B2=Assumptions!$B$120,A2<=Assumptions!$B$121)),Assumptions!$B$119,0) -> 132 | BN2: =IF(AND(B2<=Assumptions!$B$123,A2<=Assumptions!$B$124),Assumptions!$B$122,0) -> 90 | BO2: =BF2+BH2+BJ2+BK2+BL2+BM2+BN2 -> 1362 | BP2: =SUMIFS(SL_Budget!$B:$B,SL_Budget!$C:$C,"'"&TEXT(DATE(B2,A2,1),"YYYY-MM")) -> 4110 | BQ2: =MAX(BP2, IFERROR(SUMIFS(ShadowLedger!D:D, ShadowLedger!C:C, ">="&DATE(B2,A2,1), ShadowLedger!C:C, "<"&EOMONTH(DATE(B2,A2,1),0)+1), 0)) -> 4110 | BR2: =Assumptions!$B$41 -> 12000 | BS2: =IF(Debt_Register!$C$2+Debt_Register!$C$7+Debt_Register!$C$8+Debt_Register!$C$3+Debt_Register!$C$9>5,0,X2) -> 0 | BT2: 0 | BU2: =(BR2+BS2+MAX(0,BT2))*(Assumptions!$B$43-1) -> 81.816 | BV2: =BR2+BS2+BT2+BU2 -> 12081.816 | BW2: =0 -> 0 | BX2: 0 | BY2: =BW2+BX2 -> 0 | BZ2: 0 | CA2: =AH2 -> 443 | CB2: =BZ2+CA2 -> 443 | CC2: =Assumptions!$B$24+(G2+J2)/(Salary_Schedule!E2*12/208) -> 1700.4706 | CD2: =Assumptions!$B$25+(O2+R2)/(Salary_Schedule!G2*12/208) -> 20.559531 | CE2: =BV2 -> 12081.816 | CF2: =Assumptions!$B$55*(1+Assumptions!$B$56)^((B2-2025)+(A2-1)/12) -> 527800 | CG2: =-AT2 -> -396553.71 | CH2: =-(AV2+AX2+BB2+AZ2+BD2+AF2+BG2+BI2) -> -80471.279 | CI2: =CC2*(Salary_Schedule!E2/173.33)*(1-Assumptions!$B$28)+CD2*(Salary_Schedule!G2/173.33)*(1-Assumptions!$B$28) -> 47452.515 | CJ2: =CE2+CF2+CG2+CH2+CI2 -> 110309.34
A3: 2 | B3: 2026 | C3: 02/2026 | D3: =C2 -> 01/2026 | E3: =IF(I3>0,"FAT_BONUS",IF(M3+U3>0,"FAT_RSU","LEAN")) -> LEAN | F3: =Salary_Schedule!E3 -> 7366.42 | G3: =Assumptions!$B$8 -> 200 | H3: =F3*Assumptions!$B$58 -> 736.642 | I3: =Salary_Schedule!F3 -> 0 | J3: =I3*Assumptions!$B$9 -> 0 | K3: =F3-G3-H3+I3-J3 -> 6429.778 | L3: =IF(COUNTIFS(SL_Income_Log!$B:$B,TEXT(B3,"0000")&"-"&TEXT(A3,"00"),SL_Income_Log!$C:$C,"salary",SL_Income_Log!$E:$E,"H")>0,SUMIFS(SL_Income_Log!$D:$D,SL_Income_Log!$B:$B,TEXT(B3,"0000")&"-"&TEXT(A3,"00"),SL_Income_Log!$C:$C,"salary",SL_Income_Log!$E:$E,"H"),K3*(1-Assumptions!$B$102)-Z3-Y3) -> 3488.3268 | M3: =RSU_Schedule!H2 -> 0 | N3: =Salary_Schedule!G3 -> 6195.67 | O3: =Assumptions!$B$19 -> 200 | P3: =N3*Assumptions!$B$59 -> 619.567 | Q3: =Salary_Schedule!H3 -> 0 | R3: =Q3*Assumptions!$B$20 -> 0 | S3: =N3-O3-P3+Q3-R3 -> 5376.103 | T3: =IF(COUNTIFS(SL_Income_Log!$B:$B,TEXT(B3,"0000")&"-"&TEXT(A3,"00"),SL_Income_Log!$C:$C,"salary",SL_Income_Log!$E:$E,"W")>0,SUMIFS(SL_Income_Log!$D:$D,SL_Income_Log!$B:$B,TEXT(B3,"0000")&"-"&TEXT(A3,"00"),SL_Income_Log!$C:$C,"salary",SL_Income_Log!$E:$E,"W"),S3*(1-Assumptions!$B$102)-AC3-AB3) -> 2856.1218 | U3: =RSU_Schedule!M2 -> 0 | V3: =H3*(1+Assumptions!$B$60)+Assumptions!$B$61 -> 1051.2988 | W3: =P3*(1+Assumptions!$B$60)+Assumptions!$B$61 -> 887.3938 | X3: =V3+W3 -> 1938.6926 | Y3: =ROUND(AA2*0.003,2) -> 77.87 | Z3: 291.67 | AA3: =MAX(0,AA2-Z3) -> 25666.66 | AB3: =ROUND(AD2*0.003,2) -> 77.87 | AC3: 291.67 | AD3: =MAX(0,AD2-AC3) -> 25666.66 | AE3: =Z3+AC3 -> 583.34 | AF3: =AA3+AD3 -> 51333.32 | AG3: =IF(COUNTIFS(SL_Income_Log!$B:$B,TEXT(B3,"0000")&"-"&TEXT(A3,"00"),SL_Income_Log!$C:$C,"youtube")>0,SUMIFS(SL_Income_Log!$D:$D,SL_Income_Log!$B:$B,TEXT(B3,"0000")&"-"&TEXT(A3,"00"),SL_Income_Log!$C:$C,"youtube"),MIN(Assumptions!$B$49+FLOOR((ROW()-2)/6,1)*Assumptions!$B$50,Assumptions!$B$51)) -> 1000 | AH3: =AG3*Assumptions!$B$104 -> 443 | AI3: =AG3-AH3 -> 557 | AJ3: =SUMIFS(SL_Income_Log!$D:$D,SL_Income_Log!$B:$B,TEXT(B3,"0000")&"-"&TEXT(A3,"00"),SL_Income_Log!$C:$C,"other") -> 0 | AK3: =AN2 -> -740.84 | AL3: =L3+M3+T3+U3+AI3+AJ3-Y3-Z3-AB3-AC3+IF((Debt_Register!$C$2+Debt_Register!$C$6+Debt_Register!$C$7+Debt_Register!$C$8+Debt_Register!$C$9)>5,X3,0) -> 8101.0612 | AM3: =AK3+AL3 -> 7360.2212 | AN3: =MAX(Assumptions!$B$94,MIN(Assumptions!$B$93,AM3-AP3-BE3-BO3-BQ3)) -> -1000 | AO3: =AT2 -> 396553.71 | AP3: =IF(AO3>0,Assumptions!$B$33,0) -> 2281 | AQ3: =AO3*Assumptions!$B$32/12 -> 1285.4949 | AR3: =AP3-AQ3 -> 995.50505 | AS3: =IF(AND((AV2+AX2+AZ2+BB2+BD2)<5,AO3>0,SUMIF($B$2:B2,B3,$AS$2:AS2)=0,(MAX(0,AN3-10000)+MAX(0,BY2-5000)+MAX(0,BV2-20000))>=21550),21550,0) -> 0 | AT3: =MAX(0,AO3-AR3-AS3) -> 395558.21 | AU3: =IF(AV2>0,MIN(AV2,MAX(300,AM3-AP3-BO3-BQ3-AW3-AY3-BA3-BC3)),0) -> 300 | AV3: =MAX(0,AV2-AU3) -> 8314.6188 | AW3: =IF(AX2>0,MIN(250,AX2),0) -> 250 | AX3: =MAX(0,AX2-AW3) -> 1500 | AY3: =IF(AZ2>0,MIN(200,AZ2),0) -> 200 | AZ3: =MAX(0,AZ2-AY3) -> 1600 | BA3: =IF(AND(AV2<5,BB2>0),MIN(BB2,MAX(0,AM3-AP3-BO3-BQ3-AW3-AY3-BC3)),0) -> 0 | BB3: =MAX(0,BB2-BA3) -> 5500 | BC3: =IF(BD2>0,MIN(50,BD2),0) -> 50 | BD3: =MAX(0,BD2-BC3) -> 340 | BE3: =AU3+AW3+AY3+BA3+BC3 -> 800 | BF3: 0 | BG3: =MAX(0,BG2-BF3) -> 5500 | BH3: 0 | BI3: =MAX(0,BI2-BH3) -> 5000 | BJ3: =IF(OR(B3<Assumptions!$B$111,AND(B3=Assumptions!$B$111,A3<=Assumptions!$B$112)),Assumptions!$B$110,0) -> 650 | BK3: =IF(B3<2027,Assumptions!$B$116+IF(OR(A3=4,A3=10),Assumptions!$B$117,0),IF(AND(B3=2027,A3<=4),IF(A3=4,MIN(950,Assumptions!$B$116+Assumptions!$B$117),Assumptions!$B$116),0)) -> 290 | BL3: =IF(OR(B3<2030,AND(B3=2030,A3<8)),Assumptions!$B$118,IF(AND(B3=2030,A3=8),MOD(11000,200),0)) -> 200 | BM3: =IF(OR(B3<Assumptions!$B$120,AND(B3=Assumptions!$B$120,A3<=Assumptions!$B$121)),Assumptions!$B$119,0) -> 132 | BN3: =IF(AND(B3<=Assumptions!$B$123,A3<=Assumptions!$B$124),Assumptions!$B$122,0) -> 90 | BO3: =BF3+BH3+BJ3+BK3+BL3+BM3+BN3 -> 1362 | BP3: =SUMIFS(SL_Budget!$B:$B,SL_Budget!$C:$C,"'"&TEXT(DATE(B3,A3,1),"YYYY-MM")) -> 4110 | BQ3: =MAX(BP3, IFERROR(SUMIFS(ShadowLedger!D:D, ShadowLedger!C:C, ">="&DATE(B3,A3,1), ShadowLedger!C:C, "<"&EOMONTH(DATE(B3,A3,1),0)+1), 0)) -> 4110 | BR3: =BV2 -> 12081.816 | BS3: =IF((AV2+AX2+BB2+AZ2+BD2)>5,0,X3) -> 0 | BT3: =IF(AS3>0,-MAX(0,21550-MAX(0,MAX(0,(AM3-AP3-BE3-BO3-BQ3)-Assumptions!$B$93))-MIN(MAX(0,21550-MAX(0,MAX(0,(AM3-AP3-BE3-BO3-BQ3)-Assumptions!$B$93))),MAX(0,BY2-Assumptions!$B$91))),IF(BY2>=Assumptions!$B$92,MAX(0,(AM3-AP3-BE3-BO3-BQ3)-Assumptions!$B$93),MAX(0,(AM3-AP3-BE3-BO3-BQ3)-Assumptions!$B$93)*Assumptions!$B$99)) -> 0 | BU3: =(BR3+BS3+MAX(0,BT3))*(Assumptions!$B$43-1) -> 82.373821 | BV3: =BR3+BS3+BT3+BU3 -> 12164.19 | BW3: =BY2 -> 0 | BX3: =IF(AS3>0,-MIN(MAX(0,21550-MAX(0,MAX(0,(AM3-AP3-BE3-BO3-BQ3)-Assumptions!$B$93))),MAX(0,BY2-Assumptions!$B$91)),IF(BY2<Assumptions!$B$92,MAX(0,(AM3-AP3-BE3-BO3-BQ3)-Assumptions!$B$93)*Assumptions!$B$98,0)) -> 0 | BY3: =BW3+BX3 -> 0 | BZ3: =IF(A3=1,0,CB2) -> 443 | CA3: =AH3 -> 443 | CB3: =BZ3+CA3 -> 886 | CC3: =CC2+(G3+J3)/(Salary_Schedule!E3*12/208) -> 1700.9412 | CD3: =CD2+(O3+R3)/(Salary_Schedule!G3*12/208) -> 21.119061 | CE3: =BV3 -> 12164.19 | CF3: =Assumptions!$B$55*(1+Assumptions!$B$56)^((B3-2025)+(A3-1)/12) -> 528455.26 | CG3: =-AT3 -> -395558.21 | CH3: =-(AV3+AX3+BB3+AZ3+BD3+AF3+BG3+BI3) -> -79087.939 | CI3: =CC3*(Salary_Schedule!E3/173.33)*(1-Assumptions!$B$28)+CD3*(Salary_Schedule!G3/173.33)*(1-Assumptions!$B$28) -> 47478.516 | CJ3: =CE3+CF3+CG3+CH3+CI3 -> 113451.82
A4: 3 | B4: 2026 | C4: 03/2026 | D4: =C3 -> 02/2026 | E4: =IF(I4>0,"FAT_BONUS",IF(M4+U4>0,"FAT_RSU","LEAN")) -> LEAN | F4: =Salary_Schedule!E4 -> 7366.42 | G4: =Assumptions!$B$8 -> 200 | H4: =F4*Assumptions!$B$58 -> 736.642 | I4: =Salary_Schedule!F4 -> 0 | J4: =I4*Assumptions!$B$9 -> 0 | K4: =F4-G4-H4+I4-J4 -> 6429.778 | L4: =IF(COUNTIFS(SL_Income_Log!$B:$B,TEXT(B4,"0000")&"-"&TEXT(A4,"00"),SL_Income_Log!$C:$C,"salary",SL_Income_Log!$E:$E,"H")>0,SUMIFS(SL_Income_Log!$D:$D,SL_Income_Log!$B:$B,TEXT(B4,"0000")&"-"&TEXT(A4,"00"),SL_Income_Log!$C:$C,"salary",SL_Income_Log!$E:$E,"H"),K4*(1-Assumptions!$B$102)-Z4-Y4) -> 3489.1968 | M4: =RSU_Schedule!H3 -> 0 | N4: =Salary_Schedule!G4 -> 6195.67 | O4: =Assumptions!$B$19 -> 200 | P4: =N4*Assumptions!$B$59 -> 619.567 | Q4: =Salary_Schedule!H4 -> 0 | R4: =Q4*Assumptions!$B$20 -> 0 | S4: =N4-O4-P4+Q4-R4 -> 5376.103 | T4: =IF(COUNTIFS(SL_Income_Log!$B:$B,TEXT(B4,"0000")&"-"&TEXT(A4,"00"),SL_Income_Log!$C:$C,"salary",SL_Income_Log!$E:$E,"W")>0,SUMIFS(SL_Income_Log!$D:$D,SL_Income_Log!$B:$B,TEXT(B4,"0000")&"-"&TEXT(A4,"00"),SL_Income_Log!$C:$C,"salary",SL_Income_Log!$E:$E,"W"),S4*(1-Assumptions!$B$102)-AC4-AB4) -> 2856.9918 | U4: =RSU_Schedule!M3 -> 0 | V4: =H4*(1+Assumptions!$B$60)+Assumptions!$B$61 -> 1051.2988 | W4: =P4*(1+Assumptions!$B$60)+Assumptions!$B$61 -> 887.3938 | X4: =V4+W4 -> 1938.6926 | Y4: =ROUND(AA3*0.003,2) -> 77 | Z4: 291.67 | AA4: =MAX(0,AA3-Z4) -> 25374.99 | AB4: =ROUND(AD3*0.003,2) -> 77 | AC4: 291.67 | AD4: =MAX(0,AD3-AC4) -> 25374.99 | AE4: =Z4+AC4 -> 583.34 | AF4: =AA4+AD4 -> 50749.98 | AG4: =IF(COUNTIFS(SL_Income_Log!$B:$B,TEXT(B4,"0000")&"-"&TEXT(A4,"00"),SL_Income_Log!$C:$C,"youtube")>0,SUMIFS(SL_Income_Log!$D:$D,SL_Income_Log!$B:$B,TEXT(B4,"0000")&"-"&TEXT(A4,"00"),SL_Income_Log!$C:$C,"youtube"),MIN(Assumptions!$B$49+FLOOR((ROW()-2)/6,1)*Assumptions!$B$50,Assumptions!$B$51)) -> 1000 | AH4: =AG4*Assumptions!$B$104 -> 443 | AI4: =AG4-AH4 -> 557 | AJ4: =SUMIFS(SL_Income_Log!$D:$D,SL_Income_Log!$B:$B,TEXT(B4,"0000")&"-"&TEXT(A4,"00"),SL_Income_Log!$C:$C,"other") -> 0 | AK4: =AN3 -> -1000 | AL4: =L4+M4+T4+U4+AI4+AJ4-Y4-Z4-AB4-AC4+IF((Debt_Register!$C$2+Debt_Register!$C$6+Debt_Register!$C$7+Debt_Register!$C$8+Debt_Register!$C$9)>5,X4,0) -> 8104.5412 | AM4: =AK4+AL4 -> 7104.5412 | AN4: =MAX(Assumptions!$B$94,MIN(Assumptions!$B$93,AM4-AP4-BE4-BO4-BQ4)) -> -1000 | AO4: =AT3 -> 395558.21 | AP4: =IF(AO4>0,Assumptions!$B$33,0) -> 2281 | AQ4: =AO4*Assumptions!$B$32/12 -> 1282.2679 | AR4: =AP4-AQ4 -> 998.73215 | AS4: =IF(AND((AV3+AX3+AZ3+BB3+BD3)<5,AO4>0,SUMIF($B$2:B3,B4,$AS$2:AS3)=0,(MAX(0,AN4-10000)+MAX(0,BY3-5000)+MAX(0,BV3-20000))>=21550),21550,0) -> 0 | AT4: =MAX(0,AO4-AR4-AS4) -> 394559.47 | AU4: =IF(AV3>0,MIN(AV3,MAX(300,AM4-AP4-BO4-BQ4-AW4-AY4-BA4-BC4)),0) -> 300 | AV4: =MAX(0,AV3-AU4) -> 8014.6188 | AW4: =IF(AX3>0,MIN(250,AX3),0) -> 250 | AX4: =MAX(0,AX3-AW4) -> 1250 | AY4: =IF(AZ3>0,MIN(200,AZ3),0) -> 200 | AZ4: =MAX(0,AZ3-AY4) -> 1400 | BA4: =IF(AND(AV3<5,BB3>0),MIN(BB3,MAX(0,AM4-AP4-BO4-BQ4-AW4-AY4-BC4)),0) -> 0 | BB4: =MAX(0,BB3-BA4) -> 5500 | BC4: =IF(BD3>0,MIN(50,BD3),0) -> 50 | BD4: =MAX(0,BD3-BC4) -> 290 | BE4: =AU4+AW4+AY4+BA4+BC4 -> 800 | BF4: 0 | BG4: =MAX(0,BG3-BF4) -> 5500 | BH4: 0 | BI4: =MAX(0,BI3-BH4) -> 5000 | BJ4: =IF(OR(B4<Assumptions!$B$111,AND(B4=Assumptions!$B$111,A4<=Assumptions!$B$112)),Assumptions!$B$110,0) -> 650 | BK4: =IF(B4<2027,Assumptions!$B$116+IF(OR(A4=4,A4=10),Assumptions!$B$117,0),IF(AND(B4=2027,A4<=4),IF(A4=4,MIN(950,Assumptions!$B$116+Assumptions!$B$117),Assumptions!$B$116),0)) -> 290 | BL4: =IF(OR(B4<2030,AND(B4=2030,A4<8)),Assumptions!$B$118,IF(AND(B4=2030,A4=8),MOD(11000,200),0)) -> 200 | BM4: =IF(OR(B4<Assumptions!$B$120,AND(B4=Assumptions!$B$120,A4<=Assumptions!$B$121)),Assumptions!$B$119,0) -> 132 | BN4: =IF(AND(B4<=Assumptions!$B$123,A4<=Assumptions!$B$124),Assumptions!$B$122,0) -> 90 | BO4: =BF4+BH4+BJ4+BK4+BL4+BM4+BN4 -> 1362 | BP4: =SUMIFS(SL_Budget!$B:$B,SL_Budget!$C:$C,"'"&TEXT(DATE(B4,A4,1),"YYYY-MM")) -> 4110 | BQ4: =MAX(BP4, IFERROR(SUMIFS(ShadowLedger!D:D, ShadowLedger!C:C, ">="&DATE(B4,A4,1), ShadowLedger!C:C, "<"&EOMONTH(DATE(B4,A4,1),0)+1), 0)) -> 4110 | BR4: =BV3 -> 12164.19 | BS4: =IF((AV3+AX3+BB3+AZ3+BD3)>5,0,X4) -> 0 | BT4: =IF(AS4>0,-MAX(0,21550-MAX(0,MAX(0,(AM4-AP4-BE4-BO4-BQ4)-Assumptions!$B$93))-MIN(MAX(0,21550-MAX(0,MAX(0,(AM4-AP4-BE4-BO4-BQ4)-Assumptions!$B$93))),MAX(0,BY3-Assumptions!$B$91))),IF(BY3>=Assumptions!$B$92,MAX(0,(AM4-AP4-BE4-BO4-BQ4)-Assumptions!$B$93),MAX(0,(AM4-AP4-BE4-BO4-BQ4)-Assumptions!$B$93)*Assumptions!$B$99)) -> 0 | BU4: =(BR4+BS4+MAX(0,BT4))*(Assumptions!$B$43-1) -> 82.935446 | BV4: =BR4+BS4+BT4+BU4 -> 12247.125 | BW4: =BY3 -> 0 | BX4: =IF(AS4>0,-MIN(MAX(0,21550-MAX(0,MAX(0,(AM4-AP4-BE4-BO4-BQ4)-Assumptions!$B$93))),MAX(0,BY3-Assumptions!$B$91)),IF(BY3<Assumptions!$B$92,MAX(0,(AM4-AP4-BE4-BO4-BQ4)-Assumptions!$B$93)*Assumptions!$B$98,0)) -> 0 | BY4: =BW4+BX4 -> 0 | BZ4: =IF(A4=1,0,CB3) -> 886 | CA4: =AH4 -> 443 | CB4: =BZ4+CA4 -> 1329 | CC4: =CC3+(G4+J4)/(Salary_Schedule!E4*12/208) -> 1701.4118 | CD4: =CD3+(O4+R4)/(Salary_Schedule!G4*12/208) -> 21.678592 | CE4: =BV4 -> 12247.125 | CF4: =Assumptions!$B$55*(1+Assumptions!$B$56)^((B4-2025)+(A4-1)/12) -> 529111.33 | CG4: =-AT4 -> -394559.47 | CH4: =-(AV4+AX4+BB4+AZ4+BD4+AF4+BG4+BI4) -> -77704.599 | CI4: =CC4*(Salary_Schedule!E4/173.33)*(1-Assumptions!$B$28)+CD4*(Salary_Schedule!G4/173.33)*(1-Assumptions!$B$28) -> 47504.516 | CJ4: =CE4+CF4+CG4+CH4+CI4 -> 116598.9
A5: 4 | B5: 2026 | C5: 04/2026 | D5: =C4 -> 03/2026 | E5: =IF(I5>0,"FAT_BONUS",IF(M5+U5>0,"FAT_RSU","LEAN")) -> FAT_BONUS | F5: =Salary_Schedule!E5 -> 7366.42 | G5: =Assumptions!$B$8 -> 200 | H5: =F5*Assumptions!$B$58 -> 736.642 | I5: =Salary_Schedule!F5 -> 9821 | J5: =I5*Assumptions!$B$9 -> 3437.35 | K5: =F5-G5-H5+I5-J5 -> 12813.428 | L5: =IF(COUNTIFS(SL_Income_Log!$B:$B,TEXT(B5,"0000")&"-"&TEXT(A5,"00"),SL_Income_Log!$C:$C,"salary",SL_Income_Log!$E:$E,"H")>0,SUMIFS(SL_Income_Log!$D:$D,SL_Income_Log!$B:$B,TEXT(B5,"0000")&"-"&TEXT(A5,"00"),SL_Income_Log!$C:$C,"salary",SL_Income_Log!$E:$E,"H"),K5*(1-Assumptions!$B$102)-Z5-Y5) -> 7320.2668 | M5: =RSU_Schedule!H4 -> 4788.75 | N5: =Salary_Schedule!G5 -> 6195.67 | O5: =Assumptions!$B$19 -> 200 | P5: =N5*Assumptions!$B$59 -> 619.567 | Q5: =Salary_Schedule!H5 -> 8261 | R5: =Q5*Assumptions!$B$20 -> 2891.35 | S5: =N5-O5-P5+Q5-R5 -> 10745.753 | T5: =IF(COUNTIFS(SL_Income_Log!$B:$B,TEXT(B5,"0000")&"-"&TEXT(A5,"00"),SL_Income_Log!$C:$C,"salary",SL_Income_Log!$E:$E,"W")>0,SUMIFS(SL_Income_Log!$D:$D,SL_Income_Log!$B:$B,TEXT(B5,"0000")&"-"&TEXT(A5,"00"),SL_Income_Log!$C:$C,"salary",SL_Income_Log!$E:$E,"W"),S5*(1-Assumptions!$B$102)-AC5-AB5) -> 6079.6618 | U5: =RSU_Schedule!M4 -> 2394.38 | V5: =H5*(1+Assumptions!$B$60)+Assumptions!$B$61 -> 1051.2988 | W5: =P5*(1+Assumptions!$B$60)+Assumptions!$B$61 -> 887.3938 | X5: =V5+W5 -> 1938.6926 | Y5: =ROUND(AA4*0.003,2) -> 76.12 | Z5: 291.67 | AA5: =MAX(0,AA4-Z5) -> 25083.32 | AB5: =ROUND(AD4*0.003,2) -> 76.12 | AC5: 291.67 | AD5: =MAX(0,AD4-AC5) -> 25083.32 | AE5: =Z5+AC5 -> 583.34 | AF5: =AA5+AD5 -> 50166.64 | AG5: =IF(COUNTIFS(SL_Income_Log!$B:$B,TEXT(B5,"0000")&"-"&TEXT(A5,"00"),SL_Income_Log!$C:$C,"youtube")>0,SUMIFS(SL_Income_Log!$D:$D,SL_Income_Log!$B:$B,TEXT(B5,"0000")&"-"&TEXT(A5,"00"),SL_Income_Log!$C:$C,"youtube"),MIN(Assumptions!$B$49+FLOOR((ROW()-2)/6,1)*Assumptions!$B$50,Assumptions!$B$51)) -> 1000 | AH5: =AG5*Assumptions!$B$104 -> 443 | AI5: =AG5-AH5 -> 557 | AJ5: =SUMIFS(SL_Income_Log!$D:$D,SL_Income_Log!$B:$B,TEXT(B5,"0000")&"-"&TEXT(A5,"00"),SL_Income_Log!$C:$C,"other") -> 0 | AK5: =AN4 -> -1000 | AL5: =L5+M5+T5+U5+AI5+AJ5-Y5-Z5-AB5-AC5+IF((Debt_Register!$C$2+Debt_Register!$C$6+Debt_Register!$C$7+Debt_Register!$C$8+Debt_Register!$C$9)>5,X5,0) -> 22343.171 | AM5: =AK5+AL5 -> 21343.171 | AN5: =MAX(Assumptions!$B$94,MIN(Assumptions!$B$93,AM5-AP5-BE5-BO5-BQ5)) -> 2725.5524 | AO5: =AT4 -> 394559.47 | AP5: =IF(AO5>0,Assumptions!$B$33,0) -> 2281 | AQ5: =AO5*Assumptions!$B$32/12 -> 1279.0303 | AR5: =AP5-AQ5 -> 1001.9697 | AS5: =IF(AND((AV4+AX4+AZ4+BB4+BD4)<5,AO5>0,SUMIF($B$2:B4,B5,$AS$2:AS4)=0,(MAX(0,AN5-10000)+MAX(0,BY4-5000)+MAX(0,BV4-20000))>=21550),21550,0) -> 0 | AT5: =MAX(0,AO5-AR5-AS5) -> 393557.5 | AU5: =IF(AV4>0,MIN(AV4,MAX(300,AM5-AP5-BO5-BQ5-AW5-AY5-BA5-BC5)),0) -> 8014.6188 | AV5: =MAX(0,AV4-AU5) -> 0 | AW5: =IF(AX4>0,MIN(250,AX4),0) -> 250 | AX5: =MAX(0,AX4-AW5) -> 1000 | AY5: =IF(AZ4>0,MIN(200,AZ4),0) -> 200 | AZ5: =MAX(0,AZ4-AY5) -> 1200 | BA5: =IF(AND(AV4<5,BB4>0),MIN(BB4,MAX(0,AM5-AP5-BO5-BQ5-AW5-AY5-BC5)),0) -> 0 | BB5: =MAX(0,BB4-BA5) -> 5500 | BC5: =IF(BD4>0,MIN(50,BD4),0) -> 50 | BD5: =MAX(0,BD4-BC5) -> 240 | BE5: =AU5+AW5+AY5+BA5+BC5 -> 8514.6188 | BF5: 0 | BG5: =MAX(0,BG4-BF5) -> 5500 | BH5: 0 | BI5: =MAX(0,BI4-BH5) -> 5000 | BJ5: =IF(OR(B5<Assumptions!$B$111,AND(B5=Assumptions!$B$111,A5<=Assumptions!$B$112)),Assumptions!$B$110,0) -> 650 | BK5: =IF(B5<2027,Assumptions!$B$116+IF(OR(A5=4,A5=10),Assumptions!$B$117,0),IF(AND(B5=2027,A5<=4),IF(A5=4,MIN(950,Assumptions!$B$116+Assumptions!$B$117),Assumptions!$B$116),0)) -> 2640 | BL5: =IF(OR(B5<2030,AND(B5=2030,A5<8)),Assumptions!$B$118,IF(AND(B5=2030,A5=8),MOD(11000,200),0)) -> 200 | BM5: =IF(OR(B5<Assumptions!$B$120,AND(B5=Assumptions!$B$120,A5<=Assumptions!$B$121)),Assumptions!$B$119,0) -> 132 | BN5: =IF(AND(B5<=Assumptions!$B$123,A5<=Assumptions!$B$124),Assumptions!$B$122,0) -> 90 | BO5: =BF5+BH5+BJ5+BK5+BL5+BM5+BN5 -> 3712 | BP5: =SUMIFS(SL_Budget!$B:$B,SL_Budget!$C:$C,"'"&TEXT(DATE(B5,A5,1),"YYYY-MM")) -> 4110 | BQ5: =MAX(BP5, IFERROR(SUMIFS(ShadowLedger!D:D, ShadowLedger!C:C, ">="&DATE(B5,A5,1), ShadowLedger!C:C, "<"&EOMONTH(DATE(B5,A5,1),0)+1), 0)) -> 4110 | BR5: =BV4 -> 12247.125 | BS5: =IF((AV4+AX4+BB4+AZ4+BD4)>5,0,X5) -> 0 | BT5: =IF(AS5>0,-MAX(0,21550-MAX(0,MAX(0,(AM5-AP5-BE5-BO5-BQ5)-Assumptions!$B$93))-MIN(MAX(0,21550-MAX(0,MAX(0,(AM5-AP5-BE5-BO5-BQ5)-Assumptions!$B$93))),MAX(0,BY4-Assumptions!$B$91))),IF(BY4>=Assumptions!$B$92,MAX(0,(AM5-AP5-BE5-BO5-BQ5)-Assumptions!$B$93),MAX(0,(AM5-AP5-BE5-BO5-BQ5)-Assumptions!$B$93)*Assumptions!$B$99)) -> 0 | BU5: =(BR5+BS5+MAX(0,BT5))*(Assumptions!$B$43-1) -> 83.5009 | BV5: =BR5+BS5+BT5+BU5 -> 12330.626 | BW5: =BY4 -> 0 | BX5: =IF(AS5>0,-MIN(MAX(0,21550-MAX(0,MAX(0,(AM5-AP5-BE5-BO5-BQ5)-Assumptions!$B$93))),MAX(0,BY4-Assumptions!$B$91)),IF(BY4<Assumptions!$B$92,MAX(0,(AM5-AP5-BE5-BO5-BQ5)-Assumptions!$B$93)*Assumptions!$B$98,0)) -> 0 | BY5: =BW5+BX5 -> 0 | BZ5: =IF(A5=1,0,CB4) -> 1329 | CA5: =AH5 -> 443 | CB5: =BZ5+CA5 -> 1772 | CC5: =CC4+(G5+J5)/(Salary_Schedule!E5*12/208) -> 1709.9706 | CD5: =CD4+(O5+R5)/(Salary_Schedule!G5*12/208) -> 30.327116 | CE5: =BV5 -> 12330.626 | CF5: =Assumptions!$B$55*(1+Assumptions!$B$56)^((B5-2025)+(A5-1)/12) -> 529768.21 | CG5: =-AT5 -> -393557.5 | CH5: =-(AV5+AX5+BB5+AZ5+BD5+AF5+BG5+BI5) -> -68606.64 | CI5: =CC5*(Salary_Schedule!E5/173.33)*(1-Assumptions!$B$28)+CD5*(Salary_Schedule!G5/173.33)*(1-Assumptions!$B$28) -> 47941.89 | CJ5: =CE5+CF5+CG5+CH5+CI5 -> 127876.58
A6: 5 | B6: 2026 | C6: 05/2026 | D6: =C5 -> 04/2026 | E6: =IF(I6>0,"FAT_BONUS",IF(M6+U6>0,"FAT_RSU","LEAN")) -> LEAN | F6: =Salary_Schedule!E6 -> 7366.42 | G6: =Assumptions!$B$8 -> 200 | H6: =F6*Assumptions!$B$58 -> 736.642 | I6: =Salary_Schedule!F6 -> 0 | J6: =I6*Assumptions!$B$9 -> 0 | K6: =F6-G6-H6+I6-J6 -> 6429.778 | L6: =IF(COUNTIFS(SL_Income_Log!$B:$B,TEXT(B6,"0000")&"-"&TEXT(A6,"00"),SL_Income_Log!$C:$C,"salary",SL_Income_Log!$E:$E,"H")>0,SUMIFS(SL_Income_Log!$D:$D,SL_Income_Log!$B:$B,TEXT(B6,"0000")&"-"&TEXT(A6,"00"),SL_Income_Log!$C:$C,"salary",SL_Income_Log!$E:$E,"H"),K6*(1-Assumptions!$B$102)-Z6-Y6) -> 3490.9468 | M6: =RSU_Schedule!H5 -> 0 | N6: =Salary_Schedule!G6 -> 6195.67 | O6: =Assumptions!$B$19 -> 200 | P6: =N6*Assumptions!$B$59 -> 619.567 | Q6: =Salary_Schedule!H6 -> 0 | R6: =Q6*Assumptions!$B$20 -> 0 | S6: =N6-O6-P6+Q6-R6 -> 5376.103 | T6: =IF(COUNTIFS(SL_Income_Log!$B:$B,TEXT(B6,"0000")&"-"&TEXT(A6,"00"),SL_Income_Log!$C:$C,"salary",SL_Income_Log!$E:$E,"W")>0,SUMIFS(SL_Income_Log!$D:$D,SL_Income_Log!$B:$B,TEXT(B6,"0000")&"-"&TEXT(A6,"00"),SL_Income_Log!$C:$C,"salary",SL_Income_Log!$E:$E,"W"),S6*(1-Assumptions!$B$102)-AC6-AB6) -> 2858.7418 | U6: =RSU_Schedule!M5 -> 0 | V6: =H6*(1+Assumptions!$B$60)+Assumptions!$B$61 -> 1051.2988 | W6: =P6*(1+Assumptions!$B$60)+Assumptions!$B$61 -> 887.3938 | X6: =V6+W6 -> 1938.6926 | Y6: =ROUND(AA5*0.003,2) -> 75.25 | Z6: 291.67 | AA6: =MAX(0,AA5-Z6) -> 24791.65 | AB6: =ROUND(AD5*0.003,2) -> 75.25 | AC6: 291.67 | AD6: =MAX(0,AD5-AC6) -> 24791.65 | AE6: =Z6+AC6 -> 583.34 | AF6: =AA6+AD6 -> 49583.3 | AG6: =IF(COUNTIFS(SL_Income_Log!$B:$B,TEXT(B6,"0000")&"-"&TEXT(A6,"00"),SL_Income_Log!$C:$C,"youtube")>0,SUMIFS(SL_Income_Log!$D:$D,SL_Income_Log!$B:$B,TEXT(B6,"0000")&"-"&TEXT(A6,"00"),SL_Income_Log!$C:$C,"youtube"),MIN(Assumptions!$B$49+FLOOR((ROW()-2)/6,1)*Assumptions!$B$50,Assumptions!$B$51)) -> 1000 | AH6: =AG6*Assumptions!$B$104 -> 443 | AI6: =AG6-AH6 -> 557 | AJ6: =SUMIFS(SL_Income_Log!$D:$D,SL_Income_Log!$B:$B,TEXT(B6,"0000")&"-"&TEXT(A6,"00"),SL_Income_Log!$C:$C,"other") -> 0 | AK6: =AN5 -> 2725.5524 | AL6: =L6+M6+T6+U6+AI6+AJ6-Y6-Z6-AB6-AC6+IF((Debt_Register!$C$2+Debt_Register!$C$6+Debt_Register!$C$7+Debt_Register!$C$8+Debt_Register!$C$9)>5,X6,0) -> 8111.5412 | AM6: =AK6+AL6 -> 10837.094 | AN6: =MAX(Assumptions!$B$94,MIN(Assumptions!$B$93,AM6-AP6-BE6-BO6-BQ6)) -> 0 | AO6: =AT5 -> 393557.5 | AP6: =IF(AO6>0,Assumptions!$B$33,0) -> 2281 | AQ6: =AO6*Assumptions!$B$32/12 -> 1275.7822 | AR6: =AP6-AQ6 -> 1005.2178 | AS6: =IF(AND((AV5+AX5+AZ5+BB5+BD5)<5,AO6>0,SUMIF($B$2:B5,B6,$AS$2:AS5)=0,(MAX(0,AN6-10000)+MAX(0,BY5-5000)+MAX(0,BV5-20000))>=21550),21550,0) -> 0 | AT6: =MAX(0,AO6-AR6-AS6) -> 392552.29 | AU6: =IF(AV5>0,MIN(AV5,MAX(300,AM6-AP6-BO6-BQ6-AW6-AY6-BA6-BC6)),0) -> 0 | AV6: =MAX(0,AV5-AU6) -> 0 | AW6: =IF(AX5>0,MIN(250,AX5),0) -> 250 | AX6: =MAX(0,AX5-AW6) -> 750 | AY6: =IF(AZ5>0,MIN(200,AZ5),0) -> 200 | AZ6: =MAX(0,AZ5-AY6) -> 1000 | BA6: =IF(AND(AV5<5,BB5>0),MIN(BB5,MAX(0,AM6-AP6-BO6-BQ6-AW6-AY6-BC6)),0) -> 2674.0936 | BB6: =MAX(0,BB5-BA6) -> 2825.9064 | BC6: =IF(BD5>0,MIN(50,BD5),0) -> 50 | BD6: =MAX(0,BD5-BC6) -> 190 | BE6: =AU6+AW6+AY6+BA6+BC6 -> 3174.0936 | BF6: 0 | BG6: =MAX(0,BG5-BF6) -> 5500 | BH6: 0 | BI6: =MAX(0,BI5-BH6) -> 5000 | BJ6: =IF(OR(B6<Assumptions!$B$111,AND(B6=Assumptions!$B$111,A6<=Assumptions!$B$112)),Assumptions!$B$110,0) -> 650 | BK6: =IF(B6<2027,Assumptions!$B$116+IF(OR(A6=4,A6=10),Assumptions!$B$117,0),IF(AND(B6=2027,A6<=4),IF(A6=4,MIN(950,Assumptions!$B$116+Assumptions!$B$117),Assumptions!$B$116),0)) -> 290 | BL6: =IF(OR(B6<2030,AND(B6=2030,A6<8)),Assumptions!$B$118,IF(AND(B6=2030,A6=8),MOD(11000,200),0)) -> 200 | BM6: =IF(OR(B6<Assumptions!$B$120,AND(B6=Assumptions!$B$120,A6<=Assumptions!$B$121)),Assumptions!$B$119,0) -> 132 | BN6: =IF(AND(B6<=Assumptions!$B$123,A6<=Assumptions!$B$124),Assumptions!$B$122,0) -> 0 | BO6: =BF6+BH6+BJ6+BK6+BL6+BM6+BN6 -> 1272 | BP6: =SUMIFS(SL_Budget!$B:$B,SL_Budget!$C:$C,"'"&TEXT(DATE(B6,A6,1),"YYYY-MM")) -> 4110 | BQ6: =MAX(BP6, IFERROR(SUMIFS(ShadowLedger!D:D, ShadowLedger!C:C, ">="&DATE(B6,A6,1), ShadowLedger!C:C, "<"&EOMONTH(DATE(B6,A6,1),0)+1), 0)) -> 4110 | BR6: =BV5 -> 12330.626 | BS6: =IF((AV5+AX5+BB5+AZ5+BD5)>5,0,X6) -> 0 | BT6: =IF(AS6>0,-MAX(0,21550-MAX(0,MAX(0,(AM6-AP6-BE6-BO6-BQ6)-Assumptions!$B$93))-MIN(MAX(0,21550-MAX(0,MAX(0,(AM6-AP6-BE6-BO6-BQ6)-Assumptions!$B$93))),MAX(0,BY5-Assumptions!$B$91))),IF(BY5>=Assumptions!$B$92,MAX(0,(AM6-AP6-BE6-BO6-BQ6)-Assumptions!$B$93),MAX(0,(AM6-AP6-BE6-BO6-BQ6)-Assumptions!$B$93)*Assumptions!$B$99)) -> 0 | BU6: =(BR6+BS6+MAX(0,BT6))*(Assumptions!$B$43-1) -> 84.070209 | BV6: =BR6+BS6+BT6+BU6 -> 12414.696 | BW6: =BY5 -> 0 | BX6: =IF(AS6>0,-MIN(MAX(0,21550-MAX(0,MAX(0,(AM6-AP6-BE6-BO6-BQ6)-Assumptions!$B$93))),MAX(0,BY5-Assumptions!$B$91)),IF(BY5<Assumptions!$B$92,MAX(0,(AM6-AP6-BE6-BO6-BQ6)-Assumptions!$B$93)*Assumptions!$B$98,0)) -> 0 | BY6: =BW6+BX6 -> 0 | BZ6: =IF(A6=1,0,CB5) -> 1772 | CA6: =AH6 -> 443 | CB6: =BZ6+CA6 -> 2215 | CC6: =CC5+(G6+J6)/(Salary_Schedule!E6*12/208) -> 1710.4412 | CD6: =CD5+(O6+R6)/(Salary_Schedule!G6*12/208) -> 30.886646 | CE6: =BV6 -> 12414.696 | CF6: =Assumptions!$B$55*(1+Assumptions!$B$56)^((B6-2025)+(A6-1)/12) -> 530425.91 | CG6: =-AT6 -> -392552.29 | CH6: =-(AV6+AX6+BB6+AZ6+BD6+AF6+BG6+BI6) -> -64849.206 | CI6: =CC6*(Salary_Schedule!E6/173.33)*(1-Assumptions!$B$28)+CD6*(Salary_Schedule!G6/173.33)*(1-Assumptions!$B$28) -> 47967.891 | CJ6: =CE6+CF6+CG6+CH6+CI6 -> 133407.01
A7: 6 | B7: 2026 | C7: 06/2026 | D7: =C6 -> 05/2026 | E7: =IF(I7>0,"FAT_BONUS",IF(M7+U7>0,"FAT_RSU","LEAN")) -> LEAN | F7: =Salary_Schedule!E7 -> 7366.42 | G7: =Assumptions!$B$8 -> 200 | H7: =F7*Assumptions!$B$58 -> 736.642 | I7: =Salary_Schedule!F7 -> 0 | J7: =I7*Assumptions!$B$9 -> 0 | K7: =F7-G7-H7+I7-J7 -> 6429.778 | L7: =IF(COUNTIFS(SL_Income_Log!$B:$B,TEXT(B7,"0000")&"-"&TEXT(A7,"00"),SL_Income_Log!$C:$C,"salary",SL_Income_Log!$E:$E,"H")>0,SUMIFS(SL_Income_Log!$D:$D,SL_Income_Log!$B:$B,TEXT(B7,"0000")&"-"&TEXT(A7,"00"),SL_Income_Log!$C:$C,"salary",SL_Income_Log!$E:$E,"H"),K7*(1-Assumptions!$B$102)-Z7-Y7) -> 3491.8268 | M7: =RSU_Schedule!H6 -> 0 | N7: =Salary_Schedule!G7 -> 6195.67 | O7: =Assumptions!$B$19 -> 200 | P7: =N7*Assumptions!$B$59 -> 619.567 | Q7: =Salary_Schedule!H7 -> 0 | R7: =Q7*Assumptions!$B$20 -> 0 | S7: =N7-O7-P7+Q7-R7 -> 5376.103 | T7: =IF(COUNTIFS(SL_Income_Log!$B:$B,TEXT(B7,"0000")&"-"&TEXT(A7,"00"),SL_Income_Log!$C:$C,"salary",SL_Income_Log!$E:$E,"W")>0,SUMIFS(SL_Income_Log!$D:$D,SL_Income_Log!$B:$B,TEXT(B7,"0000")&"-"&TEXT(A7,"00"),SL_Income_Log!$C:$C,"salary",SL_Income_Log!$E:$E,"W"),S7*(1-Assumptions!$B$102)-AC7-AB7) -> 2859.6218 | U7: =RSU_Schedule!M6 -> 0 | V7: =H7*(1+Assumptions!$B$60)+Assumptions!$B$61 -> 1051.2988 | W7: =P7*(1+Assumptions!$B$60)+Assumptions!$B$61 -> 887.3938 | X7: =V7+W7 -> 1938.6926 | Y7: =ROUND(AA6*0.003,2) -> 74.37 | Z7: 291.67 | AA7: =MAX(0,AA6-Z7) -> 24499.98 | AB7: =ROUND(AD6*0.003,2) -> 74.37 | AC7: 291.67 | AD7: =MAX(0,AD6-AC7) -> 24499.98 | AE7: =Z7+AC7 -> 583.34 | AF7: =AA7+AD7 -> 48999.96 | AG7: =IF(COUNTIFS(SL_Income_Log!$B:$B,TEXT(B7,"0000")&"-"&TEXT(A7,"00"),SL_Income_Log!$C:$C,"youtube")>0,SUMIFS(SL_Income_Log!$D:$D,SL_Income_Log!$B:$B,TEXT(B7,"0000")&"-"&TEXT(A7,"00"),SL_Income_Log!$C:$C,"youtube"),MIN(Assumptions!$B$49+FLOOR((ROW()-2)/6,1)*Assumptions!$B$50,Assumptions!$B$51)) -> 1000 | AH7: =AG7*Assumptions!$B$104 -> 443 | AI7: =AG7-AH7 -> 557 | AJ7: =SUMIFS(SL_Income_Log!$D:$D,SL_Income_Log!$B:$B,TEXT(B7,"0000")&"-"&TEXT(A7,"00"),SL_Income_Log!$C:$C,"other") -> 0 | AK7: =AN6 -> 0 | AL7: =L7+M7+T7+U7+AI7+AJ7-Y7-Z7-AB7-AC7+IF((Debt_Register!$C$2+Debt_Register!$C$6+Debt_Register!$C$7+Debt_Register!$C$8+Debt_Register!$C$9)>5,X7,0) -> 8115.0612 | AM7: =AK7+AL7 -> 8115.0612 | AN7: =MAX(Assumptions!$B$94,MIN(Assumptions!$B$93,AM7-AP7-BE7-BO7-BQ7)) -> -47.9388 | AO7: =AT6 -> 392552.29 | AP7: =IF(AO7>0,Assumptions!$B$33,0) -> 2281 | AQ7: =AO7*Assumptions!$B$32/12 -> 1272.5237 | AR7: =AP7-AQ7 -> 1008.4763 | AS7: =IF(AND((AV6+AX6+AZ6+BB6+BD6)<5,AO7>0,SUMIF($B$2:B6,B7,$AS$2:AS6)=0,(MAX(0,AN7-10000)+MAX(0,BY6-5000)+MAX(0,BV6-20000))>=21550),21550,0) -> 0 | AT7: =MAX(0,AO7-AR7-AS7) -> 391543.81 | AU7: =IF(AV6>0,MIN(AV6,MAX(300,AM7-AP7-BO7-BQ7-AW7-AY7-BA7-BC7)),0) -> 0 | AV7: =MAX(0,AV6-AU7) -> 0 | AW7: =IF(AX6>0,MIN(250,AX6),0) -> 250 | AX7: =MAX(0,AX6-AW7) -> 500 | AY7: =IF(AZ6>0,MIN(200,AZ6),0) -> 200 | AZ7: =MAX(0,AZ6-AY7) -> 800 | BA7: =IF(AND(AV6<5,BB6>0),MIN(BB6,MAX(0,AM7-AP7-BO7-BQ7-AW7-AY7-BC7)),0) -> 0 | BB7: =MAX(0,BB6-BA7) -> 2825.9064 | BC7: =IF(BD6>0,MIN(50,BD6),0) -> 50 | BD7: =MAX(0,BD6-BC7) -> 140 | BE7: =AU7+AW7+AY7+BA7+BC7 -> 500 | BF7: 0 | BG7: =MAX(0,BG6-BF7) -> 5500 | BH7: 0 | BI7: =MAX(0,BI6-BH7) -> 5000 | BJ7: =IF(OR(B7<Assumptions!$B$111,AND(B7=Assumptions!$B$111,A7<=Assumptions!$B$112)),Assumptions!$B$110,0) -> 650 | BK7: =IF(B7<2027,Assumptions!$B$116+IF(OR(A7=4,A7=10),Assumptions!$B$117,0),IF(AND(B7=2027,A7<=4),IF(A7=4,MIN(950,Assumptions!$B$116+Assumptions!$B$117),Assumptions!$B$116),0)) -> 290 | BL7: =IF(OR(B7<2030,AND(B7=2030,A7<8)),Assumptions!$B$118,IF(AND(B7=2030,A7=8),MOD(11000,200),0)) -> 200 | BM7: =IF(OR(B7<Assumptions!$B$120,AND(B7=Assumptions!$B$120,A7<=Assumptions!$B$121)),Assumptions!$B$119,0) -> 132 | BN7: =IF(AND(B7<=Assumptions!$B$123,A7<=Assumptions!$B$124),Assumptions!$B$122,0) -> 0 | BO7: =BF7+BH7+BJ7+BK7+BL7+BM7+BN7 -> 1272 | BP7: =SUMIFS(SL_Budget!$B:$B,SL_Budget!$C:$C,"'"&TEXT(DATE(B7,A7,1),"YYYY-MM")) -> 4110 | BQ7: =MAX(BP7, IFERROR(SUMIFS(ShadowLedger!D:D, ShadowLedger!C:C, ">="&DATE(B7,A7,1), ShadowLedger!C:C, "<"&EOMONTH(DATE(B7,A7,1),0)+1), 0)) -> 4110 | BR7: =BV6 -> 12414.696 | BS7: =IF((AV6+AX6+BB6+AZ6+BD6)>5,0,X7) -> 0 | BT7: =IF(AS7>0,-MAX(0,21550-MAX(0,MAX(0,(AM7-AP7-BE7-BO7-BQ7)-Assumptions!$B$93))-MIN(MAX(0,21550-MAX(0,MAX(0,(AM7-AP7-BE7-BO7-BQ7)-Assumptions!$B$93))),MAX(0,BY6-Assumptions!$B$91))),IF(BY6>=Assumptions!$B$92,MAX(0,(AM7-AP7-BE7-BO7-BQ7)-Assumptions!$B$93),MAX(0,(AM7-AP7-BE7-BO7-BQ7)-Assumptions!$B$93)*Assumptions!$B$99)) -> 0 | BU7: =(BR7+BS7+MAX(0,BT7))*(Assumptions!$B$43-1) -> 84.6434 | BV7: =BR7+BS7+BT7+BU7 -> 12499.34 | BW7: =BY6 -> 0 | BX7: =IF(AS7>0,-MIN(MAX(0,21550-MAX(0,MAX(0,(AM7-AP7-BE7-BO7-BQ7)-Assumptions!$B$93))),MAX(0,BY6-Assumptions!$B$91)),IF(BY6<Assumptions!$B$92,MAX(0,(AM7-AP7-BE7-BO7-BQ7)-Assumptions!$B$93)*Assumptions!$B$98,0)) -> 0 | BY7: =BW7+BX7 -> 0 | BZ7: =IF(A7=1,0,CB6) -> 2215 | CA7: =AH7 -> 443 | CB7: =BZ7+CA7 -> 2658 | CC7: =CC6+(G7+J7)/(Salary_Schedule!E7*12/208) -> 1710.9118 | CD7: =CD6+(O7+R7)/(Salary_Schedule!G7*12/208) -> 31.446177 | CE7: =BV7 -> 12499.34 | CF7: =Assumptions!$B$55*(1+Assumptions!$B$56)^((B7-2025)+(A7-1)/12) -> 531084.43 | CG7: =-AT7 -> -391543.81 | CH7: =-(AV7+AX7+BB7+AZ7+BD7+AF7+BG7+BI7) -> -63765.866 | CI7: =CC7*(Salary_Schedule!E7/173.33)*(1-Assumptions!$B$28)+CD7*(Salary_Schedule!G7/173.33)*(1-Assumptions!$B$28) -> 47993.891 | CJ7: =CE7+CF7+CG7+CH7+CI7 -> 136267.99
A8: 7 | B8: 2026 | C8: 07/2026 | D8: =C7 -> 06/2026 | E8: =IF(I8>0,"FAT_BONUS",IF(M8+U8>0,"FAT_RSU","LEAN")) -> FAT_RSU | F8: =Salary_Schedule!E8 -> 7366.42 | G8: =Assumptions!$B$8 -> 200 | H8: =F8*Assumptions!$B$58 -> 736.642 | I8: =Salary_Schedule!F8 -> 0 | J8: =I8*Assumptions!$B$9 -> 0 | K8: =F8-G8-H8+I8-J8 -> 6429.778 | L8: =IF(COUNTIFS(SL_Income_Log!$B:$B,TEXT(B8,"0000")&"-"&TEXT(A8,"00"),SL_Income_Log!$C:$C,"salary",SL_Income_Log!$E:$E,"H")>0,SUMIFS(SL_Income_Log!$D:$D,SL_Income_Log!$B:$B,TEXT(B8,"0000")&"-"&TEXT(A8,"00"),SL_Income_Log!$C:$C,"salary",SL_Income_Log!$E:$E,"H"),K8*(1-Assumptions!$B$102)-Z8-Y8) -> 3492.6968 | M8: =RSU_Schedule!H7 -> 3030.69 | N8: =Salary_Schedule!G8 -> 6195.67 | O8: =Assumptions!$B$19 -> 200 | P8: =N8*Assumptions!$B$59 -> 619.567 | Q8: =Salary_Schedule!H8 -> 0 | R8: =Q8*Assumptions!$B$20 -> 0 | S8: =N8-O8-P8+Q8-R8 -> 5376.103 | T8: =IF(COUNTIFS(SL_Income_Log!$B:$B,TEXT(B8,"0000")&"-"&TEXT(A8,"00"),SL_Income_Log!$C:$C,"salary",SL_Income_Log!$E:$E,"W")>0,SUMIFS(SL_Income_Log!$D:$D,SL_Income_Log!$B:$B,TEXT(B8,"0000")&"-"&TEXT(A8,"00"),SL_Income_Log!$C:$C,"salary",SL_Income_Log!$E:$E,"W"),S8*(1-Assumptions!$B$102)-AC8-AB8) -> 2860.4918 | U8: =RSU_Schedule!M7 -> 1515.35 | V8: =H8*(1+Assumptions!$B$60)+Assumptions!$B$61 -> 1051.2988 | W8: =P8*(1+Assumptions!$B$60)+Assumptions!$B$61 -> 887.3938 | X8: =V8+W8 -> 1938.6926 | Y8: =ROUND(AA7*0.003,2) -> 73.5 | Z8: 291.67 | AA8: =MAX(0,AA7-Z8) -> 24208.31 | AB8: =ROUND(AD7*0.003,2) -> 73.5 | AC8: 291.67 | AD8: =MAX(0,AD7-AC8) -> 24208.31 | AE8: =Z8+AC8 -> 583.34 | AF8: =AA8+AD8 -> 48416.62 | AG8: =IF(COUNTIFS(SL_Income_Log!$B:$B,TEXT(B8,"0000")&"-"&TEXT(A8,"00"),SL_Income_Log!$C:$C,"youtube")>0,SUMIFS(SL_Income_Log!$D:$D,SL_Income_Log!$B:$B,TEXT(B8,"0000")&"-"&TEXT(A8,"00"),SL_Income_Log!$C:$C,"youtube"),MIN(Assumptions!$B$49+FLOOR((ROW()-2)/6,1)*Assumptions!$B$50,Assumptions!$B$51)) -> 2000 | AH8: =AG8*Assumptions!$B$104 -> 886 | AI8: =AG8-AH8 -> 1114 | AJ8: =SUMIFS(SL_Income_Log!$D:$D,SL_Income_Log!$B:$B,TEXT(B8,"0000")&"-"&TEXT(A8,"00"),SL_Income_Log!$C:$C,"other") -> 0 | AK8: =AN7 -> -47.9388 | AL8: =L8+M8+T8+U8+AI8+AJ8-Y8-Z8-AB8-AC8+IF((Debt_Register!$C$2+Debt_Register!$C$6+Debt_Register!$C$7+Debt_Register!$C$8+Debt_Register!$C$9)>5,X8,0) -> 13221.581 | AM8: =AK8+AL8 -> 13173.642 | AN8: =MAX(Assumptions!$B$94,MIN(Assumptions!$B$93,AM8-AP8-BE8-BO8-BQ8)) -> 2184.736 | AO8: =AT7 -> 391543.81 | AP8: =IF(AO8>0,Assumptions!$B$33,0) -> 2281 | AQ8: =AO8*Assumptions!$B$32/12 -> 1269.2545 | AR8: =AP8-AQ8 -> 1011.7455 | AS8: =IF(AND((AV7+AX7+AZ7+BB7+BD7)<5,AO8>0,SUMIF($B$2:B7,B8,$AS$2:AS7)=0,(MAX(0,AN8-10000)+MAX(0,BY7-5000)+MAX(0,BV7-20000))>=21550),21550,0) -> 0 | AT8: =MAX(0,AO8-AR8-AS8) -> 390532.07 | AU8: =IF(AV7>0,MIN(AV7,MAX(300,AM8-AP8-BO8-BQ8-AW8-AY8-BA8-BC8)),0) -> 0 | AV8: =MAX(0,AV7-AU8) -> 0 | AW8: =IF(AX7>0,MIN(250,AX7),0) -> 250 | AX8: =MAX(0,AX7-AW8) -> 250 | AY8: =IF(AZ7>0,MIN(200,AZ7),0) -> 200 | AZ8: =MAX(0,AZ7-AY8) -> 600 | BA8: =IF(AND(AV7<5,BB7>0),MIN(BB7,MAX(0,AM8-AP8-BO8-BQ8-AW8-AY8-BC8)),0) -> 2825.9064 | BB8: =MAX(0,BB7-BA8) -> 0 | BC8: =IF(BD7>0,MIN(50,BD7),0) -> 50 | BD8: =MAX(0,BD7-BC8) -> 90 | BE8: =AU8+AW8+AY8+BA8+BC8 -> 3325.9064 | BF8: 0 | BG8: =MAX(0,BG7-BF8) -> 5500 | BH8: 0 | BI8: =MAX(0,BI7-BH8) -> 5000 | BJ8: =IF(OR(B8<Assumptions!$B$111,AND(B8=Assumptions!$B$111,A8<=Assumptions!$B$112)),Assumptions!$B$110,0) -> 650 | BK8: =IF(B8<2027,Assumptions!$B$116+IF(OR(A8=4,A8=10),Assumptions!$B$117,0),IF(AND(B8=2027,A8<=4),IF(A8=4,MIN(950,Assumptions!$B$116+Assumptions!$B$117),Assumptions!$B$116),0)) -> 290 | BL8: =IF(OR(B8<2030,AND(B8=2030,A8<8)),Assumptions!$B$118,IF(AND(B8=2030,A8=8),MOD(11000,200),0)) -> 200 | BM8: =IF(OR(B8<Assumptions!$B$120,AND(B8=Assumptions!$B$120,A8<=Assumptions!$B$121)),Assumptions!$B$119,0) -> 132 | BN8: =IF(AND(B8<=Assumptions!$B$123,A8<=Assumptions!$B$124),Assumptions!$B$122,0) -> 0 | BO8: =BF8+BH8+BJ8+BK8+BL8+BM8+BN8 -> 1272 | BP8: =SUMIFS(SL_Budget!$B:$B,SL_Budget!$C:$C,"'"&TEXT(DATE(B8,A8,1),"YYYY-MM")) -> 4110 | BQ8: =MAX(BP8, IFERROR(SUMIFS(ShadowLedger!D:D, ShadowLedger!C:C, ">="&DATE(B8,A8,1), ShadowLedger!C:C, "<"&EOMONTH(DATE(B8,A8,1),0)+1), 0)) -> 4110 | BR8: =BV7 -> 12499.34 | BS8: =IF((AV7+AX7+BB7+AZ7+BD7)>5,0,X8) -> 0 | BT8: =IF(AS8>0,-MAX(0,21550-MAX(0,MAX(0,(AM8-AP8-BE8-BO8-BQ8)-Assumptions!$B$93))-MIN(MAX(0,21550-MAX(0,MAX(0,(AM8-AP8-BE8-BO8-BQ8)-Assumptions!$B$93))),MAX(0,BY7-Assumptions!$B$91))),IF(BY7>=Assumptions!$B$92,MAX(0,(AM8-AP8-BE8-BO8-BQ8)-Assumptions!$B$93),MAX(0,(AM8-AP8-BE8-BO8-BQ8)-Assumptions!$B$93)*Assumptions!$B$99)) -> 0 | BU8: =(BR8+BS8+MAX(0,BT8))*(Assumptions!$B$43-1) -> 85.220499 | BV8: =BR8+BS8+BT8+BU8 -> 12584.56 | BW8: =BY7 -> 0 | BX8: =IF(AS8>0,-MIN(MAX(0,21550-MAX(0,MAX(0,(AM8-AP8-BE8-BO8-BQ8)-Assumptions!$B$93))),MAX(0,BY7-Assumptions!$B$91)),IF(BY7<Assumptions!$B$92,MAX(0,(AM8-AP8-BE8-BO8-BQ8)-Assumptions!$B$93)*Assumptions!$B$98,0)) -> 0 | BY8: =BW8+BX8 -> 0 | BZ8: =IF(A8=1,0,CB7) -> 2658 | CA8: =AH8 -> 886 | CB8: =BZ8+CA8 -> 3544 | CC8: =CC7+(G8+J8)/(Salary_Schedule!E8*12/208) -> 1711.3824 | CD8: =CD7+(O8+R8)/(Salary_Schedule!G8*12/208) -> 32.005707 | CE8: =BV8 -> 12584.56 | CF8: =Assumptions!$B$55*(1+Assumptions!$B$56)^((B8-2025)+(A8-1)/12) -> 531743.77 | CG8: =-AT8 -> -390532.07 | CH8: =-(AV8+AX8+BB8+AZ8+BD8+AF8+BG8+BI8) -> -59856.62 | CI8: =CC8*(Salary_Schedule!E8/173.33)*(1-Assumptions!$B$28)+CD8*(Salary_Schedule!G8/173.33)*(1-Assumptions!$B$28) -> 48019.892 | CJ8: =CE8+CF8+CG8+CH8+CI8 -> 141959.53
A9: 8 | B9: 2026 | C9: 08/2026 | D9: =C8 -> 07/2026 | E9: =IF(I9>0,"FAT_BONUS",IF(M9+U9>0,"FAT_RSU","LEAN")) -> LEAN | F9: =Salary_Schedule!E9 -> 7366.42 | G9: =Assumptions!$B$8 -> 200 | H9: =F9*Assumptions!$B$58 -> 736.642 | I9: =Salary_Schedule!F9 -> 0 | J9: =I9*Assumptions!$B$9 -> 0 | K9: =F9-G9-H9+I9-J9 -> 6429.778 | L9: =IF(COUNTIFS(SL_Income_Log!$B:$B,TEXT(B9,"0000")&"-"&TEXT(A9,"00"),SL_Income_Log!$C:$C,"salary",SL_Income_Log!$E:$E,"H")>0,SUMIFS(SL_Income_Log!$D:$D,SL_Income_Log!$B:$B,TEXT(B9,"0000")&"-"&TEXT(A9,"00"),SL_Income_Log!$C:$C,"salary",SL_Income_Log!$E:$E,"H"),K9*(1-Assumptions!$B$102)-Z9-Y9) -> 3493.5768 | M9: =RSU_Schedule!H8 -> 0 | N9: =Salary_Schedule!G9 -> 6195.67 | O9: =Assumptions!$B$19 -> 200 | P9: =N9*Assumptions!$B$59 -> 619.567 | Q9: =Salary_Schedule!H9 -> 0 | R9: =Q9*Assumptions!$B$20 -> 0 | S9: =N9-O9-P9+Q9-R9 -> 5376.103 | T9: =IF(COUNTIFS(SL_Income_Log!$B:$B,TEXT(B9,"0000")&"-"&TEXT(A9,"00"),SL_Income_Log!$C:$C,"salary",SL_Income_Log!$E:$E,"W")>0,SUMIFS(SL_Income_Log!$D:$D,SL_Income_Log!$B:$B,TEXT(B9,"0000")&"-"&TEXT(A9,"00"),SL_Income_Log!$C:$C,"salary",SL_Income_Log!$E:$E,"W"),S9*(1-Assumptions!$B$102)-AC9-AB9) -> 2861.3718 | U9: =RSU_Schedule!M8 -> 0 | V9: =H9*(1+Assumptions!$B$60)+Assumptions!$B$61 -> 1051.2988 | W9: =P9*(1+Assumptions!$B$60)+Assumptions!$B$61 -> 887.3938 | X9: =V9+W9 -> 1938.6926 | Y9: =ROUND(AA8*0.003,2) -> 72.62 | Z9: 291.67 | AA9: =MAX(0,AA8-Z9) -> 23916.64 | AB9: =ROUND(AD8*0.003,2) -> 72.62 | AC9: 291.67 | AD9: =MAX(0,AD8-AC9) -> 23916.64 | AE9: =Z9+AC9 -> 583.34 | AF9: =AA9+AD9 -> 47833.28 | AG9: =IF(COUNTIFS(SL_Income_Log!$B:$B,TEXT(B9,"0000")&"-"&TEXT(A9,"00"),SL_Income_Log!$C:$C,"youtube")>0,SUMIFS(SL_Income_Log!$D:$D,SL_Income_Log!$B:$B,TEXT(B9,"0000")&"-"&TEXT(A9,"00"),SL_Income_Log!$C:$C,"youtube"),MIN(Assumptions!$B$49+FLOOR((ROW()-2)/6,1)*Assumptions!$B$50,Assumptions!$B$51)) -> 2000 | AH9: =AG9*Assumptions!$B$104 -> 886 | AI9: =AG9-AH9 -> 1114 | AJ9: =SUMIFS(SL_Income_Log!$D:$D,SL_Income_Log!$B:$B,TEXT(B9,"0000")&"-"&TEXT(A9,"00"),SL_Income_Log!$C:$C,"other") -> 0 | AK9: =AN8 -> 2184.736 | AL9: =L9+M9+T9+U9+AI9+AJ9-Y9-Z9-AB9-AC9+IF((Debt_Register!$C$2+Debt_Register!$C$6+Debt_Register!$C$7+Debt_Register!$C$8+Debt_Register!$C$9)>5,X9,0) -> 8679.0612 | AM9: =AK9+AL9 -> 10863.797 | AN9: =MAX(Assumptions!$B$94,MIN(Assumptions!$B$93,AM9-AP9-BE9-BO9-BQ9)) -> 2700.7972 | AO9: =AT8 -> 390532.07 | AP9: =IF(AO9>0,Assumptions!$B$33,0) -> 2281 | AQ9: =AO9*Assumptions!$B$32/12 -> 1265.9748 | AR9: =AP9-AQ9 -> 1015.0252 | AS9: =IF(AND((AV8+AX8+AZ8+BB8+BD8)<5,AO9>0,SUMIF($B$2:B8,B9,$AS$2:AS8)=0,(MAX(0,AN9-10000)+MAX(0,BY8-5000)+MAX(0,BV8-20000))>=21550),21550,0) -> 0 | AT9: =MAX(0,AO9-AR9-AS9) -> 389517.04 | AU9: =IF(AV8>0,MIN(AV8,MAX(300,AM9-AP9-BO9-BQ9-AW9-AY9-BA9-BC9)),0) -> 0 | AV9: =MAX(0,AV8-AU9) -> 0 | AW9: =IF(AX8>0,MIN(250,AX8),0) -> 250 | AX9: =MAX(0,AX8-AW9) -> 0 | AY9: =IF(AZ8>0,MIN(200,AZ8),0) -> 200 | AZ9: =MAX(0,AZ8-AY9) -> 400 | BA9: =IF(AND(AV8<5,BB8>0),MIN(BB8,MAX(0,AM9-AP9-BO9-BQ9-AW9-AY9-BC9)),0) -> 0 | BB9: =MAX(0,BB8-BA9) -> 0 | BC9: =IF(BD8>0,MIN(50,BD8),0) -> 50 | BD9: =MAX(0,BD8-BC9) -> 40 | BE9: =AU9+AW9+AY9+BA9+BC9 -> 500 | BF9: 0 | BG9: =MAX(0,BG8-BF9) -> 5500 | BH9: 0 | BI9: =MAX(0,BI8-BH9) -> 5000 | BJ9: =IF(OR(B9<Assumptions!$B$111,AND(B9=Assumptions!$B$111,A9<=Assumptions!$B$112)),Assumptions!$B$110,0) -> 650 | BK9: =IF(B9<2027,Assumptions!$B$116+IF(OR(A9=4,A9=10),Assumptions!$B$117,0),IF(AND(B9=2027,A9<=4),IF(A9=4,MIN(950,Assumptions!$B$116+Assumptions!$B$117),Assumptions!$B$116),0)) -> 290 | BL9: =IF(OR(B9<2030,AND(B9=2030,A9<8)),Assumptions!$B$118,IF(AND(B9=2030,A9=8),MOD(11000,200),0)) -> 200 | BM9: =IF(OR(B9<Assumptions!$B$120,AND(B9=Assumptions!$B$120,A9<=Assumptions!$B$121)),Assumptions!$B$119,0) -> 132 | BN9: =IF(AND(B9<=Assumptions!$B$123,A9<=Assumptions!$B$124),Assumptions!$B$122,0) -> 0 | BO9: =BF9+BH9+BJ9+BK9+BL9+BM9+BN9 -> 1272 | BP9: =SUMIFS(SL_Budget!$B:$B,SL_Budget!$C:$C,"'"&TEXT(DATE(B9,A9,1),"YYYY-MM")) -> 4110 | BQ9: =MAX(BP9, IFERROR(SUMIFS(ShadowLedger!D:D, ShadowLedger!C:C, ">="&DATE(B9,A9,1), ShadowLedger!C:C, "<"&EOMONTH(DATE(B9,A9,1),0)+1), 0)) -> 4110 | BR9: =BV8 -> 12584.56 | BS9: =IF((AV8+AX8+BB8+AZ8+BD8)>5,0,X9) -> 0 | BT9: =IF(AS9>0,-MAX(0,21550-MAX(0,MAX(0,(AM9-AP9-BE9-BO9-BQ9)-Assumptions!$B$93))-MIN(MAX(0,21550-MAX(0,MAX(0,(AM9-AP9-BE9-BO9-BQ9)-Assumptions!$B$93))),MAX(0,BY8-Assumptions!$B$91))),IF(BY8>=Assumptions!$B$92,MAX(0,(AM9-AP9-BE9-BO9-BQ9)-Assumptions!$B$93),MAX(0,(AM9-AP9-BE9-BO9-BQ9)-Assumptions!$B$93)*Assumptions!$B$99)) -> 0 | BU9: =(BR9+BS9+MAX(0,BT9))*(Assumptions!$B$43-1) -> 85.801532 | BV9: =BR9+BS9+BT9+BU9 -> 12670.362 | BW9: =BY8 -> 0 | BX9: =IF(AS9>0,-MIN(MAX(0,21550-MAX(0,MAX(0,(AM9-AP9-BE9-BO9-BQ9)-Assumptions!$B$93))),MAX(0,BY8-Assumptions!$B$91)),IF(BY8<Assumptions!$B$92,MAX(0,(AM9-AP9-BE9-BO9-BQ9)-Assumptions!$B$93)*Assumptions!$B$98,0)) -> 0 | BY9: =BW9+BX9 -> 0 | BZ9: =IF(A9=1,0,CB8) -> 3544 | CA9: =AH9 -> 886 | CB9: =BZ9+CA9 -> 4430 | CC9: =CC8+(G9+J9)/(Salary_Schedule!E9*12/208) -> 1711.853 | CD9: =CD8+(O9+R9)/(Salary_Schedule!G9*12/208) -> 32.565238 | CE9: =BV9 -> 12670.362 | CF9: =Assumptions!$B$55*(1+Assumptions!$B$56)^((B9-2025)+(A9-1)/12) -> 532403.92 | CG9: =-AT9 -> -389517.04 | CH9: =-(AV9+AX9+BB9+AZ9+BD9+AF9+BG9+BI9) -> -58773.28 | CI9: =CC9*(Salary_Schedule!E9/173.33)*(1-Assumptions!$B$28)+CD9*(Salary_Schedule!G9/173.33)*(1-Assumptions!$B$28) -> 48045.892 | CJ9: =CE9+CF9+CG9+CH9+CI9 -> 144829.85
A10: 9 | B10: 2026 | C10: 09/2026 | D10: =C9 -> 08/2026 | E10: =IF(I10>0,"FAT_BONUS",IF(M10+U10>0,"FAT_RSU","LEAN")) -> LEAN | F10: =Salary_Schedule!E10 -> 7366.42 | G10: =Assumptions!$B$8 -> 200 | H10: =F10*Assumptions!$B$58 -> 736.642 | I10: =Salary_Schedule!F10 -> 0 | J10: =I10*Assumptions!$B$9 -> 0 | K10: =F10-G10-H10+I10-J10 -> 6429.778 | L10: =IF(COUNTIFS(SL_Income_Log!$B:$B,TEXT(B10,"0000")&"-"&TEXT(A10,"00"),SL_Income_Log!$C:$C,"salary",SL_Income_Log!$E:$E,"H")>0,SUMIFS(SL_Income_Log!$D:$D,SL_Income_Log!$B:$B,TEXT(B10,"0000")&"-"&TEXT(A10,"00"),SL_Income_Log!$C:$C,"salary",SL_Income_Log!$E:$E,"H"),K10*(1-Assumptions!$B$102)-Z10-Y10) -> 3494.4468 | M10: =RSU_Schedule!H9 -> 0 | N10: =Salary_Schedule!G10 -> 6195.67 | O10: =Assumptions!$B$19 -> 200 | P10: =N10*Assumptions!$B$59 -> 619.567 | Q10: =Salary_Schedule!H10 -> 0 | R10: =Q10*Assumptions!$B$20 -> 0 | S10: =N10-O10-P10+Q10-R10 -> 5376.103 | T10: =IF(COUNTIFS(SL_Income_Log!$B:$B,TEXT(B10,"0000")&"-"&TEXT(A10,"00"),SL_Income_Log!$C:$C,"salary",SL_Income_Log!$E:$E,"W")>0,SUMIFS(SL_Income_Log!$D:$D,SL_Income_Log!$B:$B,TEXT(B10,"0000")&"-"&TEXT(A10,"00"),SL_Income_Log!$C:$C,"salary",SL_Income_Log!$E:$E,"W"),S10*(1-Assumptions!$B$102)-AC10-AB10) -> 2862.2418 | U10: =RSU_Schedule!M9 -> 0 | V10: =H10*(1+Assumptions!$B$60)+Assumptions!$B$61 -> 1051.2988 | W10: =P10*(1+Assumptions!$B$60)+Assumptions!$B$61 -> 887.3938 | X10: =V10+W10 -> 1938.6926 | Y10: =ROUND(AA9*0.003,2) -> 71.75 | Z10: 291.67 | AA10: =MAX(0,AA9-Z10) -> 23624.97 | AB10: =ROUND(AD9*0.003,2) -> 71.75 | AC10: 291.67 | AD10: =MAX(0,AD9-AC10) -> 23624.97 | AE10: =Z10+AC10 -> 583.34 | AF10: =AA10+AD10 -> 47249.94 | AG10: =IF(COUNTIFS(SL_Income_Log!$B:$B,TEXT(B10,"0000")&"-"&TEXT(A10,"00"),SL_Income_Log!$C:$C,"youtube")>0,SUMIFS(SL_Income_Log!$D:$D,SL_Income_Log!$B:$B,TEXT(B10,"0000")&"-"&TEXT(A10,"00"),SL_Income_Log!$C:$C,"youtube"),MIN(Assumptions!$B$49+FLOOR((ROW()-2)/6,1)*Assumptions!$B$50,Assumptions!$B$51)) -> 2000 | AH10: =AG10*Assumptions!$B$104 -> 886 | AI10: =AG10-AH10 -> 1114 | AJ10: =SUMIFS(SL_Income_Log!$D:$D,SL_Income_Log!$B:$B,TEXT(B10,"0000")&"-"&TEXT(A10,"00"),SL_Income_Log!$C:$C,"other") -> 0 | AK10: =AN9 -> 2700.7972 | AL10: =L10+M10+T10+U10+AI10+AJ10-Y10-Z10-AB10-AC10+IF((Debt_Register!$C$2+Debt_Register!$C$6+Debt_Register!$C$7+Debt_Register!$C$8+Debt_Register!$C$9)>5,X10,0) -> 8682.5412 | AM10: =AK10+AL10 -> 11383.338 | AN10: =MAX(Assumptions!$B$94,MIN(Assumptions!$B$93,AM10-AP10-BE10-BO10-BQ10)) -> 3480.3384 | AO10: =AT9 -> 389517.04 | AP10: =IF(AO10>0,Assumptions!$B$33,0) -> 2281 | AQ10: =AO10*Assumptions!$B$32/12 -> 1262.6844 | AR10: =AP10-AQ10 -> 1018.3156 | AS10: =IF(AND((AV9+AX9+AZ9+BB9+BD9)<5,AO10>0,SUMIF($B$2:B9,B10,$AS$2:AS9)=0,(MAX(0,AN10-10000)+MAX(0,BY9-5000)+MAX(0,BV9-20000))>=21550),21550,0) -> 0 | AT10: =MAX(0,AO10-AR10-AS10) -> 388498.72 | AU10: =IF(AV9>0,MIN(AV9,MAX(300,AM10-AP10-BO10-BQ10-AW10-AY10-BA10-BC10)),0) -> 0 | AV10: =MAX(0,AV9-AU10) -> 0 | AW10: =IF(AX9>0,MIN(250,AX9),0) -> 0 | AX10: =MAX(0,AX9-AW10) -> 0 | AY10: =IF(AZ9>0,MIN(200,AZ9),0) -> 200 | AZ10: =MAX(0,AZ9-AY10) -> 200 | BA10: =IF(AND(AV9<5,BB9>0),MIN(BB9,MAX(0,AM10-AP10-BO10-BQ10-AW10-AY10-BC10)),0) -> 0 | BB10: =MAX(0,BB9-BA10) -> 0 | BC10: =IF(BD9>0,MIN(50,BD9),0) -> 40 | BD10: =MAX(0,BD9-BC10) -> 0 | BE10: =AU10+AW10+AY10+BA10+BC10 -> 240 | BF10: 0 | BG10: =MAX(0,BG9-BF10) -> 5500 | BH10: 0 | BI10: =MAX(0,BI9-BH10) -> 5000 | BJ10: =IF(OR(B10<Assumptions!$B$111,AND(B10=Assumptions!$B$111,A10<=Assumptions!$B$112)),Assumptions!$B$110,0) -> 650 | BK10: =IF(B10<2027,Assumptions!$B$116+IF(OR(A10=4,A10=10),Assumptions!$B$117,0),IF(AND(B10=2027,A10<=4),IF(A10=4,MIN(950,Assumptions!$B$116+Assumptions!$B$117),Assumptions!$B$116),0)) -> 290 | BL10: =IF(OR(B10<2030,AND(B10=2030,A10<8)),Assumptions!$B$118,IF(AND(B10=2030,A10=8),MOD(11000,200),0)) -> 200 | BM10: =IF(OR(B10<Assumptions!$B$120,AND(B10=Assumptions!$B$120,A10<=Assumptions!$B$121)),Assumptions!$B$119,0) -> 132 | BN10: =IF(AND(B10<=Assumptions!$B$123,A10<=Assumptions!$B$124),Assumptions!$B$122,0) -> 0 | BO10: =BF10+BH10+BJ10+BK10+BL10+BM10+BN10 -> 1272 | BP10: =SUMIFS(SL_Budget!$B:$B,SL_Budget!$C:$C,"'"&TEXT(DATE(B10,A10,1),"YYYY-MM")) -> 4110 | BQ10: =MAX(BP10, IFERROR(SUMIFS(ShadowLedger!D:D, ShadowLedger!C:C, ">="&DATE(B10,A10,1), ShadowLedger!C:C, "<"&EOMONTH(DATE(B10,A10,1),0)+1), 0)) -> 4110 | BR10: =BV9 -> 12670.362 | BS10: =IF((AV9+AX9+BB9+AZ9+BD9)>5,0,X10) -> 0 | BT10: =IF(AS10>0,-MAX(0,21550-MAX(0,MAX(0,(AM10-AP10-BE10-BO10-BQ10)-Assumptions!$B$93))-MIN(MAX(0,21550-MAX(0,MAX(0,(AM10-AP10-BE10-BO10-BQ10)-Assumptions!$B$93))),MAX(0,BY9-Assumptions!$B$91))),IF(BY9>=Assumptions!$B$92,MAX(0,(AM10-AP10-BE10-BO10-BQ10)-Assumptions!$B$93),MAX(0,(AM10-AP10-BE10-BO10-BQ10)-Assumptions!$B$93)*Assumptions!$B$99)) -> 0 | BU10: =(BR10+BS10+MAX(0,BT10))*(Assumptions!$B$43-1) -> 86.386527 | BV10: =BR10+BS10+BT10+BU10 -> 12756.748 | BW10: =BY9 -> 0 | BX10: =IF(AS10>0,-MIN(MAX(0,21550-MAX(0,MAX(0,(AM10-AP10-BE10-BO10-BQ10)-Assumptions!$B$93))),MAX(0,BY9-Assumptions!$B$91)),IF(BY9<Assumptions!$B$92,MAX(0,(AM10-AP10-BE10-BO10-BQ10)-Assumptions!$B$93)*Assumptions!$B$98,0)) -> 0 | BY10: =BW10+BX10 -> 0 | BZ10: =IF(A10=1,0,CB9) -> 4430 | CA10: =AH10 -> 886 | CB10: =BZ10+CA10 -> 5316 | CC10: =CC9+(G10+J10)/(Salary_Schedule!E10*12/208) -> 1712.3236 | CD10: =CD9+(O10+R10)/(Salary_Schedule!G10*12/208) -> 33.124768 | CE10: =BV10 -> 12756.748 | CF10: =Assumptions!$B$55*(1+Assumptions!$B$56)^((B10-2025)+(A10-1)/12) -> 533064.89 | CG10: =-AT10 -> -388498.72 | CH10: =-(AV10+AX10+BB10+AZ10+BD10+AF10+BG10+BI10) -> -57949.94 | CI10: =CC10*(Salary_Schedule!E10/173.33)*(1-Assumptions!$B$28)+CD10*(Salary_Schedule!G10/173.33)*(1-Assumptions!$B$28) -> 48071.893 | CJ10: =CE10+CF10+CG10+CH10+CI10 -> 147444.87
A11: 10 | B11: 2026 | C11: 10/2026 | D11: =C10 -> 09/2026 | E11: =IF(I11>0,"FAT_BONUS",IF(M11+U11>0,"FAT_RSU","LEAN")) -> FAT_RSU | F11: =Salary_Schedule!E11 -> 7366.42 | G11: =Assumptions!$B$8 -> 200 | H11: =F11*Assumptions!$B$58 -> 736.642 | I11: =Salary_Schedule!F11 -> 0 | J11: =I11*Assumptions!$B$9 -> 0 | K11: =F11-G11-H11+I11-J11 -> 6429.778 | L11: =IF(COUNTIFS(SL_Income_Log!$B:$B,TEXT(B11,"0000")&"-"&TEXT(A11,"00"),SL_Income_Log!$C:$C,"salary",SL_Income_Log!$E:$E,"H")>0,SUMIFS(SL_Income_Log!$D:$D,SL_Income_Log!$B:$B,TEXT(B11,"0000")&"-"&TEXT(A11,"00"),SL_Income_Log!$C:$C,"salary",SL_Income_Log!$E:$E,"H"),K11*(1-Assumptions!$B$102)-Z11-Y11) -> 3495.3268 | M11: =RSU_Schedule!H10 -> 3959.02 | N11: =Salary_Schedule!G11 -> 6195.67 | O11: =Assumptions!$B$19 -> 200 | P11: =N11*Assumptions!$B$59 -> 619.567 | Q11: =Salary_Schedule!H11 -> 0 | R11: =Q11*Assumptions!$B$20 -> 0 | S11: =N11-O11-P11+Q11-R11 -> 5376.103 | T11: =IF(COUNTIFS(SL_Income_Log!$B:$B,TEXT(B11,"0000")&"-"&TEXT(A11,"00"),SL_Income_Log!$C:$C,"salary",SL_Income_Log!$E:$E,"W")>0,SUMIFS(SL_Income_Log!$D:$D,SL_Income_Log!$B:$B,TEXT(B11,"0000")&"-"&TEXT(A11,"00"),SL_Income_Log!$C:$C,"salary",SL_Income_Log!$E:$E,"W"),S11*(1-Assumptions!$B$102)-AC11-AB11) -> 2863.1218 | U11: =RSU_Schedule!M10 -> 1979.52 | V11: =H11*(1+Assumptions!$B$60)+Assumptions!$B$61 -> 1051.2988 | W11: =P11*(1+Assumptions!$B$60)+Assumptions!$B$61 -> 887.3938 | X11: =V11+W11 -> 1938.6926 | Y11: =ROUND(AA10*0.003,2) -> 70.87 | Z11: 291.67 | AA11: =MAX(0,AA10-Z11) -> 23333.3 | AB11: =ROUND(AD10*0.003,2) -> 70.87 | AC11: 291.67 | AD11: =MAX(0,AD10-AC11) -> 23333.3 | AE11: =Z11+AC11 -> 583.34 | AF11: =AA11+AD11 -> 46666.6 | AG11: =IF(COUNTIFS(SL_Income_Log!$B:$B,TEXT(B11,"0000")&"-"&TEXT(A11,"00"),SL_Income_Log!$C:$C,"youtube")>0,SUMIFS(SL_Income_Log!$D:$D,SL_Income_Log!$B:$B,TEXT(B11,"0000")&"-"&TEXT(A11,"00"),SL_Income_Log!$C:$C,"youtube"),MIN(Assumptions!$B$49+FLOOR((ROW()-2)/6,1)*Assumptions!$B$50,Assumptions!$B$51)) -> 2000 | AH11: =AG11*Assumptions!$B$104 -> 886 | AI11: =AG11-AH11 -> 1114 | AJ11: =SUMIFS(SL_Income_Log!$D:$D,SL_Income_Log!$B:$B,TEXT(B11,"0000")&"-"&TEXT(A11,"00"),SL_Income_Log!$C:$C,"other") -> 0 | AK11: =AN10 -> 3480.3384 | AL11: =L11+M11+T11+U11+AI11+AJ11-Y11-Z11-AB11-AC11+IF((Debt_Register!$C$2+Debt_Register!$C$6+Debt_Register!$C$7+Debt_Register!$C$8+Debt_Register!$C$9)>5,X11,0) -> 14624.601 | AM11: =AK11+AL11 -> 18104.94 | AN11: =MAX(Assumptions!$B$94,MIN(Assumptions!$B$93,AM11-AP11-BE11-BO11-BQ11)) -> 7891.9396 | AO11: =AT10 -> 388498.72 | AP11: =IF(AO11>0,Assumptions!$B$33,0) -> 2281 | AQ11: =AO11*Assumptions!$B$32/12 -> 1259.3834 | AR11: =AP11-AQ11 -> 1021.6166 | AS11: =IF(AND((AV10+AX10+AZ10+BB10+BD10)<5,AO11>0,SUMIF($B$2:B10,B11,$AS$2:AS10)=0,(MAX(0,AN11-10000)+MAX(0,BY10-5000)+MAX(0,BV10-20000))>=21550),21550,0) -> 0 | AT11: =MAX(0,AO11-AR11-AS11) -> 387477.11 | AU11: =IF(AV10>0,MIN(AV10,MAX(300,AM11-AP11-BO11-BQ11-AW11-AY11-BA11-BC11)),0) -> 0 | AV11: =MAX(0,AV10-AU11) -> 0 | AW11: =IF(AX10>0,MIN(250,AX10),0) -> 0 | AX11: =MAX(0,AX10-AW11) -> 0 | AY11: =IF(AZ10>0,MIN(200,AZ10),0) -> 200 | AZ11: =MAX(0,AZ10-AY11) -> 0 | BA11: =IF(AND(AV10<5,BB10>0),MIN(BB10,MAX(0,AM11-AP11-BO11-BQ11-AW11-AY11-BC11)),0) -> 0 | BB11: =MAX(0,BB10-BA11) -> 0 | BC11: =IF(BD10>0,MIN(50,BD10),0) -> 0 | BD11: =MAX(0,BD10-BC11) -> 0 | BE11: =AU11+AW11+AY11+BA11+BC11 -> 200 | BF11: 0 | BG11: =MAX(0,BG10-BF11) -> 5500 | BH11: 0 | BI11: =MAX(0,BI10-BH11) -> 5000 | BJ11: =IF(OR(B11<Assumptions!$B$111,AND(B11=Assumptions!$B$111,A11<=Assumptions!$B$112)),Assumptions!$B$110,0) -> 650 | BK11: =IF(B11<2027,Assumptions!$B$116+IF(OR(A11=4,A11=10),Assumptions!$B$117,0),IF(AND(B11=2027,A11<=4),IF(A11=4,MIN(950,Assumptions!$B$116+Assumptions!$B$117),Assumptions!$B$116),0)) -> 2640 | BL11: =IF(OR(B11<2030,AND(B11=2030,A11<8)),Assumptions!$B$118,IF(AND(B11=2030,A11=8),MOD(11000,200),0)) -> 200 | BM11: =IF(OR(B11<Assumptions!$B$120,AND(B11=Assumptions!$B$120,A11<=Assumptions!$B$121)),Assumptions!$B$119,0) -> 132 | BN11: =IF(AND(B11<=Assumptions!$B$123,A11<=Assumptions!$B$124),Assumptions!$B$122,0) -> 0 | BO11: =BF11+BH11+BJ11+BK11+BL11+BM11+BN11 -> 3622 | BP11: =SUMIFS(SL_Budget!$B:$B,SL_Budget!$C:$C,"'"&TEXT(DATE(B11,A11,1),"YYYY-MM")) -> 4110 | BQ11: =MAX(BP11, IFERROR(SUMIFS(ShadowLedger!D:D, ShadowLedger!C:C, ">="&DATE(B11,A11,1), ShadowLedger!C:C, "<"&EOMONTH(DATE(B11,A11,1),0)+1), 0)) -> 4110 | BR11: =BV10 -> 12756.748 | BS11: =IF((AV10+AX10+BB10+AZ10+BD10)>5,0,X11) -> 0 | BT11: =IF(AS11>0,-MAX(0,21550-MAX(0,MAX(0,(AM11-AP11-BE11-BO11-BQ11)-Assumptions!$B$93))-MIN(MAX(0,21550-MAX(0,MAX(0,(AM11-AP11-BE11-BO11-BQ11)-Assumptions!$B$93))),MAX(0,BY10-Assumptions!$B$91))),IF(BY10>=Assumptions!$B$92,MAX(0,(AM11-AP11-BE11-BO11-BQ11)-Assumptions!$B$93),MAX(0,(AM11-AP11-BE11-BO11-BQ11)-Assumptions!$B$93)*Assumptions!$B$99)) -> 0 | BU11: =(BR11+BS11+MAX(0,BT11))*(Assumptions!$B$43-1) -> 86.97551 | BV11: =BR11+BS11+BT11+BU11 -> 12843.724 | BW11: =BY10 -> 0 | BX11: =IF(AS11>0,-MIN(MAX(0,21550-MAX(0,MAX(0,(AM11-AP11-BE11-BO11-BQ11)-Assumptions!$B$93))),MAX(0,BY10-Assumptions!$B$91)),IF(BY10<Assumptions!$B$92,MAX(0,(AM11-AP11-BE11-BO11-BQ11)-Assumptions!$B$93)*Assumptions!$B$98,0)) -> 0 | BY11: =BW11+BX11 -> 0 | BZ11: =IF(A11=1,0,CB10) -> 5316 | CA11: =AH11 -> 886 | CB11: =BZ11+CA11 -> 6202 | CC11: =CC10+(G11+J11)/(Salary_Schedule!E11*12/208) -> 1712.7942 | CD11: =CD10+(O11+R11)/(Salary_Schedule!G11*12/208) -> 33.684299 | CE11: =BV11 -> 12843.724 | CF11: =Assumptions!$B$55*(1+Assumptions!$B$56)^((B11-2025)+(A11-1)/12) -> 533726.69 | CG11: =-AT11 -> -387477.11 | CH11: =-(AV11+AX11+BB11+AZ11+BD11+AF11+BG11+BI11) -> -57166.6 | CI11: =CC11*(Salary_Schedule!E11/173.33)*(1-Assumptions!$B$28)+CD11*(Salary_Schedule!G11/173.33)*(1-Assumptions!$B$28) -> 48097.893 | CJ11: =CE11+CF11+CG11+CH11+CI11 -> 150024.6
A12: 11 | B12: 2026 | C12: 11/2026 | D12: =C11 -> 10/2026 | E12: =IF(I12>0,"FAT_BONUS",IF(M12+U12>0,"FAT_RSU","LEAN")) -> LEAN | F12: =Salary_Schedule!E12 -> 7366.42 | G12: =Assumptions!$B$8 -> 200 | H12: =F12*Assumptions!$B$58 -> 736.642 | I12: =Salary_Schedule!F12 -> 0 | J12: =I12*Assumptions!$B$9 -> 0 | K12: =F12-G12-H12+I12-J12 -> 6429.778 | L12: =IF(COUNTIFS(SL_Income_Log!$B:$B,TEXT(B12,"0000")&"-"&TEXT(A12,"00"),SL_Income_Log!$C:$C,"salary",SL_Income_Log!$E:$E,"H")>0,SUMIFS(SL_Income_Log!$D:$D,SL_Income_Log!$B:$B,TEXT(B12,"0000")&"-"&TEXT(A12,"00"),SL_Income_Log!$C:$C,"salary",SL_Income_Log!$E:$E,"H"),K12*(1-Assumptions!$B$102)-Z12-Y12) -> 3496.1968 | M12: =RSU_Schedule!H11 -> 0 | N12: =Salary_Schedule!G12 -> 6195.67 | O12: =Assumptions!$B$19 -> 200 | P12: =N12*Assumptions!$B$59 -> 619.567 | Q12: =Salary_Schedule!H12 -> 0 | R12: =Q12*Assumptions!$B$20 -> 0 | S12: =N12-O12-P12+Q12-R12 -> 5376.103 | T12: =IF(COUNTIFS(SL_Income_Log!$B:$B,TEXT(B12,"0000")&"-"&TEXT(A12,"00"),SL_Income_Log!$C:$C,"salary",SL_Income_Log!$E:$E,"W")>0,SUMIFS(SL_Income_Log!$D:$D,SL_Income_Log!$B:$B,TEXT(B12,"0000")&"-"&TEXT(A12,"00"),SL_Income_Log!$C:$C,"salary",SL_Income_Log!$E:$E,"W"),S12*(1-Assumptions!$B$102)-AC12-AB12) -> 2863.9918 | U12: =RSU_Schedule!M11 -> 0 | V12: =H12*(1+Assumptions!$B$60)+Assumptions!$B$61 -> 1051.2988 | W12: =P12*(1+Assumptions!$B$60)+Assumptions!$B$61 -> 887.3938 | X12: =V12+W12 -> 1938.6926 | Y12: =ROUND(AA11*0.003,2) -> 70 | Z12: 291.67 | AA12: =MAX(0,AA11-Z12) -> 23041.63 | AB12: =ROUND(AD11*0.003,2) -> 70 | AC12: 291.67 | AD12: =MAX(0,AD11-AC12) -> 23041.63 | AE12: =Z12+AC12 -> 583.34 | AF12: =AA12+AD12 -> 46083.26 | AG12: =IF(COUNTIFS(SL_Income_Log!$B:$B,TEXT(B12,"0000")&"-"&TEXT(A12,"00"),SL_Income_Log!$C:$C,"youtube")>0,SUMIFS(SL_Income_Log!$D:$D,SL_Income_Log!$B:$B,TEXT(B12,"0000")&"-"&TEXT(A12,"00"),SL_Income_Log!$C:$C,"youtube"),MIN(Assumptions!$B$49+FLOOR((ROW()-2)/6,1)*Assumptions!$B$50,Assumptions!$B$51)) -> 2000 | AH12: =AG12*Assumptions!$B$104 -> 886 | AI12: =AG12-AH12 -> 1114 | AJ12: =SUMIFS(SL_Income_Log!$D:$D,SL_Income_Log!$B:$B,TEXT(B12,"0000")&"-"&TEXT(A12,"00"),SL_Income_Log!$C:$C,"other") -> 0 | AK12: =AN11 -> 7891.9396 | AL12: =L12+M12+T12+U12+AI12+AJ12-Y12-Z12-AB12-AC12+IF((Debt_Register!$C$2+Debt_Register!$C$6+Debt_Register!$C$7+Debt_Register!$C$8+Debt_Register!$C$9)>5,X12,0) -> 8689.5412 | AM12: =AK12+AL12 -> 16581.481 | AN12: =MAX(Assumptions!$B$94,MIN(Assumptions!$B$93,AM12-AP12-BE12-BO12-BQ12)) -> 8918.4808 | AO12: =AT11 -> 387477.11 | AP12: =IF(AO12>0,Assumptions!$B$33,0) -> 2281 | AQ12: =AO12*Assumptions!$B$32/12 -> 1256.0716 | AR12: =AP12-AQ12 -> 1024.9284 | AS12: =IF(AND((AV11+AX11+AZ11+BB11+BD11)<5,AO12>0,SUMIF($B$2:B11,B12,$AS$2:AS11)=0,(MAX(0,AN12-10000)+MAX(0,BY11-5000)+MAX(0,BV11-20000))>=21550),21550,0) -> 0 | AT12: =MAX(0,AO12-AR12-AS12) -> 386452.18 | AU12: =IF(AV11>0,MIN(AV11,MAX(300,AM12-AP12-BO12-BQ12-AW12-AY12-BA12-BC12)),0) -> 0 | AV12: =MAX(0,AV11-AU12) -> 0 | AW12: =IF(AX11>0,MIN(250,AX11),0) -> 0 | AX12: =MAX(0,AX11-AW12) -> 0 | AY12: =IF(AZ11>0,MIN(200,AZ11),0) -> 0 | AZ12: =MAX(0,AZ11-AY12) -> 0 | BA12: =IF(AND(AV11<5,BB11>0),MIN(BB11,MAX(0,AM12-AP12-BO12-BQ12-AW12-AY12-BC12)),0) -> 0 | BB12: =MAX(0,BB11-BA12) -> 0 | BC12: =IF(BD11>0,MIN(50,BD11),0) -> 0 | BD12: =MAX(0,BD11-BC12) -> 0 | BE12: =AU12+AW12+AY12+BA12+BC12 -> 0 | BF12: 0 | BG12: =MAX(0,BG11-BF12) -> 5500 | BH12: 0 | BI12: =MAX(0,BI11-BH12) -> 5000 | BJ12: =IF(OR(B12<Assumptions!$B$111,AND(B12=Assumptions!$B$111,A12<=Assumptions!$B$112)),Assumptions!$B$110,0) -> 650 | BK12: =IF(B12<2027,Assumptions!$B$116+IF(OR(A12=4,A12=10),Assumptions!$B$117,0),IF(AND(B12=2027,A12<=4),IF(A12=4,MIN(950,Assumptions!$B$116+Assumptions!$B$117),Assumptions!$B$116),0)) -> 290 | BL12: =IF(OR(B12<2030,AND(B12=2030,A12<8)),Assumptions!$B$118,IF(AND(B12=2030,A12=8),MOD(11000,200),0)) -> 200 | BM12: =IF(OR(B12<Assumptions!$B$120,AND(B12=Assumptions!$B$120,A12<=Assumptions!$B$121)),Assumptions!$B$119,0) -> 132 | BN12: =IF(AND(B12<=Assumptions!$B$123,A12<=Assumptions!$B$124),Assumptions!$B$122,0) -> 0 | BO12: =BF12+BH12+BJ12+BK12+BL12+BM12+BN12 -> 1272 | BP12: =SUMIFS(SL_Budget!$B:$B,SL_Budget!$C:$C,"'"&TEXT(DATE(B12,A12,1),"YYYY-MM")) -> 4110 | BQ12: =MAX(BP12, IFERROR(SUMIFS(ShadowLedger!D:D, ShadowLedger!C:C, ">="&DATE(B12,A12,1), ShadowLedger!C:C, "<"&EOMONTH(DATE(B12,A12,1),0)+1), 0)) -> 4110 | BR12: =BV11 -> 12843.724 | BS12: =IF((AV11+AX11+BB11+AZ11+BD11)>5,0,X12) -> 1938.6926 | BT12: =IF(AS12>0,-MAX(0,21550-MAX(0,MAX(0,(AM12-AP12-BE12-BO12-BQ12)-Assumptions!$B$93))-MIN(MAX(0,21550-MAX(0,MAX(0,(AM12-AP12-BE12-BO12-BQ12)-Assumptions!$B$93))),MAX(0,BY11-Assumptions!$B$91))),IF(BY11>=Assumptions!$B$92,MAX(0,(AM12-AP12-BE12-BO12-BQ12)-Assumptions!$B$93),MAX(0,(AM12-AP12-BE12-BO12-BQ12)-Assumptions!$B$93)*Assumptions!$B$99)) -> 0 | BU12: =(BR12+BS12+MAX(0,BT12))*(Assumptions!$B$43-1) -> 100.78652 | BV12: =BR12+BS12+BT12+BU12 -> 14883.203 | BW12: =BY11 -> 0 | BX12: =IF(AS12>0,-MIN(MAX(0,21550-MAX(0,MAX(0,(AM12-AP12-BE12-BO12-BQ12)-Assumptions!$B$93))),MAX(0,BY11-Assumptions!$B$91)),IF(BY11<Assumptions!$B$92,MAX(0,(AM12-AP12-BE12-BO12-BQ12)-Assumptions!$B$93)*Assumptions!$B$98,0)) -> 0 | BY12: =BW12+BX12 -> 0 | BZ12: =IF(A12=1,0,CB11) -> 6202 | CA12: =AH12 -> 886 | CB12: =BZ12+CA12 -> 7088 | CC12: =CC11+(G12+J12)/(Salary_Schedule!E12*12/208) -> 1713.2648 | CD12: =CD11+(O12+R12)/(Salary_Schedule!G12*12/208) -> 34.243829 | CE12: =BV12 -> 14883.203 | CF12: =Assumptions!$B$55*(1+Assumptions!$B$56)^((B12-2025)+(A12-1)/12) -> 534389.3 | CG12: =-AT12 -> -386452.18 | CH12: =-(AV12+AX12+BB12+AZ12+BD12+AF12+BG12+BI12) -> -56583.26 | CI12: =CC12*(Salary_Schedule!E12/173.33)*(1-Assumptions!$B$28)+CD12*(Salary_Schedule!G12/173.33)*(1-Assumptions!$B$28) -> 48123.894 | CJ12: =CE12+CF12+CG12+CH12+CI12 -> 154360.96
A13: 12 | B13: 2026 | C13: 12/2026 | D13: =C12 -> 11/2026 | E13: =IF(I13>0,"FAT_BONUS",IF(M13+U13>0,"FAT_RSU","LEAN")) -> LEAN | F13: =Salary_Schedule!E13 -> 7366.42 | G13: =Assumptions!$B$8 -> 200 | H13: =F13*Assumptions!$B$58 -> 736.642 | I13: =Salary_Schedule!F13 -> 0 | J13: =I13*Assumptions!$B$9 -> 0 | K13: =F13-G13-H13+I13-J13 -> 6429.778 | L13: =IF(COUNTIFS(SL_Income_Log!$B:$B,TEXT(B13,"0000")&"-"&TEXT(A13,"00"),SL_Income_Log!$C:$C,"salary",SL_Income_Log!$E:$E,"H")>0,SUMIFS(SL_Income_Log!$D:$D,SL_Income_Log!$B:$B,TEXT(B13,"0000")&"-"&TEXT(A13,"00"),SL_Income_Log!$C:$C,"salary",SL_Income_Log!$E:$E,"H"),K13*(1-Assumptions!$B$102)-Z13-Y13) -> 3497.0768 | M13: =RSU_Schedule!H12 -> 0 | N13: =Salary_Schedule!G13 -> 6195.67 | O13: =Assumptions!$B$19 -> 200 | P13: =N13*Assumptions!$B$59 -> 619.567 | Q13: =Salary_Schedule!H13 -> 0 | R13: =Q13*Assumptions!$B$20 -> 0 | S13: =N13-O13-P13+Q13-R13 -> 5376.103 | T13: =IF(COUNTIFS(SL_Income_Log!$B:$B,TEXT(B13,"0000")&"-"&TEXT(A13,"00"),SL_Income_Log!$C:$C,"salary",SL_Income_Log!$E:$E,"W")>0,SUMIFS(SL_Income_Log!$D:$D,SL_Income_Log!$B:$B,TEXT(B13,"0000")&"-"&TEXT(A13,"00"),SL_Income_Log!$C:$C,"salary",SL_Income_Log!$E:$E,"W"),S13*(1-Assumptions!$B$102)-AC13-AB13) -> 2864.8718 | U13: =RSU_Schedule!M12 -> 0 | V13: =H13*(1+Assumptions!$B$60)+Assumptions!$B$61 -> 1051.2988 | W13: =P13*(1+Assumptions!$B$60)+Assumptions!$B$61 -> 887.3938 | X13: =V13+W13 -> 1938.6926 | Y13: =ROUND(AA12*0.003,2) -> 69.12 | Z13: 291.67 | AA13: =MAX(0,AA12-Z13) -> 22749.96 | AB13: =ROUND(AD12*0.003,2) -> 69.12 | AC13: 291.67 | AD13: =MAX(0,AD12-AC13) -> 22749.96 | AE13: =Z13+AC13 -> 583.34 | AF13: =AA13+AD13 -> 45499.92 | AG13: =IF(COUNTIFS(SL_Income_Log!$B:$B,TEXT(B13,"0000")&"-"&TEXT(A13,"00"),SL_Income_Log!$C:$C,"youtube")>0,SUMIFS(SL_Income_Log!$D:$D,SL_Income_Log!$B:$B,TEXT(B13,"0000")&"-"&TEXT(A13,"00"),SL_Income_Log!$C:$C,"youtube"),MIN(Assumptions!$B$49+FLOOR((ROW()-2)/6,1)*Assumptions!$B$50,Assumptions!$B$51)) -> 2000 | AH13: =AG13*Assumptions!$B$104 -> 886 | AI13: =AG13-AH13 -> 1114 | AJ13: =SUMIFS(SL_Income_Log!$D:$D,SL_Income_Log!$B:$B,TEXT(B13,"0000")&"-"&TEXT(A13,"00"),SL_Income_Log!$C:$C,"other") -> 0 | AK13: =AN12 -> 8918.4808 | AL13: =L13+M13+T13+U13+AI13+AJ13-Y13-Z13-AB13-AC13+IF((Debt_Register!$C$2+Debt_Register!$C$6+Debt_Register!$C$7+Debt_Register!$C$8+Debt_Register!$C$9)>5,X13,0) -> 8693.0612 | AM13: =AK13+AL13 -> 17611.542 | AN13: =MAX(Assumptions!$B$94,MIN(Assumptions!$B$93,AM13-AP13-BE13-BO13-BQ13)) -> 9948.542 | AO13: =AT12 -> 386452.18 | AP13: =IF(AO13>0,Assumptions!$B$33,0) -> 2281 | AQ13: =AO13*Assumptions!$B$32/12 -> 1252.7491 | AR13: =AP13-AQ13 -> 1028.2509 | AS13: =IF(AND((AV12+AX12+AZ12+BB12+BD12)<5,AO13>0,SUMIF($B$2:B12,B13,$AS$2:AS12)=0,(MAX(0,AN13-10000)+MAX(0,BY12-5000)+MAX(0,BV12-20000))>=21550),21550,0) -> 0 | AT13: =MAX(0,AO13-AR13-AS13) -> 385423.93 | AU13: =IF(AV12>0,MIN(AV12,MAX(300,AM13-AP13-BO13-BQ13-AW13-AY13-BA13-BC13)),0) -> 0 | AV13: =MAX(0,AV12-AU13) -> 0 | AW13: =IF(AX12>0,MIN(250,AX12),0) -> 0 | AX13: =MAX(0,AX12-AW13) -> 0 | AY13: =IF(AZ12>0,MIN(200,AZ12),0) -> 0 | AZ13: =MAX(0,AZ12-AY13) -> 0 | BA13: =IF(AND(AV12<5,BB12>0),MIN(BB12,MAX(0,AM13-AP13-BO13-BQ13-AW13-AY13-BC13)),0) -> 0 | BB13: =MAX(0,BB12-BA13) -> 0 | BC13: =IF(BD12>0,MIN(50,BD12),0) -> 0 | BD13: =MAX(0,BD12-BC13) -> 0 | BE13: =AU13+AW13+AY13+BA13+BC13 -> 0 | BF13: 0 | BG13: =MAX(0,BG12-BF13) -> 5500 | BH13: 0 | BI13: =MAX(0,BI12-BH13) -> 5000 | BJ13: =IF(OR(B13<Assumptions!$B$111,AND(B13=Assumptions!$B$111,A13<=Assumptions!$B$112)),Assumptions!$B$110,0) -> 650 | BK13: =IF(B13<2027,Assumptions!$B$116+IF(OR(A13=4,A13=10),Assumptions!$B$117,0),IF(AND(B13=2027,A13<=4),IF(A13=4,MIN(950,Assumptions!$B$116+Assumptions!$B$117),Assumptions!$B$116),0)) -> 290 | BL13: =IF(OR(B13<2030,AND(B13=2030,A13<8)),Assumptions!$B$118,IF(AND(B13=2030,A13=8),MOD(11000,200),0)) -> 200 | BM13: =IF(OR(B13<Assumptions!$B$120,AND(B13=Assumptions!$B$120,A13<=Assumptions!$B$121)),Assumptions!$B$119,0) -> 132 | BN13: =IF(AND(B13<=Assumptions!$B$123,A13<=Assumptions!$B$124),Assumptions!$B$122,0) -> 0 | BO13: =BF13+BH13+BJ13+BK13+BL13+BM13+BN13 -> 1272 | BP13: =SUMIFS(SL_Budget!$B:$B,SL_Budget!$C:$C,"'"&TEXT(DATE(B13,A13,1),"YYYY-MM")) -> 4110 | BQ13: =MAX(BP13, IFERROR(SUMIFS(ShadowLedger!D:D, ShadowLedger!C:C, ">="&DATE(B13,A13,1), ShadowLedger!C:C, "<"&EOMONTH(DATE(B13,A13,1),0)+1), 0)) -> 4110 | BR13: =BV12 -> 14883.203 | BS13: =IF((AV12+AX12+BB12+AZ12+BD12)>5,0,X13) -> 1938.6926 | BT13: =IF(AS13>0,-MAX(0,21550-MAX(0,MAX(0,(AM13-AP13-BE13-BO13-BQ13)-Assumptions!$B$93))-MIN(MAX(0,21550-MAX(0,MAX(0,(AM13-AP13-BE13-BO13-BQ13)-Assumptions!$B$93))),MAX(0,BY12-Assumptions!$B$91))),IF(BY12>=Assumptions!$B$92,MAX(0,(AM13-AP13-BE13-BO13-BQ13)-Assumptions!$B$93),MAX(0,(AM13-AP13-BE13-BO13-BQ13)-Assumptions!$B$93)*Assumptions!$B$99)) -> 0 | BU13: =(BR13+BS13+MAX(0,BT13))*(Assumptions!$B$43-1) -> 114.69168 | BV13: =BR13+BS13+BT13+BU13 -> 16936.587 | BW13: =BY12 -> 0 | BX13: =IF(AS13>0,-MIN(MAX(0,21550-MAX(0,MAX(0,(AM13-AP13-BE13-BO13-BQ13)-Assumptions!$B$93))),MAX(0,BY12-Assumptions!$B$91)),IF(BY12<Assumptions!$B$92,MAX(0,(AM13-AP13-BE13-BO13-BQ13)-Assumptions!$B$93)*Assumptions!$B$98,0)) -> 0 | BY13: =BW13+BX13 -> 0 | BZ13: =IF(A13=1,0,CB12) -> 7088 | CA13: =AH13 -> 886 | CB13: =BZ13+CA13 -> 7974 | CC13: =CC12+(G13+J13)/(Salary_Schedule!E13*12/208) -> 1713.7354 | CD13: =CD12+(O13+R13)/(Salary_Schedule!G13*12/208) -> 34.80336 | CE13: =BV13 -> 16936.587 | CF13: =Assumptions!$B$55*(1+Assumptions!$B$56)^((B13-2025)+(A13-1)/12) -> 535052.74 | CG13: =-AT13 -> -385423.93 | CH13: =-(AV13+AX13+BB13+AZ13+BD13+AF13+BG13+BI13) -> -55999.92 | CI13: =CC13*(Salary_Schedule!E13/173.33)*(1-Assumptions!$B$28)+CD13*(Salary_Schedule!G13/173.33)*(1-Assumptions!$B$28) -> 48149.894 | CJ13: =CE13+CF13+CG13+CH13+CI13 -> 158715.37
A14: 1 | B14: 2027 | C14: 01/2027 | D14: =C13 -> 12/2026 | E14: =IF(I14>0,"FAT_BONUS",IF(M14+U14>0,"FAT_RSU","LEAN")) -> FAT_RSU | F14: =Salary_Schedule!E14 -> 7734.74 | G14: =Assumptions!$B$8 -> 200 | H14: =F14*Assumptions!$B$58 -> 773.474 | I14: =Salary_Schedule!F14 -> 0 | J14: =I14*Assumptions!$B$9 -> 0 | K14: =F14-G14-H14+I14-J14 -> 6761.266 | L14: =IF(COUNTIFS(SL_Income_Log!$B:$B,TEXT(B14,"0000")&"-"&TEXT(A14,"00"),SL_Income_Log!$C:$C,"salary",SL_Income_Log!$E:$E,"H")>0,SUMIFS(SL_Income_Log!$D:$D,SL_Income_Log!$B:$B,TEXT(B14,"0000")&"-"&TEXT(A14,"00"),SL_Income_Log!$C:$C,"salary",SL_Income_Log!$E:$E,"H"),K14*(1-Assumptions!$B$102)-Z14-Y14) -> 3696.8396 | M14: =RSU_Schedule!H13 -> 3959.02 | N14: =Salary_Schedule!G14 -> 6412.51 | O14: =Assumptions!$B$19 -> 200 | P14: =N14*Assumptions!$B$59 -> 641.251 | Q14: =Salary_Schedule!H14 -> 0 | R14: =Q14*Assumptions!$B$20 -> 0 | S14: =N14-O14-P14+Q14-R14 -> 5571.259 | T14: =IF(COUNTIFS(SL_Income_Log!$B:$B,TEXT(B14,"0000")&"-"&TEXT(A14,"00"),SL_Income_Log!$C:$C,"salary",SL_Income_Log!$E:$E,"W")>0,SUMIFS(SL_Income_Log!$D:$D,SL_Income_Log!$B:$B,TEXT(B14,"0000")&"-"&TEXT(A14,"00"),SL_Income_Log!$C:$C,"salary",SL_Income_Log!$E:$E,"W"),S14*(1-Assumptions!$B$102)-AC14-AB14) -> 2982.8354 | U14: =RSU_Schedule!M13 -> 1979.52 | V14: =H14*(1+Assumptions!$B$60)+Assumptions!$B$61 -> 1102.8636 | W14: =P14*(1+Assumptions!$B$60)+Assumptions!$B$61 -> 917.7514 | X14: =V14+W14 -> 2020.615 | Y14: =ROUND(AA13*0.003,2) -> 68.25 | Z14: 291.67 | AA14: =MAX(0,AA13-Z14) -> 22458.29 | AB14: =ROUND(AD13*0.003,2) -> 68.25 | AC14: 291.67 | AD14: =MAX(0,AD13-AC14) -> 22458.29 | AE14: =Z14+AC14 -> 583.34 | AF14: =AA14+AD14 -> 44916.58 | AG14: =IF(COUNTIFS(SL_Income_Log!$B:$B,TEXT(B14,"0000")&"-"&TEXT(A14,"00"),SL_Income_Log!$C:$C,"youtube")>0,SUMIFS(SL_Income_Log!$D:$D,SL_Income_Log!$B:$B,TEXT(B14,"0000")&"-"&TEXT(A14,"00"),SL_Income_Log!$C:$C,"youtube"),MIN(Assumptions!$B$49+FLOOR((ROW()-2)/6,1)*Assumptions!$B$50,Assumptions!$B$51)) -> 3000 | AH14: =AG14*Assumptions!$B$104 -> 1329 | AI14: =AG14-AH14 -> 1671 | AJ14: =SUMIFS(SL_Income_Log!$D:$D,SL_Income_Log!$B:$B,TEXT(B14,"0000")&"-"&TEXT(A14,"00"),SL_Income_Log!$C:$C,"other") -> 0 | AK14: =AN13 -> 9948.542 | AL14: =L14+M14+T14+U14+AI14+AJ14-Y14-Z14-AB14-AC14+IF((Debt_Register!$C$2+Debt_Register!$C$6+Debt_Register!$C$7+Debt_Register!$C$8+Debt_Register!$C$9)>5,X14,0) -> 15589.99 | AM14: =AK14+AL14 -> 25538.532 | AN14: =MAX(Assumptions!$B$94,MIN(Assumptions!$B$93,AM14-AP14-BE14-BO14-BQ14)) -> 10000 | AO14: =AT13 -> 385423.93 | AP14: =IF(AO14>0,Assumptions!$B$33,0) -> 2281 | AQ14: =AO14*Assumptions!$B$32/12 -> 1249.4159 | AR14: =AP14-AQ14 -> 1031.5841 | AS14: =IF(AND((AV13+AX13+AZ13+BB13+BD13)<5,AO14>0,SUMIF($B$2:B13,B14,$AS$2:AS13)=0,(MAX(0,AN14-10000)+MAX(0,BY13-5000)+MAX(0,BV13-20000))>=21550),21550,0) -> 0 | AT14: =MAX(0,AO14-AR14-AS14) -> 384392.34 | AU14: =IF(AV13>0,MIN(AV13,MAX(300,AM14-AP14-BO14-BQ14-AW14-AY14-BA14-BC14)),0) -> 0 | AV14: =MAX(0,AV13-AU14) -> 0 | AW14: =IF(AX13>0,MIN(250,AX13),0) -> 0 | AX14: =MAX(0,AX13-AW14) -> 0 | AY14: =IF(AZ13>0,MIN(200,AZ13),0) -> 0 | AZ14: =MAX(0,AZ13-AY14) -> 0 | BA14: =IF(AND(AV13<5,BB13>0),MIN(BB13,MAX(0,AM14-AP14-BO14-BQ14-AW14-AY14-BC14)),0) -> 0 | BB14: =MAX(0,BB13-BA14) -> 0 | BC14: =IF(BD13>0,MIN(50,BD13),0) -> 0 | BD14: =MAX(0,BD13-BC14) -> 0 | BE14: =AU14+AW14+AY14+BA14+BC14 -> 0 | BF14: 0 | BG14: =MAX(0,BG13-BF14) -> 5500 | BH14: 0 | BI14: =MAX(0,BI13-BH14) -> 5000 | BJ14: =IF(OR(B14<Assumptions!$B$111,AND(B14=Assumptions!$B$111,A14<=Assumptions!$B$112)),Assumptions!$B$110,0) -> 650 | BK14: =IF(B14<2027,Assumptions!$B$116+IF(OR(A14=4,A14=10),Assumptions!$B$117,0),IF(AND(B14=2027,A14<=4),IF(A14=4,MIN(950,Assumptions!$B$116+Assumptions!$B$117),Assumptions!$B$116),0)) -> 290 | BL14: =IF(OR(B14<2030,AND(B14=2030,A14<8)),Assumptions!$B$118,IF(AND(B14=2030,A14=8),MOD(11000,200),0)) -> 200 | BM14: =IF(OR(B14<Assumptions!$B$120,AND(B14=Assumptions!$B$120,A14<=Assumptions!$B$121)),Assumptions!$B$119,0) -> 132 | BN14: =IF(AND(B14<=Assumptions!$B$123,A14<=Assumptions!$B$124),Assumptions!$B$122,0) -> 0 | BO14: =BF14+BH14+BJ14+BK14+BL14+BM14+BN14 -> 1272 | BP14: =SUMIFS(SL_Budget!$B:$B,SL_Budget!$C:$C,"'"&TEXT(DATE(B14,A14,1),"YYYY-MM")) -> 4237 | BQ14: =MAX(BP14, IFERROR(SUMIFS(ShadowLedger!D:D, ShadowLedger!C:C, ">="&DATE(B14,A14,1), ShadowLedger!C:C, "<"&EOMONTH(DATE(B14,A14,1),0)+1), 0)) -> 4237 | BR14: =BV13 -> 16936.587 | BS14: =IF((AV13+AX13+BB13+AZ13+BD13)>5,0,X14) -> 2020.615 | BT14: =IF(AS14>0,-MAX(0,21550-MAX(0,MAX(0,(AM14-AP14-BE14-BO14-BQ14)-Assumptions!$B$93))-MIN(MAX(0,21550-MAX(0,MAX(0,(AM14-AP14-BE14-BO14-BQ14)-Assumptions!$B$93))),MAX(0,BY13-Assumptions!$B$91))),IF(BY13>=Assumptions!$B$92,MAX(0,(AM14-AP14-BE14-BO14-BQ14)-Assumptions!$B$93),MAX(0,(AM14-AP14-BE14-BO14-BQ14)-Assumptions!$B$93)*Assumptions!$B$99)) -> 6198.8256 | BU14: =(BR14+BS14+MAX(0,BT14))*(Assumptions!$B$43-1) -> 171.5138 | BV14: =BR14+BS14+BT14+BU14 -> 25327.542 | BW14: =BY13 -> 0 | BX14: =IF(AS14>0,-MIN(MAX(0,21550-MAX(0,MAX(0,(AM14-AP14-BE14-BO14-BQ14)-Assumptions!$B$93))),MAX(0,BY13-Assumptions!$B$91)),IF(BY13<Assumptions!$B$92,MAX(0,(AM14-AP14-BE14-BO14-BQ14)-Assumptions!$B$93)*Assumptions!$B$98,0)) -> 1549.7064 | BY14: =BW14+BX14 -> 1549.7064 | BZ14: =IF(A14=1,0,CB13) -> 0 | CA14: =AH14 -> 1329 | CB14: =BZ14+CA14 -> 1329 | CC14: =CC13+(G14+J14)/(Salary_Schedule!E14*12/208) -> 1714.1836 | CD14: =CD13+(O14+R14)/(Salary_Schedule!G14*12/208) -> 35.34397 | CE14: =BV14 -> 25327.542 | CF14: =Assumptions!$B$55*(1+Assumptions!$B$56)^((B14-2025)+(A14-1)/12) -> 535717 | CG14: =-AT14 -> -384392.34 | CH14: =-(AV14+AX14+BB14+AZ14+BD14+AF14+BG14+BI14) -> -55416.58 | CI14: =CC14*(Salary_Schedule!E14/173.33)*(1-Assumptions!$B$28)+CD14*(Salary_Schedule!G14/173.33)*(1-Assumptions!$B$28) -> 50571.252 | CJ14: =CE14+CF14+CG14+CH14+CI14 -> 171806.87
... A85: 12 | B85: 2032 | C85: 12/2032 | D85: =C84 -> 11/2032 | E85: =IF(I85>0,"FAT_BONUS",IF(M85+U85>0,"FAT_RSU","LEAN")) -> LEAN | F85: =Salary_Schedule!E85 -> 9871.7 | G85: =Assumptions!$B$8 -> 200 | H85: =F85*Assumptions!$B$58 -> 987.17 | I85: =Salary_Schedule!F85 -> 0 | J85: =I85*Assumptions!$B$9 -> 0 | K85: =F85-G85-H85+I85-J85 -> 8684.53 | L85: =IF(COUNTIFS(SL_Income_Log!$B:$B,TEXT(B85,"0000")&"-"&TEXT(A85,"00"),SL_Income_Log!$C:$C,"salary",SL_Income_Log!$E:$E,"H")>0,SUMIFS(SL_Income_Log!$D:$D,SL_Income_Log!$B:$B,TEXT(B85,"0000")&"-"&TEXT(A85,"00"),SL_Income_Log!$C:$C,"salary",SL_Income_Log!$E:$E,"H"),K85*(1-Assumptions!$B$102)-Z85-Y85) -> 4912.928 | M85: =RSU_Schedule!H84 -> 0 | N85: =Salary_Schedule!G85 -> 7616.06 | O85: =Assumptions!$B$19 -> 200 | P85: =N85*Assumptions!$B$59 -> 761.606 | Q85: =Salary_Schedule!H85 -> 0 | R85: =Q85*Assumptions!$B$20 -> 0 | S85: =N85-O85-P85+Q85-R85 -> 6654.454 | T85: =IF(COUNTIFS(SL_Income_Log!$B:$B,TEXT(B85,"0000")&"-"&TEXT(A85,"00"),SL_Income_Log!$C:$C,"salary",SL_Income_Log!$E:$E,"W")>0,SUMIFS(SL_Income_Log!$D:$D,SL_Income_Log!$B:$B,TEXT(B85,"0000")&"-"&TEXT(A85,"00"),SL_Income_Log!$C:$C,"salary",SL_Income_Log!$E:$E,"W"),S85*(1-Assumptions!$B$102)-AC85-AB85) -> 3694.8824 | U85: =RSU_Schedule!M84 -> 0 | V85: =H85*(1+Assumptions!$B$60)+Assumptions!$B$61 -> 1402.038 | W85: =P85*(1+Assumptions!$B$60)+Assumptions!$B$61 -> 1086.2484 | X85: =V85+W85 -> 2488.2864 | Y85: =ROUND(AA84*0.003,2) -> 6.12 | Z85: 291.67 | AA85: =MAX(0,AA84-Z85) -> 1749.72 | AB85: =ROUND(AD84*0.003,2) -> 6.12 | AC85: 291.67 | AD85: =MAX(0,AD84-AC85) -> 1749.72 | AE85: =Z85+AC85 -> 583.34 | AF85: =AA85+AD85 -> 3499.44 | AG85: =IF(COUNTIFS(SL_Income_Log!$B:$B,TEXT(B85,"0000")&"-"&TEXT(A85,"00"),SL_Income_Log!$C:$C,"youtube")>0,SUMIFS(SL_Income_Log!$D:$D,SL_Income_Log!$B:$B,TEXT(B85,"0000")&"-"&TEXT(A85,"00"),SL_Income_Log!$C:$C,"youtube"),MIN(Assumptions!$B$49+FLOOR((ROW()-2)/6,1)*Assumptions!$B$50,Assumptions!$B$51)) -> 14000 | AH85: =AG85*Assumptions!$B$104 -> 6202 | AI85: =AG85-AH85 -> 7798 | AJ85: =SUMIFS(SL_Income_Log!$D:$D,SL_Income_Log!$B:$B,TEXT(B85,"0000")&"-"&TEXT(A85,"00"),SL_Income_Log!$C:$C,"other") -> 0 | AK85: =AN84 -> 10000 | AL85: =L85+M85+T85+U85+AI85+AJ85-Y85-Z85-AB85-AC85+IF((Debt_Register!$C$2+Debt_Register!$C$6+Debt_Register!$C$7+Debt_Register!$C$8+Debt_Register!$C$9)>5,X85,0) -> 18298.517 | AM85: =AK85+AL85 -> 28298.517 | AN85: =MAX(Assumptions!$B$94,MIN(Assumptions!$B$93,AM85-AP85-BE85-BO85-BQ85)) -> 10000 | AO85: =AT84 -> 156069.39 | AP85: =IF(AO85>0,Assumptions!$B$33,0) -> 2281 | AQ85: =AO85*Assumptions!$B$32/12 -> 505.92496 | AR85: =AP85-AQ85 -> 1775.075 | AS85: =IF(AND((AV84+AX84+AZ84+BB84+BD84)<5,AO85>0,SUMIF($B$2:B84,B85,$AS$2:AS84)=0,(MAX(0,AN85-10000)+MAX(0,BY84-5000)+MAX(0,BV84-20000))>=21550),21550,0) -> 0 | AT85: =MAX(0,AO85-AR85-AS85) -> 154294.32 | AU85: =IF(AV84>0,MIN(AV84,MAX(300,AM85-AP85-BO85-BQ85-AW85-AY85-BA85-BC85)),0) -> 0 | AV85: =MAX(0,AV84-AU85) -> 0 | AW85: =IF(AX84>0,MIN(250,AX84),0) -> 0 | AX85: =MAX(0,AX84-AW85) -> 0 | AY85: =IF(AZ84>0,MIN(200,AZ84),0) -> 0 | AZ85: =MAX(0,AZ84-AY85) -> 0 | BA85: =IF(AND(AV84<5,BB84>0),MIN(BB84,MAX(0,AM85-AP85-BO85-BQ85-AW85-AY85-BC85)),0) -> 0 | BB85: =MAX(0,BB84-BA85) -> 0 | BC85: =IF(BD84>0,MIN(50,BD84),0) -> 0 | BD85: =MAX(0,BD84-BC85) -> 0 | BE85: =AU85+AW85+AY85+BA85+BC85 -> 0 | BF85: 0 | BG85: =MAX(0,BG84-BF85) -> 5500 | BH85: 0 | BI85: =MAX(0,BI84-BH85) -> 5000 | BJ85: =IF(OR(B85<Assumptions!$B$111,AND(B85=Assumptions!$B$111,A85<=Assumptions!$B$112)),Assumptions!$B$110,0) -> 0 | BK85: =IF(B85<2027,Assumptions!$B$116+IF(OR(A85=4,A85=10),Assumptions!$B$117,0),IF(AND(B85=2027,A85<=4),IF(A85=4,MIN(950,Assumptions!$B$116+Assumptions!$B$117),Assumptions!$B$116),0)) -> 0 | BL85: =IF(OR(B85<2030,AND(B85=2030,A85<8)),Assumptions!$B$118,IF(AND(B85=2030,A85=8),MOD(11000,200),0)) -> 0 | BM85: =IF(OR(B85<Assumptions!$B$120,AND(B85=Assumptions!$B$120,A85<=Assumptions!$B$121)),Assumptions!$B$119,0) -> 0 | BN85: =IF(AND(B85<=Assumptions!$B$123,A85<=Assumptions!$B$124),Assumptions!$B$122,0) -> 0 | BO85: =BF85+BH85+BJ85+BK85+BL85+BM85+BN85 -> 0 | BP85: =SUMIFS(SL_Budget!$B:$B,SL_Budget!$C:$C,"'"&TEXT(DATE(B85,A85,1),"YYYY-MM")) -> 4908 | BQ85: =MAX(BP85, IFERROR(SUMIFS(ShadowLedger!D:D, ShadowLedger!C:C, ">="&DATE(B85,A85,1), ShadowLedger!C:C, "<"&EOMONTH(DATE(B85,A85,1),0)+1), 0)) -> 4908 | BR85: =BV84 -> 818305.55 | BS85: =IF((AV84+AX84+BB84+AZ84+BD84)>5,0,X85) -> 2488.2864 | BT85: =IF(AS85>0,-MAX(0,21550-MAX(0,MAX(0,(AM85-AP85-BE85-BO85-BQ85)-Assumptions!$B$93))-MIN(MAX(0,21550-MAX(0,MAX(0,(AM85-AP85-BE85-BO85-BQ85)-Assumptions!$B$93))),MAX(0,BY84-Assumptions!$B$91))),IF(BY84>=Assumptions!$B$92,MAX(0,(AM85-AP85-BE85-BO85-BQ85)-Assumptions!$B$93),MAX(0,(AM85-AP85-BE85-BO85-BQ85)-Assumptions!$B$93)*Assumptions!$B$99)) -> 11109.517 | BU85: =(BR85+BS85+MAX(0,BT85))*(Assumptions!$B$43-1) -> 5671.9171 | BV85: =BR85+BS85+BT85+BU85 -> 837575.28 | BW85: =BY84 -> 18713.476 | BX85: =IF(AS85>0,-MIN(MAX(0,21550-MAX(0,MAX(0,(AM85-AP85-BE85-BO85-BQ85)-Assumptions!$B$93))),MAX(0,BY84-Assumptions!$B$91)),IF(BY84<Assumptions!$B$92,MAX(0,(AM85-AP85-BE85-BO85-BQ85)-Assumptions!$B$93)*Assumptions!$B$98,0)) -> 0 | BY85: =BW85+BX85 -> 18713.476 | BZ85: =IF(A85=1,0,CB84) -> 65564 | CA85: =AH85 -> 6202 | CB85: =BZ85+CA85 -> 71766 | CC85: =CC84+(G85+J85)/(Salary_Schedule!E85*12/208) -> 1790.928 | CD85: =CD84+(O85+R85)/(Salary_Schedule!G85*12/208) -> 119.11524 | CE85: =BV85 -> 837575.28 | CF85: =Assumptions!$B$55*(1+Assumptions!$B$56)^((B85-2025)+(A85-1)/12) -> 585049.81 | CG85: =-AT85 -> -154294.32 | CH85: =-(AV85+AX85+BB85+AZ85+BD85+AF85+BG85+BI85) -> -13999.44 | CI85: =CC85*(Salary_Schedule!E85/173.33)*(1-Assumptions!$B$28)+CD85*(Salary_Schedule!G85/173.33)*(1-Assumptions!$B$28) -> 69701.44 | CJ85: =CE85+CF85+CG85+CH85+CI85 -> 1324032.8
A86: 1 | B86: 2033 | C86: 01/2033 | D86: =C85 -> 12/2032 | E86: =IF(I86>0,"FAT_BONUS",IF(M86+U86>0,"FAT_RSU","LEAN")) -> FAT_RSU | F86: =Salary_Schedule!E86 -> 10365.29 | G86: =Assumptions!$B$8 -> 200 | H86: =F86*Assumptions!$B$58 -> 1036.529 | I86: =Salary_Schedule!F86 -> 0 | J86: =I86*Assumptions!$B$9 -> 0 | K86: =F86-G86-H86+I86-J86 -> 9128.761 | L86: =IF(COUNTIFS(SL_Income_Log!$B:$B,TEXT(B86,"0000")&"-"&TEXT(A86,"00"),SL_Income_Log!$C:$C,"salary",SL_Income_Log!$E:$E,"H")>0,SUMIFS(SL_Income_Log!$D:$D,SL_Income_Log!$B:$B,TEXT(B86,"0000")&"-"&TEXT(A86,"00"),SL_Income_Log!$C:$C,"salary",SL_Income_Log!$E:$E,"H"),K86*(1-Assumptions!$B$102)-Z86-Y86) -> 5180.3366 | M86: =RSU_Schedule!H85 -> 2784.99 | N86: =Salary_Schedule!G86 -> 7882.62 | O86: =Assumptions!$B$19 -> 200 | P86: =N86*Assumptions!$B$59 -> 788.262 | Q86: =Salary_Schedule!H86 -> 0 | R86: =Q86*Assumptions!$B$20 -> 0 | S86: =N86-O86-P86+Q86-R86 -> 6894.358 | T86: =IF(COUNTIFS(SL_Income_Log!$B:$B,TEXT(B86,"0000")&"-"&TEXT(A86,"00"),SL_Income_Log!$C:$C,"salary",SL_Income_Log!$E:$E,"W")>0,SUMIFS(SL_Income_Log!$D:$D,SL_Income_Log!$B:$B,TEXT(B86,"0000")&"-"&TEXT(A86,"00"),SL_Income_Log!$C:$C,"salary",SL_Income_Log!$E:$E,"W"),S86*(1-Assumptions!$B$102)-AC86-AB86) -> 3839.6948 | U86: =RSU_Schedule!M85 -> 1392.51 | V86: =H86*(1+Assumptions!$B$60)+Assumptions!$B$61 -> 1471.1406 | W86: =P86*(1+Assumptions!$B$60)+Assumptions!$B$61 -> 1123.5668 | X86: =V86+W86 -> 2594.7074 | Y86: =ROUND(AA85*0.003,2) -> 5.25 | Z86: 291.67 | AA86: =MAX(0,AA85-Z86) -> 1458.05 | AB86: =ROUND(AD85*0.003,2) -> 5.25 | AC86: 291.67 | AD86: =MAX(0,AD85-AC86) -> 1458.05 | AE86: =Z86+AC86 -> 583.34 | AF86: =AA86+AD86 -> 2916.1 | AG86: =IF(COUNTIFS(SL_Income_Log!$B:$B,TEXT(B86,"0000")&"-"&TEXT(A86,"00"),SL_Income_Log!$C:$C,"youtube")>0,SUMIFS(SL_Income_Log!$D:$D,SL_Income_Log!$B:$B,TEXT(B86,"0000")&"-"&TEXT(A86,"00"),SL_Income_Log!$C:$C,"youtube"),MIN(Assumptions!$B$49+FLOOR((ROW()-2)/6,1)*Assumptions!$B$50,Assumptions!$B$51)) -> 15000 | AH86: =AG86*Assumptions!$B$104 -> 6645 | AI86: =AG86-AH86 -> 8355 | AJ86: =SUMIFS(SL_Income_Log!$D:$D,SL_Income_Log!$B:$B,TEXT(B86,"0000")&"-"&TEXT(A86,"00"),SL_Income_Log!$C:$C,"other") -> 0 | AK86: =AN85 -> 10000 | AL86: =L86+M86+T86+U86+AI86+AJ86-Y86-Z86-AB86-AC86+IF((Debt_Register!$C$2+Debt_Register!$C$6+Debt_Register!$C$7+Debt_Register!$C$8+Debt_Register!$C$9)>5,X86,0) -> 23553.399 | AM86: =AK86+AL86 -> 33553.399 | AN86: =MAX(Assumptions!$B$94,MIN(Assumptions!$B$93,AM86-AP86-BE86-BO86-BQ86)) -> 10000 | AO86: =AT85 -> 154294.32 | AP86: =IF(AO86>0,Assumptions!$B$33,0) -> 2281 | AQ86: =AO86*Assumptions!$B$32/12 -> 500.17075 | AR86: =AP86-AQ86 -> 1780.8292 | AS86: 0 | AT86: =MAX(0,AO86-AR86-AS86) -> 152513.49 | AU86: =IF(AV85>0,MIN(AV85,MAX(300,AM86-AP86-BO86-BQ86-AW86-AY86-BA86-BC86)),0) -> 0 | AV86: =MAX(0,AV85-AU86) -> 0 | AW86: =IF(AX85>0,MIN(250,AX85),0) -> 0 | AX86: =MAX(0,AX85-AW86) -> 0 | AY86: =IF(AZ85>0,MIN(200,AZ85),0) -> 0 | AZ86: =MAX(0,AZ85-AY86) -> 0 | BA86: =IF(AND(AV85<5,BB85>0),MIN(BB85,MAX(0,AM86-AP86-BO86-BQ86-AW86-AY86-BC86)),0) -> 0 | BB86: =MAX(0,BB85-BA86) -> 0 | BC86: =IF(BD85>0,MIN(50,BD85),0) -> 0 | BD86: =MAX(0,BD85-BC86) -> 0 | BE86: =AU86+AW86+AY86+BA86+BC86 -> 0 | BF86: 0 | BG86: =MAX(0,BG85-BF86) -> 5500 | BH86: 0 | BI86: =MAX(0,BI85-BH86) -> 5000 | BJ86: =IF(OR(B86<Assumptions!$B$111,AND(B86=Assumptions!$B$111,A86<=Assumptions!$B$112)),Assumptions!$B$110,0) -> 0 | BK86: =IF(B86<2027,Assumptions!$B$116+IF(OR(A86=4,A86=10),Assumptions!$B$117,0),IF(AND(B86=2027,A86<=4),IF(A86=4,MIN(950,Assumptions!$B$116+Assumptions!$B$117),Assumptions!$B$116),0)) -> 0 | BL86: =IF(OR(B86<2030,AND(B86=2030,A86<8)),Assumptions!$B$118,IF(AND(B86=2030,A86=8),MOD(11000,200),0)) -> 0 | BM86: =IF(OR(B86<Assumptions!$B$120,AND(B86=Assumptions!$B$120,A86<=Assumptions!$B$121)),Assumptions!$B$119,0) -> 0 | BN86: =IF(AND(B86<=Assumptions!$B$123,A86<=Assumptions!$B$124),Assumptions!$B$122,0) -> 0 | BO86: =BF86+BH86+BJ86+BK86+BL86+BM86+BN86 -> 0 | BP86: =SUMIFS(SL_Budget!$B:$B,SL_Budget!$C:$C,"'"&TEXT(DATE(B86,A86,1),"YYYY-MM")) -> 5053 | BQ86: =MAX(BP86, IFERROR(SUMIFS(ShadowLedger!D:D, ShadowLedger!C:C, ">="&DATE(B86,A86,1), ShadowLedger!C:C, "<"&EOMONTH(DATE(B86,A86,1),0)+1), 0)) -> 5053 | BR86: =BV85 -> 837575.28 | BS86: =IF((AV85+AX85+BB85+AZ85+BD85)>5,0,X86) -> 2594.7074 | BT86: =IF(AS86>0,-MAX(0,21550-MAX(0,MAX(0,(AM86-AP86-BE86-BO86-BQ86)-Assumptions!$B$93))-MIN(MAX(0,21550-MAX(0,MAX(0,(AM86-AP86-BE86-BO86-BQ86)-Assumptions!$B$93))),MAX(0,BY85-Assumptions!$B$91))),IF(BY85>=Assumptions!$B$92,MAX(0,(AM86-AP86-BE86-BO86-BQ86)-Assumptions!$B$93),MAX(0,(AM86-AP86-BE86-BO86-BQ86)-Assumptions!$B$93)*Assumptions!$B$99)) -> 16219.399 | BU86: =(BR86+BS86+MAX(0,BT86))*(Assumptions!$B$43-1) -> 5838.8628 | BV86: =BR86+BS86+BT86+BU86 -> 862228.24 | BW86: =BY85 -> 18713.476 | BX86: =IF(AS86>0,-MIN(MAX(0,21550-MAX(0,MAX(0,(AM86-AP86-BE86-BO86-BQ86)-Assumptions!$B$93))),MAX(0,BY85-Assumptions!$B$91)),IF(BY85<Assumptions!$B$92,MAX(0,(AM86-AP86-BE86-BO86-BQ86)-Assumptions!$B$93)*Assumptions!$B$98,0)) -> 0 | BY86: =BW86+BX86 -> 18713.476 | BZ86: =IF(A86=1,0,CB85) -> 0 | CA86: =AH86 -> 6645 | CB86: =BZ86+CA86 -> 6645 | CC86: =CC85+(G86+J86)/(Salary_Schedule!E86*12/208) -> 1791.2625 | CD86: =CD85+(O86+R86)/(Salary_Schedule!G86*12/208) -> 119.55502 | CE86: =BV86 -> 862228.24 | CF86: =Assumptions!$B$55*(1+Assumptions!$B$56)^((B86-2025)+(A86-1)/12) -> 585776.15 | CG86: =-AT86 -> -152513.49 | CH86: =-(AV86+AX86+BB86+AZ86+BD86+AF86+BG86+BI86) -> -13416.1 | CI86: =CC86*(Salary_Schedule!E86/173.33)*(1-Assumptions!$B$28)+CD86*(Salary_Schedule!G86/173.33)*(1-Assumptions!$B$28) -> 73161.515 | CJ86: =CE86+CF86+CG86+CH86+CI86 -> 1355236.3
A87: 2 | B87: 2033 | C87: 02/2033 | D87: =C86 -> 01/2033 | E87: =IF(I87>0,"FAT_BONUS",IF(M87+U87>0,"FAT_RSU","LEAN")) -> LEAN | F87: =Salary_Schedule!E87 -> 10365.29 | G87: =Assumptions!$B$8 -> 200 | H87: =F87*Assumptions!$B$58 -> 1036.529 | I87: =Salary_Schedule!F87 -> 0 | J87: =I87*Assumptions!$B$9 -> 0 | K87: =F87-G87-H87+I87-J87 -> 9128.761 | L87: =IF(COUNTIFS(SL_Income_Log!$B:$B,TEXT(B87,"0000")&"-"&TEXT(A87,"00"),SL_Income_Log!$C:$C,"salary",SL_Income_Log!$E:$E,"H")>0,SUMIFS(SL_Income_Log!$D:$D,SL_Income_Log!$B:$B,TEXT(B87,"0000")&"-"&TEXT(A87,"00"),SL_Income_Log!$C:$C,"salary",SL_Income_Log!$E:$E,"H"),K87*(1-Assumptions!$B$102)-Z87-Y87) -> 5181.2166 | M87: =RSU_Schedule!H86 -> 0 | N87: =Salary_Schedule!G87 -> 7882.62 | O87: =Assumptions!$B$19 -> 200 | P87: =N87*Assumptions!$B$59 -> 788.262 | Q87: =Salary_Schedule!H87 -> 0 | R87: =Q87*Assumptions!$B$20 -> 0 | S87: =N87-O87-P87+Q87-R87 -> 6894.358 | T87: =IF(COUNTIFS(SL_Income_Log!$B:$B,TEXT(B87,"0000")&"-"&TEXT(A87,"00"),SL_Income_Log!$C:$C,"salary",SL_Income_Log!$E:$E,"W")>0,SUMIFS(SL_Income_Log!$D:$D,SL_Income_Log!$B:$B,TEXT(B87,"0000")&"-"&TEXT(A87,"00"),SL_Income_Log!$C:$C,"salary",SL_Income_Log!$E:$E,"W"),S87*(1-Assumptions!$B$102)-AC87-AB87) -> 3840.5748 | U87: =RSU_Schedule!M86 -> 0 | V87: =H87*(1+Assumptions!$B$60)+Assumptions!$B$61 -> 1471.1406 | W87: =P87*(1+Assumptions!$B$60)+Assumptions!$B$61 -> 1123.5668 | X87: =V87+W87 -> 2594.7074 | Y87: =ROUND(AA86*0.003,2) -> 4.37 | Z87: 291.67 | AA87: =MAX(0,AA86-Z87) -> 1166.38 | AB87: =ROUND(AD86*0.003,2) -> 4.37 | AC87: 291.67 | AD87: =MAX(0,AD86-AC87) -> 1166.38 | AE87: =Z87+AC87 -> 583.34 | AF87: =AA87+AD87 -> 2332.76 | AG87: =IF(COUNTIFS(SL_Income_Log!$B:$B,TEXT(B87,"0000")&"-"&TEXT(A87,"00"),SL_Income_Log!$C:$C,"youtube")>0,SUMIFS(SL_Income_Log!$D:$D,SL_Income_Log!$B:$B,TEXT(B87,"0000")&"-"&TEXT(A87,"00"),SL_Income_Log!$C:$C,"youtube"),MIN(Assumptions!$B$49+FLOOR((ROW()-2)/6,1)*Assumptions!$B$50,Assumptions!$B$51)) -> 15000 | AH87: =AG87*Assumptions!$B$104 -> 6645 | AI87: =AG87-AH87 -> 8355 | AJ87: =SUMIFS(SL_Income_Log!$D:$D,SL_Income_Log!$B:$B,TEXT(B87,"0000")&"-"&TEXT(A87,"00"),SL_Income_Log!$C:$C,"other") -> 0 | AK87: =AN86 -> 10000 | AL87: =L87+M87+T87+U87+AI87+AJ87-Y87-Z87-AB87-AC87+IF((Debt_Register!$C$2+Debt_Register!$C$6+Debt_Register!$C$7+Debt_Register!$C$8+Debt_Register!$C$9)>5,X87,0) -> 19379.419 | AM87: =AK87+AL87 -> 29379.419 | AN87: =MAX(Assumptions!$B$94,MIN(Assumptions!$B$93,AM87-AP87-BE87-BO87-BQ87)) -> 10000 | AO87: =AT86 -> 152513.49 | AP87: =IF(AO87>0,Assumptions!$B$33,0) -> 2281 | AQ87: =AO87*Assumptions!$B$32/12 -> 494.3979 | AR87: =AP87-AQ87 -> 1786.6021 | AS87: 0 | AT87: =MAX(0,AO87-AR87-AS87) -> 150726.89 | AU87: =IF(AV86>0,MIN(AV86,MAX(300,AM87-AP87-BO87-BQ87-AW87-AY87-BA87-BC87)),0) -> 0 | AV87: =MAX(0,AV86-AU87) -> 0 | AW87: =IF(AX86>0,MIN(250,AX86),0) -> 0 | AX87: =MAX(0,AX86-AW87) -> 0 | AY87: =IF(AZ86>0,MIN(200,AZ86),0) -> 0 | AZ87: =MAX(0,AZ86-AY87) -> 0 | BA87: =IF(AND(AV86<5,BB86>0),MIN(BB86,MAX(0,AM87-AP87-BO87-BQ87-AW87-AY87-BC87)),0) -> 0 | BB87: =MAX(0,BB86-BA87) -> 0 | BC87: =IF(BD86>0,MIN(50,BD86),0) -> 0 | BD87: =MAX(0,BD86-BC87) -> 0 | BE87: =AU87+AW87+AY87+BA87+BC87 -> 0 | BF87: 0 | BG87: =MAX(0,BG86-BF87) -> 5500 | BH87: 0 | BI87: =MAX(0,BI86-BH87) -> 5000 | BJ87: =IF(OR(B87<Assumptions!$B$111,AND(B87=Assumptions!$B$111,A87<=Assumptions!$B$112)),Assumptions!$B$110,0) -> 0 | BK87: =IF(B87<2027,Assumptions!$B$116+IF(OR(A87=4,A87=10),Assumptions!$B$117,0),IF(AND(B87=2027,A87<=4),IF(A87=4,MIN(950,Assumptions!$B$116+Assumptions!$B$117),Assumptions!$B$116),0)) -> 0 | BL87: =IF(OR(B87<2030,AND(B87=2030,A87<8)),Assumptions!$B$118,IF(AND(B87=2030,A87=8),MOD(11000,200),0)) -> 0 | BM87: =IF(OR(B87<Assumptions!$B$120,AND(B87=Assumptions!$B$120,A87<=Assumptions!$B$121)),Assumptions!$B$119,0) -> 0 | BN87: =IF(AND(B87<=Assumptions!$B$123,A87<=Assumptions!$B$124),Assumptions!$B$122,0) -> 0 | BO87: =BF87+BH87+BJ87+BK87+BL87+BM87+BN87 -> 0 | BP87: =SUMIFS(SL_Budget!$B:$B,SL_Budget!$C:$C,"'"&TEXT(DATE(B87,A87,1),"YYYY-MM")) -> 5053 | BQ87: =MAX(BP87, IFERROR(SUMIFS(ShadowLedger!D:D, ShadowLedger!C:C, ">="&DATE(B87,A87,1), ShadowLedger!C:C, "<"&EOMONTH(DATE(B87,A87,1),0)+1), 0)) -> 5053 | BR87: =BV86 -> 862228.24 | BS87: =IF((AV86+AX86+BB86+AZ86+BD86)>5,0,X87) -> 2594.7074 | BT87: =IF(AS87>0,-MAX(0,21550-MAX(0,MAX(0,(AM87-AP87-BE87-BO87-BQ87)-Assumptions!$B$93))-MIN(MAX(0,21550-MAX(0,MAX(0,(AM87-AP87-BE87-BO87-BQ87)-Assumptions!$B$93))),MAX(0,BY86-Assumptions!$B$91))),IF(BY86>=Assumptions!$B$92,MAX(0,(AM87-AP87-BE87-BO87-BQ87)-Assumptions!$B$93),MAX(0,(AM87-AP87-BE87-BO87-BQ87)-Assumptions!$B$93)*Assumptions!$B$99)) -> 12045.419 | BU87: =(BR87+BS87+MAX(0,BT87))*(Assumptions!$B$43-1) -> 5978.4885 | BV87: =BR87+BS87+BT87+BU87 -> 882846.86 | BW87: =BY86 -> 18713.476 | BX87: =IF(AS87>0,-MIN(MAX(0,21550-MAX(0,MAX(0,(AM87-AP87-BE87-BO87-BQ87)-Assumptions!$B$93))),MAX(0,BY86-Assumptions!$B$91)),IF(BY86<Assumptions!$B$92,MAX(0,(AM87-AP87-BE87-BO87-BQ87)-Assumptions!$B$93)*Assumptions!$B$98,0)) -> 0 | BY87: =BW87+BX87 -> 18713.476 | BZ87: =IF(A87=1,0,CB86) -> 6645 | CA87: =AH87 -> 6645 | CB87: =BZ87+CA87 -> 13290 | CC87: =CC86+(G87+J87)/(Salary_Schedule!E87*12/208) -> 1791.5969 | CD87: =CD86+(O87+R87)/(Salary_Schedule!G87*12/208) -> 119.99481 | CE87: =BV87 -> 882846.86 | CF87: =Assumptions!$B$55*(1+Assumptions!$B$56)^((B87-2025)+(A87-1)/12) -> 586503.38 | CG87: =-AT87 -> -150726.89 | CH87: =-(AV87+AX87+BB87+AZ87+BD87+AF87+BG87+BI87) -> -12832.76 | CI87: =CC87*(Salary_Schedule!E87/173.33)*(1-Assumptions!$B$28)+CD87*(Salary_Schedule!G87/173.33)*(1-Assumptions!$B$28) -> 73187.515 | CJ87: =CE87+CF87+CG87+CH87+CI87 -> 1378978.1
A88: 3 | B88: 2033 | C88: 03/2033 | D88: =C87 -> 02/2033 | E88: =IF(I88>0,"FAT_BONUS",IF(M88+U88>0,"FAT_RSU","LEAN")) -> LEAN | F88: =Salary_Schedule!E88 -> 10365.29 | G88: =Assumptions!$B$8 -> 200 | H88: =F88*Assumptions!$B$58 -> 1036.529 | I88: =Salary_Schedule!F88 -> 0 | J88: =I88*Assumptions!$B$9 -> 0 | K88: =F88-G88-H88+I88-J88 -> 9128.761 | L88: =IF(COUNTIFS(SL_Income_Log!$B:$B,TEXT(B88,"0000")&"-"&TEXT(A88,"00"),SL_Income_Log!$C:$C,"salary",SL_Income_Log!$E:$E,"H")>0,SUMIFS(SL_Income_Log!$D:$D,SL_Income_Log!$B:$B,TEXT(B88,"0000")&"-"&TEXT(A88,"00"),SL_Income_Log!$C:$C,"salary",SL_Income_Log!$E:$E,"H"),K88*(1-Assumptions!$B$102)-Z88-Y88) -> 5182.0866 | M88: =RSU_Schedule!H87 -> 0 | N88: =Salary_Schedule!G88 -> 7882.62 | O88: =Assumptions!$B$19 -> 200 | P88: =N88*Assumptions!$B$59 -> 788.262 | Q88: =Salary_Schedule!H88 -> 0 | R88: =Q88*Assumptions!$B$20 -> 0 | S88: =N88-O88-P88+Q88-R88 -> 6894.358 | T88: =IF(COUNTIFS(SL_Income_Log!$B:$B,TEXT(B88,"0000")&"-"&TEXT(A88,"00"),SL_Income_Log!$C:$C,"salary",SL_Income_Log!$E:$E,"W")>0,SUMIFS(SL_Income_Log!$D:$D,SL_Income_Log!$B:$B,TEXT(B88,"0000")&"-"&TEXT(A88,"00"),SL_Income_Log!$C:$C,"salary",SL_Income_Log!$E:$E,"W"),S88*(1-Assumptions!$B$102)-AC88-AB88) -> 3841.4448 | U88: =RSU_Schedule!M87 -> 0 | V88: =H88*(1+Assumptions!$B$60)+Assumptions!$B$61 -> 1471.1406 | W88: =P88*(1+Assumptions!$B$60)+Assumptions!$B$61 -> 1123.5668 | X88: =V88+W88 -> 2594.7074 | Y88: =ROUND(AA87*0.003,2) -> 3.5 | Z88: 291.67 | AA88: =MAX(0,AA87-Z88) -> 874.71 | AB88: =ROUND(AD87*0.003,2) -> 3.5 | AC88: 291.67 | AD88: =MAX(0,AD87-AC88) -> 874.71 | AE88: =Z88+AC88 -> 583.34 | AF88: =AA88+AD88 -> 1749.42 | AG88: =IF(COUNTIFS(SL_Income_Log!$B:$B,TEXT(B88,"0000")&"-"&TEXT(A88,"00"),SL_Income_Log!$C:$C,"youtube")>0,SUMIFS(SL_Income_Log!$D:$D,SL_Income_Log!$B:$B,TEXT(B88,"0000")&"-"&TEXT(A88,"00"),SL_Income_Log!$C:$C,"youtube"),MIN(Assumptions!$B$49+FLOOR((ROW()-2)/6,1)*Assumptions!$B$50,Assumptions!$B$51)) -> 15000 | AH88: =AG88*Assumptions!$B$104 -> 6645 | AI88: =AG88-AH88 -> 8355 | AJ88: =SUMIFS(SL_Income_Log!$D:$D,SL_Income_Log!$B:$B,TEXT(B88,"0000")&"-"&TEXT(A88,"00"),SL_Income_Log!$C:$C,"other") -> 0 | AK88: =AN87 -> 10000 | AL88: =L88+M88+T88+U88+AI88+AJ88-Y88-Z88-AB88-AC88+IF((Debt_Register!$C$2+Debt_Register!$C$6+Debt_Register!$C$7+Debt_Register!$C$8+Debt_Register!$C$9)>5,X88,0) -> 19382.899 | AM88: =AK88+AL88 -> 29382.899 | AN88: =MAX(Assumptions!$B$94,MIN(Assumptions!$B$93,AM88-AP88-BE88-BO88-BQ88)) -> 10000 | AO88: =AT87 -> 150726.89 | AP88: =IF(AO88>0,Assumptions!$B$33,0) -> 2281 | AQ88: =AO88*Assumptions!$B$32/12 -> 488.60633 | AR88: =AP88-AQ88 -> 1792.3937 | AS88: 0 | AT88: =MAX(0,AO88-AR88-AS88) -> 148934.49 | AU88: =IF(AV87>0,MIN(AV87,MAX(300,AM88-AP88-BO88-BQ88-AW88-AY88-BA88-BC88)),0) -> 0 | AV88: =MAX(0,AV87-AU88) -> 0 | AW88: =IF(AX87>0,MIN(250,AX87),0) -> 0 | AX88: =MAX(0,AX87-AW88) -> 0 | AY88: =IF(AZ87>0,MIN(200,AZ87),0) -> 0 | AZ88: =MAX(0,AZ87-AY88) -> 0 | BA88: =IF(AND(AV87<5,BB87>0),MIN(BB87,MAX(0,AM88-AP88-BO88-BQ88-AW88-AY88-BC88)),0) -> 0 | BB88: =MAX(0,BB87-BA88) -> 0 | BC88: =IF(BD87>0,MIN(50,BD87),0) -> 0 | BD88: =MAX(0,BD87-BC88) -> 0 | BE88: =AU88+AW88+AY88+BA88+BC88 -> 0 | BF88: 0 | BG88: =MAX(0,BG87-BF88) -> 5500 | BH88: 0 | BI88: =MAX(0,BI87-BH88) -> 5000 | BJ88: =IF(OR(B88<Assumptions!$B$111,AND(B88=Assumptions!$B$111,A88<=Assumptions!$B$112)),Assumptions!$B$110,0) -> 0 | BK88: =IF(B88<2027,Assumptions!$B$116+IF(OR(A88=4,A88=10),Assumptions!$B$117,0),IF(AND(B88=2027,A88<=4),IF(A88=4,MIN(950,Assumptions!$B$116+Assumptions!$B$117),Assumptions!$B$116),0)) -> 0 | BL88: =IF(OR(B88<2030,AND(B88=2030,A88<8)),Assumptions!$B$118,IF(AND(B88=2030,A88=8),MOD(11000,200),0)) -> 0 | BM88: =IF(OR(B88<Assumptions!$B$120,AND(B88=Assumptions!$B$120,A88<=Assumptions!$B$121)),Assumptions!$B$119,0) -> 0 | BN88: =IF(AND(B88<=Assumptions!$B$123,A88<=Assumptions!$B$124),Assumptions!$B$122,0) -> 0 | BO88: =BF88+BH88+BJ88+BK88+BL88+BM88+BN88 -> 0 | BP88: =SUMIFS(SL_Budget!$B:$B,SL_Budget!$C:$C,"'"&TEXT(DATE(B88,A88,1),"YYYY-MM")) -> 5053 | BQ88: =MAX(BP88, IFERROR(SUMIFS(ShadowLedger!D:D, ShadowLedger!C:C, ">="&DATE(B88,A88,1), ShadowLedger!C:C, "<"&EOMONTH(DATE(B88,A88,1),0)+1), 0)) -> 5053 | BR88: =BV87 -> 882846.86 | BS88: =IF((AV87+AX87+BB87+AZ87+BD87)>5,0,X88) -> 2594.7074 | BT88: =IF(AS88>0,-MAX(0,21550-MAX(0,MAX(0,(AM88-AP88-BE88-BO88-BQ88)-Assumptions!$B$93))-MIN(MAX(0,21550-MAX(0,MAX(0,(AM88-AP88-BE88-BO88-BQ88)-Assumptions!$B$93))),MAX(0,BY87-Assumptions!$B$91))),IF(BY87>=Assumptions!$B$92,MAX(0,(AM88-AP88-BE88-BO88-BQ88)-Assumptions!$B$93),MAX(0,(AM88-AP88-BE88-BO88-BQ88)-Assumptions!$B$93)*Assumptions!$B$99)) -> 12048.899 | BU88: =(BR88+BS88+MAX(0,BT88))*(Assumptions!$B$43-1) -> 6119.09 | BV88: =BR88+BS88+BT88+BU88 -> 903609.56 | BW88: =BY87 -> 18713.476 | BX88: =IF(AS88>0,-MIN(MAX(0,21550-MAX(0,MAX(0,(AM88-AP88-BE88-BO88-BQ88)-Assumptions!$B$93))),MAX(0,BY87-Assumptions!$B$91)),IF(BY87<Assumptions!$B$92,MAX(0,(AM88-AP88-BE88-BO88-BQ88)-Assumptions!$B$93)*Assumptions!$B$98,0)) -> 0 | BY88: =BW88+BX88 -> 18713.476 | BZ88: =IF(A88=1,0,CB87) -> 13290 | CA88: =AH88 -> 6645 | CB88: =BZ88+CA88 -> 19935 | CC88: =CC87+(G88+J88)/(Salary_Schedule!E88*12/208) -> 1791.9314 | CD88: =CD87+(O88+R88)/(Salary_Schedule!G88*12/208) -> 120.4346 | CE88: =BV88 -> 903609.56 | CF88: =Assumptions!$B$55*(1+Assumptions!$B$56)^((B88-2025)+(A88-1)/12) -> 587231.52 | CG88: =-AT88 -> -148934.49 | CH88: =-(AV88+AX88+BB88+AZ88+BD88+AF88+BG88+BI88) -> -12249.42 | CI88: =CC88*(Salary_Schedule!E88/173.33)*(1-Assumptions!$B$28)+CD88*(Salary_Schedule!G88/173.33)*(1-Assumptions!$B$28) -> 73213.516 | CJ88: =CE88+CF88+CG88+CH88+CI88 -> 1402870.7
A89: 4 | B89: 2033 | C89: 04/2033 | D89: =C88 -> 03/2033 | E89: =IF(I89>0,"FAT_BONUS",IF(M89+U89>0,"FAT_RSU","LEAN")) -> FAT_BONUS | F89: =Salary_Schedule!E89 -> 10365.29 | G89: =Assumptions!$B$8 -> 200 | H89: =F89*Assumptions!$B$58 -> 1036.529 | I89: =Salary_Schedule!F89 -> 13819.13 | J89: =I89*Assumptions!$B$9 -> 4836.6955 | K89: =F89-G89-H89+I89-J89 -> 18111.196 | L89: =IF(COUNTIFS(SL_Income_Log!$B:$B,TEXT(B89,"0000")&"-"&TEXT(A89,"00"),SL_Income_Log!$C:$C,"salary",SL_Income_Log!$E:$E,"H")>0,SUMIFS(SL_Income_Log!$D:$D,SL_Income_Log!$B:$B,TEXT(B89,"0000")&"-"&TEXT(A89,"00"),SL_Income_Log!$C:$C,"salary",SL_Income_Log!$E:$E,"H"),K89*(1-Assumptions!$B$102)-Z89-Y89) -> 10572.427 | M89: =RSU_Schedule!H88 -> 2784.99 | N89: =Salary_Schedule!G89 -> 7882.62 | O89: =Assumptions!$B$19 -> 200 | P89: =N89*Assumptions!$B$59 -> 788.262 | Q89: =Salary_Schedule!H89 -> 10510.3 | R89: =Q89*Assumptions!$B$20 -> 3678.605 | S89: =N89-O89-P89+Q89-R89 -> 13726.053 | T89: =IF(COUNTIFS(SL_Income_Log!$B:$B,TEXT(B89,"0000")&"-"&TEXT(A89,"00"),SL_Income_Log!$C:$C,"salary",SL_Income_Log!$E:$E,"W")>0,SUMIFS(SL_Income_Log!$D:$D,SL_Income_Log!$B:$B,TEXT(B89,"0000")&"-"&TEXT(A89,"00"),SL_Income_Log!$C:$C,"salary",SL_Income_Log!$E:$E,"W"),S89*(1-Assumptions!$B$102)-AC89-AB89) -> 7941.3418 | U89: =RSU_Schedule!M88 -> 1392.51 | V89: =H89*(1+Assumptions!$B$60)+Assumptions!$B$61 -> 1471.1406 | W89: =P89*(1+Assumptions!$B$60)+Assumptions!$B$61 -> 1123.5668 | X89: =V89+W89 -> 2594.7074 | Y89: =ROUND(AA88*0.003,2) -> 2.62 | Z89: 291.67 | AA89: =MAX(0,AA88-Z89) -> 583.04 | AB89: =ROUND(AD88*0.003,2) -> 2.62 | AC89: 291.67 | AD89: =MAX(0,AD88-AC89) -> 583.04 | AE89: =Z89+AC89 -> 583.34 | AF89: =AA89+AD89 -> 1166.08 | AG89: =IF(COUNTIFS(SL_Income_Log!$B:$B,TEXT(B89,"0000")&"-"&TEXT(A89,"00"),SL_Income_Log!$C:$C,"youtube")>0,SUMIFS(SL_Income_Log!$D:$D,SL_Income_Log!$B:$B,TEXT(B89,"0000")&"-"&TEXT(A89,"00"),SL_Income_Log!$C:$C,"youtube"),MIN(Assumptions!$B$49+FLOOR((ROW()-2)/6,1)*Assumptions!$B$50,Assumptions!$B$51)) -> 15000 | AH89: =AG89*Assumptions!$B$104 -> 6645 | AI89: =AG89-AH89 -> 8355 | AJ89: =SUMIFS(SL_Income_Log!$D:$D,SL_Income_Log!$B:$B,TEXT(B89,"0000")&"-"&TEXT(A89,"00"),SL_Income_Log!$C:$C,"other") -> 0 | AK89: =AN88 -> 10000 | AL89: =L89+M89+T89+U89+AI89+AJ89-Y89-Z89-AB89-AC89+IF((Debt_Register!$C$2+Debt_Register!$C$6+Debt_Register!$C$7+Debt_Register!$C$8+Debt_Register!$C$9)>5,X89,0) -> 33052.397 | AM89: =AK89+AL89 -> 43052.397 | AN89: =MAX(Assumptions!$B$94,MIN(Assumptions!$B$93,AM89-AP89-BE89-BO89-BQ89)) -> 10000 | AO89: =AT88 -> 148934.49 | AP89: =IF(AO89>0,Assumptions!$B$33,0) -> 2281 | AQ89: =AO89*Assumptions!$B$32/12 -> 482.79599 | AR89: =AP89-AQ89 -> 1798.204 | AS89: 0 | AT89: =MAX(0,AO89-AR89-AS89) -> 147136.29 | AU89: =IF(AV88>0,MIN(AV88,MAX(300,AM89-AP89-BO89-BQ89-AW89-AY89-BA89-BC89)),0) -> 0 | AV89: =MAX(0,AV88-AU89) -> 0 | AW89: =IF(AX88>0,MIN(250,AX88),0) -> 0 | AX89: =MAX(0,AX88-AW89) -> 0 | AY89: =IF(AZ88>0,MIN(200,AZ88),0) -> 0 | AZ89: =MAX(0,AZ88-AY89) -> 0 | BA89: =IF(AND(AV88<5,BB88>0),MIN(BB88,MAX(0,AM89-AP89-BO89-BQ89-AW89-AY89-BC89)),0) -> 0 | BB89: =MAX(0,BB88-BA89) -> 0 | BC89: =IF(BD88>0,MIN(50,BD88),0) -> 0 | BD89: =MAX(0,BD88-BC89) -> 0 | BE89: =AU89+AW89+AY89+BA89+BC89 -> 0 | BF89: 0 | BG89: =MAX(0,BG88-BF89) -> 5500 | BH89: 0 | BI89: =MAX(0,BI88-BH89) -> 5000 | BJ89: =IF(OR(B89<Assumptions!$B$111,AND(B89=Assumptions!$B$111,A89<=Assumptions!$B$112)),Assumptions!$B$110,0) -> 0 | BK89: =IF(B89<2027,Assumptions!$B$116+IF(OR(A89=4,A89=10),Assumptions!$B$117,0),IF(AND(B89=2027,A89<=4),IF(A89=4,MIN(950,Assumptions!$B$116+Assumptions!$B$117),Assumptions!$B$116),0)) -> 0 | BL89: =IF(OR(B89<2030,AND(B89=2030,A89<8)),Assumptions!$B$118,IF(AND(B89=2030,A89=8),MOD(11000,200),0)) -> 0 | BM89: =IF(OR(B89<Assumptions!$B$120,AND(B89=Assumptions!$B$120,A89<=Assumptions!$B$121)),Assumptions!$B$119,0) -> 0 | BN89: =IF(AND(B89<=Assumptions!$B$123,A89<=Assumptions!$B$124),Assumptions!$B$122,0) -> 0 | BO89: =BF89+BH89+BJ89+BK89+BL89+BM89+BN89 -> 0 | BP89: =SUMIFS(SL_Budget!$B:$B,SL_Budget!$C:$C,"'"&TEXT(DATE(B89,A89,1),"YYYY-MM")) -> 5053 | BQ89: =MAX(BP89, IFERROR(SUMIFS(ShadowLedger!D:D, ShadowLedger!C:C, ">="&DATE(B89,A89,1), ShadowLedger!C:C, "<"&EOMONTH(DATE(B89,A89,1),0)+1), 0)) -> 5053 | BR89: =BV88 -> 903609.56 | BS89: =IF((AV88+AX88+BB88+AZ88+BD88)>5,0,X89) -> 2594.7074 | BT89: =IF(AS89>0,-MAX(0,21550-MAX(0,MAX(0,(AM89-AP89-BE89-BO89-BQ89)-Assumptions!$B$93))-MIN(MAX(0,21550-MAX(0,MAX(0,(AM89-AP89-BE89-BO89-BQ89)-Assumptions!$B$93))),MAX(0,BY88-Assumptions!$B$91))),IF(BY88>=Assumptions!$B$92,MAX(0,(AM89-AP89-BE89-BO89-BQ89)-Assumptions!$B$93),MAX(0,(AM89-AP89-BE89-BO89-BQ89)-Assumptions!$B$93)*Assumptions!$B$99)) -> 25718.396 | BU89: =(BR89+BS89+MAX(0,BT89))*(Assumptions!$B$43-1) -> 6353.8487 | BV89: =BR89+BS89+BT89+BU89 -> 938276.51 | BW89: =BY88 -> 18713.476 | BX89: =IF(AS89>0,-MIN(MAX(0,21550-MAX(0,MAX(0,(AM89-AP89-BE89-BO89-BQ89)-Assumptions!$B$93))),MAX(0,BY88-Assumptions!$B$91)),IF(BY88<Assumptions!$B$92,MAX(0,(AM89-AP89-BE89-BO89-BQ89)-Assumptions!$B$93)*Assumptions!$B$98,0)) -> 0 | BY89: =BW89+BX89 -> 18713.476 | BZ89: =IF(A89=1,0,CB88) -> 19935 | CA89: =AH89 -> 6645 | CB89: =BZ89+CA89 -> 26580 | CC89: =CC88+(G89+J89)/(Salary_Schedule!E89*12/208) -> 1800.354 | CD89: =CD88+(O89+R89)/(Salary_Schedule!G89*12/208) -> 128.96338 | CE89: =BV89 -> 938276.51 | CF89: =Assumptions!$B$55*(1+Assumptions!$B$56)^((B89-2025)+(A89-1)/12) -> 587960.56 | CG89: =-AT89 -> -147136.29 | CH89: =-(AV89+AX89+BB89+AZ89+BD89+AF89+BG89+BI89) -> -11666.08 | CI89: =CC89*(Salary_Schedule!E89/173.33)*(1-Assumptions!$B$28)+CD89*(Salary_Schedule!G89/173.33)*(1-Assumptions!$B$28) -> 73793.021 | CJ89: =CE89+CF89+CG89+CH89+CI89 -> 1441227.7
A90: 5 | B90: 2033 | C90: 05/2033 | D90: =C89 -> 04/2033 | E90: =IF(I90>0,"FAT_BONUS",IF(M90+U90>0,"FAT_RSU","LEAN")) -> LEAN | F90: =Salary_Schedule!E90 -> 10365.29 | G90: =Assumptions!$B$8 -> 200 | H90: =F90*Assumptions!$B$58 -> 1036.529 | I90: =Salary_Schedule!F90 -> 0 | J90: =I90*Assumptions!$B$9 -> 0 | K90: =F90-G90-H90+I90-J90 -> 9128.761 | L90: =IF(COUNTIFS(SL_Income_Log!$B:$B,TEXT(B90,"0000")&"-"&TEXT(A90,"00"),SL_Income_Log!$C:$C,"salary",SL_Income_Log!$E:$E,"H")>0,SUMIFS(SL_Income_Log!$D:$D,SL_Income_Log!$B:$B,TEXT(B90,"0000")&"-"&TEXT(A90,"00"),SL_Income_Log!$C:$C,"salary",SL_Income_Log!$E:$E,"H"),K90*(1-Assumptions!$B$102)-Z90-Y90) -> 5183.8366 | M90: =RSU_Schedule!H89 -> 0 | N90: =Salary_Schedule!G90 -> 7882.62 | O90: =Assumptions!$B$19 -> 200 | P90: =N90*Assumptions!$B$59 -> 788.262 | Q90: =Salary_Schedule!H90 -> 0 | R90: =Q90*Assumptions!$B$20 -> 0 | S90: =N90-O90-P90+Q90-R90 -> 6894.358 | T90: =IF(COUNTIFS(SL_Income_Log!$B:$B,TEXT(B90,"0000")&"-"&TEXT(A90,"00"),SL_Income_Log!$C:$C,"salary",SL_Income_Log!$E:$E,"W")>0,SUMIFS(SL_Income_Log!$D:$D,SL_Income_Log!$B:$B,TEXT(B90,"0000")&"-"&TEXT(A90,"00"),SL_Income_Log!$C:$C,"salary",SL_Income_Log!$E:$E,"W"),S90*(1-Assumptions!$B$102)-AC90-AB90) -> 3843.1948 | U90: =RSU_Schedule!M89 -> 0 | V90: =H90*(1+Assumptions!$B$60)+Assumptions!$B$61 -> 1471.1406 | W90: =P90*(1+Assumptions!$B$60)+Assumptions!$B$61 -> 1123.5668 | X90: =V90+W90 -> 2594.7074 | Y90: =ROUND(AA89*0.003,2) -> 1.75 | Z90: 291.67 | AA90: =MAX(0,AA89-Z90) -> 291.37 | AB90: =ROUND(AD89*0.003,2) -> 1.75 | AC90: 291.67 | AD90: =MAX(0,AD89-AC90) -> 291.37 | AE90: =Z90+AC90 -> 583.34 | AF90: =AA90+AD90 -> 582.74 | AG90: =IF(COUNTIFS(SL_Income_Log!$B:$B,TEXT(B90,"0000")&"-"&TEXT(A90,"00"),SL_Income_Log!$C:$C,"youtube")>0,SUMIFS(SL_Income_Log!$D:$D,SL_Income_Log!$B:$B,TEXT(B90,"0000")&"-"&TEXT(A90,"00"),SL_Income_Log!$C:$C,"youtube"),MIN(Assumptions!$B$49+FLOOR((ROW()-2)/6,1)*Assumptions!$B$50,Assumptions!$B$51)) -> 15000 | AH90: =AG90*Assumptions!$B$104 -> 6645 | AI90: =AG90-AH90 -> 8355 | AJ90: =SUMIFS(SL_Income_Log!$D:$D,SL_Income_Log!$B:$B,TEXT(B90,"0000")&"-"&TEXT(A90,"00"),SL_Income_Log!$C:$C,"other") -> 0 | AK90: =AN89 -> 10000 | AL90: =L90+M90+T90+U90+AI90+AJ90-Y90-Z90-AB90-AC90+IF((Debt_Register!$C$2+Debt_Register!$C$6+Debt_Register!$C$7+Debt_Register!$C$8+Debt_Register!$C$9)>5,X90,0) -> 19389.899 | AM90: =AK90+AL90 -> 29389.899 | AN90: =MAX(Assumptions!$B$94,MIN(Assumptions!$B$93,AM90-AP90-BE90-BO90-BQ90)) -> 10000 | AO90: =AT89 -> 147136.29 | AP90: =IF(AO90>0,Assumptions!$B$33,0) -> 2281 | AQ90: =AO90*Assumptions!$B$32/12 -> 476.96681 | AR90: =AP90-AQ90 -> 1804.0332 | AS90: 0 | AT90: =MAX(0,AO90-AR90-AS90) -> 145332.26 | AU90: =IF(AV89>0,MIN(AV89,MAX(300,AM90-AP90-BO90-BQ90-AW90-AY90-BA90-BC90)),0) -> 0 | AV90: =MAX(0,AV89-AU90) -> 0 | AW90: =IF(AX89>0,MIN(250,AX89),0) -> 0 | AX90: =MAX(0,AX89-AW90) -> 0 | AY90: =IF(AZ89>0,MIN(200,AZ89),0) -> 0 | AZ90: =MAX(0,AZ89-AY90) -> 0 | BA90: =IF(AND(AV89<5,BB89>0),MIN(BB89,MAX(0,AM90-AP90-BO90-BQ90-AW90-AY90-BC90)),0) -> 0 | BB90: =MAX(0,BB89-BA90) -> 0 | BC90: =IF(BD89>0,MIN(50,BD89),0) -> 0 | BD90: =MAX(0,BD89-BC90) -> 0 | BE90: =AU90+AW90+AY90+BA90+BC90 -> 0 | BF90: 0 | BG90: =MAX(0,BG89-BF90) -> 5500 | BH90: 0 | BI90: =MAX(0,BI89-BH90) -> 5000 | BJ90: =IF(OR(B90<Assumptions!$B$111,AND(B90=Assumptions!$B$111,A90<=Assumptions!$B$112)),Assumptions!$B$110,0) -> 0 | BK90: =IF(B90<2027,Assumptions!$B$116+IF(OR(A90=4,A90=10),Assumptions!$B$117,0),IF(AND(B90=2027,A90<=4),IF(A90=4,MIN(950,Assumptions!$B$116+Assumptions!$B$117),Assumptions!$B$116),0)) -> 0 | BL90: =IF(OR(B90<2030,AND(B90=2030,A90<8)),Assumptions!$B$118,IF(AND(B90=2030,A90=8),MOD(11000,200),0)) -> 0 | BM90: =IF(OR(B90<Assumptions!$B$120,AND(B90=Assumptions!$B$120,A90<=Assumptions!$B$121)),Assumptions!$B$119,0) -> 0 | BN90: =IF(AND(B90<=Assumptions!$B$123,A90<=Assumptions!$B$124),Assumptions!$B$122,0) -> 0 | BO90: =BF90+BH90+BJ90+BK90+BL90+BM90+BN90 -> 0 | BP90: =SUMIFS(SL_Budget!$B:$B,SL_Budget!$C:$C,"'"&TEXT(DATE(B90,A90,1),"YYYY-MM")) -> 5053 | BQ90: =MAX(BP90, IFERROR(SUMIFS(ShadowLedger!D:D, ShadowLedger!C:C, ">="&DATE(B90,A90,1), ShadowLedger!C:C, "<"&EOMONTH(DATE(B90,A90,1),0)+1), 0)) -> 5053 | BR90: =BV89 -> 938276.51 | BS90: =IF((AV89+AX89+BB89+AZ89+BD89)>5,0,X90) -> 2594.7074 | BT90: =IF(AS90>0,-MAX(0,21550-MAX(0,MAX(0,(AM90-AP90-BE90-BO90-BQ90)-Assumptions!$B$93))-MIN(MAX(0,21550-MAX(0,MAX(0,(AM90-AP90-BE90-BO90-BQ90)-Assumptions!$B$93))),MAX(0,BY89-Assumptions!$B$91))),IF(BY89>=Assumptions!$B$92,MAX(0,(AM90-AP90-BE90-BO90-BQ90)-Assumptions!$B$93),MAX(0,(AM90-AP90-BE90-BO90-BQ90)-Assumptions!$B$93)*Assumptions!$B$99)) -> 12055.899 | BU90: =(BR90+BS90+MAX(0,BT90))*(Assumptions!$B$43-1) -> 6497.0571 | BV90: =BR90+BS90+BT90+BU90 -> 959424.17 | BW90: =BY89 -> 18713.476 | BX90: =IF(AS90>0,-MIN(MAX(0,21550-MAX(0,MAX(0,(AM90-AP90-BE90-BO90-BQ90)-Assumptions!$B$93))),MAX(0,BY89-Assumptions!$B$91)),IF(BY89<Assumptions!$B$92,MAX(0,(AM90-AP90-BE90-BO90-BQ90)-Assumptions!$B$93)*Assumptions!$B$98,0)) -> 0 | BY90: =BW90+BX90 -> 18713.476 | BZ90: =IF(A90=1,0,CB89) -> 26580 | CA90: =AH90 -> 6645 | CB90: =BZ90+CA90 -> 33225 | CC90: =CC89+(G90+J90)/(Salary_Schedule!E90*12/208) -> 1800.6885 | CD90: =CD89+(O90+R90)/(Salary_Schedule!G90*12/208) -> 129.40316 | CE90: =BV90 -> 959424.17 | CF90: =Assumptions!$B$55*(1+Assumptions!$B$56)^((B90-2025)+(A90-1)/12) -> 588690.5 | CG90: =-AT90 -> -145332.26 | CH90: =-(AV90+AX90+BB90+AZ90+BD90+AF90+BG90+BI90) -> -11082.74 | CI90: =CC90*(Salary_Schedule!E90/173.33)*(1-Assumptions!$B$28)+CD90*(Salary_Schedule!G90/173.33)*(1-Assumptions!$B$28) -> 73819.022 | CJ90: =CE90+CF90+CG90+CH90+CI90 -> 1465518.7
A91: 6 | B91: 2033 | C91: 06/2033 | D91: =C90 -> 05/2033 | E91: =IF(I91>0,"FAT_BONUS",IF(M91+U91>0,"FAT_RSU","LEAN")) -> LEAN | F91: =Salary_Schedule!E91 -> 10365.29 | G91: =Assumptions!$B$8 -> 200 | H91: =F91*Assumptions!$B$58 -> 1036.529 | I91: =Salary_Schedule!F91 -> 0 | J91: =I91*Assumptions!$B$9 -> 0 | K91: =F91-G91-H91+I91-J91 -> 9128.761 | L91: =IF(COUNTIFS(SL_Income_Log!$B:$B,TEXT(B91,"0000")&"-"&TEXT(A91,"00"),SL_Income_Log!$C:$C,"salary",SL_Income_Log!$E:$E,"H")>0,SUMIFS(SL_Income_Log!$D:$D,SL_Income_Log!$B:$B,TEXT(B91,"0000")&"-"&TEXT(A91,"00"),SL_Income_Log!$C:$C,"salary",SL_Income_Log!$E:$E,"H"),K91*(1-Assumptions!$B$102)-Z91-Y91) -> 5184.7166 | M91: =RSU_Schedule!H90 -> 0 | N91: =Salary_Schedule!G91 -> 7882.62 | O91: =Assumptions!$B$19 -> 200 | P91: =N91*Assumptions!$B$59 -> 788.262 | Q91: =Salary_Schedule!H91 -> 0 | R91: =Q91*Assumptions!$B$20 -> 0 | S91: =N91-O91-P91+Q91-R91 -> 6894.358 | T91: =IF(COUNTIFS(SL_Income_Log!$B:$B,TEXT(B91,"0000")&"-"&TEXT(A91,"00"),SL_Income_Log!$C:$C,"salary",SL_Income_Log!$E:$E,"W")>0,SUMIFS(SL_Income_Log!$D:$D,SL_Income_Log!$B:$B,TEXT(B91,"0000")&"-"&TEXT(A91,"00"),SL_Income_Log!$C:$C,"salary",SL_Income_Log!$E:$E,"W"),S91*(1-Assumptions!$B$102)-AC91-AB91) -> 3844.0748 | U91: =RSU_Schedule!M90 -> 0 | V91: =H91*(1+Assumptions!$B$60)+Assumptions!$B$61 -> 1471.1406 | W91: =P91*(1+Assumptions!$B$60)+Assumptions!$B$61 -> 1123.5668 | X91: =V91+W91 -> 2594.7074 | Y91: =ROUND(AA90*0.003,2) -> 0.87 | Z91: 291.67 | AA91: =MAX(0,AA90-Z91) -> 0 | AB91: =ROUND(AD90*0.003,2) -> 0.87 | AC91: 291.67 | AD91: =MAX(0,AD90-AC91) -> 0 | AE91: =Z91+AC91 -> 583.34 | AF91: =AA91+AD91 -> 0 | AG91: =IF(COUNTIFS(SL_Income_Log!$B:$B,TEXT(B91,"0000")&"-"&TEXT(A91,"00"),SL_Income_Log!$C:$C,"youtube")>0,SUMIFS(SL_Income_Log!$D:$D,SL_Income_Log!$B:$B,TEXT(B91,"0000")&"-"&TEXT(A91,"00"),SL_Income_Log!$C:$C,"youtube"),MIN(Assumptions!$B$49+FLOOR((ROW()-2)/6,1)*Assumptions!$B$50,Assumptions!$B$51)) -> 15000 | AH91: =AG91*Assumptions!$B$104 -> 6645 | AI91: =AG91-AH91 -> 8355 | AJ91: =SUMIFS(SL_Income_Log!$D:$D,SL_Income_Log!$B:$B,TEXT(B91,"0000")&"-"&TEXT(A91,"00"),SL_Income_Log!$C:$C,"other") -> 0 | AK91: =AN90 -> 10000 | AL91: =L91+M91+T91+U91+AI91+AJ91-Y91-Z91-AB91-AC91+IF((Debt_Register!$C$2+Debt_Register!$C$6+Debt_Register!$C$7+Debt_Register!$C$8+Debt_Register!$C$9)>5,X91,0) -> 19393.419 | AM91: =AK91+AL91 -> 29393.419 | AN91: =MAX(Assumptions!$B$94,MIN(Assumptions!$B$93,AM91-AP91-BE91-BO91-BQ91)) -> 10000 | AO91: =AT90 -> 145332.26 | AP91: =IF(AO91>0,Assumptions!$B$33,0) -> 2281 | AQ91: =AO91*Assumptions!$B$32/12 -> 471.11874 | AR91: =AP91-AQ91 -> 1809.8813 | AS91: 0 | AT91: =MAX(0,AO91-AR91-AS91) -> 143522.38 | AU91: =IF(AV90>0,MIN(AV90,MAX(300,AM91-AP91-BO91-BQ91-AW91-AY91-BA91-BC91)),0) -> 0 | AV91: =MAX(0,AV90-AU91) -> 0 | AW91: =IF(AX90>0,MIN(250,AX90),0) -> 0 | AX91: =MAX(0,AX90-AW91) -> 0 | AY91: =IF(AZ90>0,MIN(200,AZ90),0) -> 0 | AZ91: =MAX(0,AZ90-AY91) -> 0 | BA91: =IF(AND(AV90<5,BB90>0),MIN(BB90,MAX(0,AM91-AP91-BO91-BQ91-AW91-AY91-BC91)),0) -> 0 | BB91: =MAX(0,BB90-BA91) -> 0 | BC91: =IF(BD90>0,MIN(50,BD90),0) -> 0 | BD91: =MAX(0,BD90-BC91) -> 0 | BE91: =AU91+AW91+AY91+BA91+BC91 -> 0 | BF91: 0 | BG91: =MAX(0,BG90-BF91) -> 5500 | BH91: 0 | BI91: =MAX(0,BI90-BH91) -> 5000 | BJ91: =IF(OR(B91<Assumptions!$B$111,AND(B91=Assumptions!$B$111,A91<=Assumptions!$B$112)),Assumptions!$B$110,0) -> 0 | BK91: =IF(B91<2027,Assumptions!$B$116+IF(OR(A91=4,A91=10),Assumptions!$B$117,0),IF(AND(B91=2027,A91<=4),IF(A91=4,MIN(950,Assumptions!$B$116+Assumptions!$B$117),Assumptions!$B$116),0)) -> 0 | BL91: =IF(OR(B91<2030,AND(B91=2030,A91<8)),Assumptions!$B$118,IF(AND(B91=2030,A91=8),MOD(11000,200),0)) -> 0 | BM91: =IF(OR(B91<Assumptions!$B$120,AND(B91=Assumptions!$B$120,A91<=Assumptions!$B$121)),Assumptions!$B$119,0) -> 0 | BN91: =IF(AND(B91<=Assumptions!$B$123,A91<=Assumptions!$B$124),Assumptions!$B$122,0) -> 0 | BO91: =BF91+BH91+BJ91+BK91+BL91+BM91+BN91 -> 0 | BP91: =SUMIFS(SL_Budget!$B:$B,SL_Budget!$C:$C,"'"&TEXT(DATE(B91,A91,1),"YYYY-MM")) -> 5053 | BQ91: =MAX(BP91, IFERROR(SUMIFS(ShadowLedger!D:D, ShadowLedger!C:C, ">="&DATE(B91,A91,1), ShadowLedger!C:C, "<"&EOMONTH(DATE(B91,A91,1),0)+1), 0)) -> 5053 | BR91: =BV90 -> 959424.17 | BS91: =IF((AV90+AX90+BB90+AZ90+BD90)>5,0,X91) -> 2594.7074 | BT91: =IF(AS91>0,-MAX(0,21550-MAX(0,MAX(0,(AM91-AP91-BE91-BO91-BQ91)-Assumptions!$B$93))-MIN(MAX(0,21550-MAX(0,MAX(0,(AM91-AP91-BE91-BO91-BQ91)-Assumptions!$B$93))),MAX(0,BY90-Assumptions!$B$91))),IF(BY90>=Assumptions!$B$92,MAX(0,(AM91-AP91-BE91-BO91-BQ91)-Assumptions!$B$93),MAX(0,(AM91-AP91-BE91-BO91-BQ91)-Assumptions!$B$93)*Assumptions!$B$99)) -> 12059.419 | BU91: =(BR91+BS91+MAX(0,BT91))*(Assumptions!$B$43-1) -> 6641.2658 | BV91: =BR91+BS91+BT91+BU91 -> 980719.56 | BW91: =BY90 -> 18713.476 | BX91: =IF(AS91>0,-MIN(MAX(0,21550-MAX(0,MAX(0,(AM91-AP91-BE91-BO91-BQ91)-Assumptions!$B$93))),MAX(0,BY90-Assumptions!$B$91)),IF(BY90<Assumptions!$B$92,MAX(0,(AM91-AP91-BE91-BO91-BQ91)-Assumptions!$B$93)*Assumptions!$B$98,0)) -> 0 | BY91: =BW91+BX91 -> 18713.476 | BZ91: =IF(A91=1,0,CB90) -> 33225 | CA91: =AH91 -> 6645 | CB91: =BZ91+CA91 -> 39870 | CC91: =CC90+(G91+J91)/(Salary_Schedule!E91*12/208) -> 1801.0229 | CD91: =CD90+(O91+R91)/(Salary_Schedule!G91*12/208) -> 129.84295 | CE91: =BV91 -> 980719.56 | CF91: =Assumptions!$B$55*(1+Assumptions!$B$56)^((B91-2025)+(A91-1)/12) -> 589421.35 | CG91: =-AT91 -> -143522.38 | CH91: =-(AV91+AX91+BB91+AZ91+BD91+AF91+BG91+BI91) -> -10500 | CI91: =CC91*(Salary_Schedule!E91/173.33)*(1-Assumptions!$B$28)+CD91*(Salary_Schedule!G91/173.33)*(1-Assumptions!$B$28) -> 73845.022 | CJ91: =CE91+CF91+CG91+CH91+CI91 -> 1489963.6
A92: 7 | B92: 2033 | C92: 07/2033 | D92: =C91 -> 06/2033 | E92: =IF(I92>0,"FAT_BONUS",IF(M92+U92>0,"FAT_RSU","LEAN")) -> FAT_RSU | F92: =Salary_Schedule!E92 -> 10365.29 | G92: =Assumptions!$B$8 -> 200 | H92: =F92*Assumptions!$B$58 -> 1036.529 | I92: =Salary_Schedule!F92 -> 0 | J92: =I92*Assumptions!$B$9 -> 0 | K92: =F92-G92-H92+I92-J92 -> 9128.761 | L92: =IF(COUNTIFS(SL_Income_Log!$B:$B,TEXT(B92,"0000")&"-"&TEXT(A92,"00"),SL_Income_Log!$C:$C,"salary",SL_Income_Log!$E:$E,"H")>0,SUMIFS(SL_Income_Log!$D:$D,SL_Income_Log!$B:$B,TEXT(B92,"0000")&"-"&TEXT(A92,"00"),SL_Income_Log!$C:$C,"salary",SL_Income_Log!$E:$E,"H"),K92*(1-Assumptions!$B$102)-Z92-Y92) -> 5477.2566 | M92: =RSU_Schedule!H91 -> 2784.99 | N92: =Salary_Schedule!G92 -> 7882.62 | O92: =Assumptions!$B$19 -> 200 | P92: =N92*Assumptions!$B$59 -> 788.262 | Q92: =Salary_Schedule!H92 -> 0 | R92: =Q92*Assumptions!$B$20 -> 0 | S92: =N92-O92-P92+Q92-R92 -> 6894.358 | T92: =IF(COUNTIFS(SL_Income_Log!$B:$B,TEXT(B92,"0000")&"-"&TEXT(A92,"00"),SL_Income_Log!$C:$C,"salary",SL_Income_Log!$E:$E,"W")>0,SUMIFS(SL_Income_Log!$D:$D,SL_Income_Log!$B:$B,TEXT(B92,"0000")&"-"&TEXT(A92,"00"),SL_Income_Log!$C:$C,"salary",SL_Income_Log!$E:$E,"W"),S92*(1-Assumptions!$B$102)-AC92-AB92) -> 4136.6148 | U92: =RSU_Schedule!M91 -> 1392.51 | V92: =H92*(1+Assumptions!$B$60)+Assumptions!$B$61 -> 1471.1406 | W92: =P92*(1+Assumptions!$B$60)+Assumptions!$B$61 -> 1123.5668 | X92: =V92+W92 -> 2594.7074 | Y92: 0 | Z92: 0 | AA92: 0 | AB92: 0 | AC92: 0 | AD92: 0 | AE92: =Z92+AC92 -> 0 | AF92: =AA92+AD92 -> 0 | AG92: =IF(COUNTIFS(SL_Income_Log!$B:$B,TEXT(B92,"0000")&"-"&TEXT(A92,"00"),SL_Income_Log!$C:$C,"youtube")>0,SUMIFS(SL_Income_Log!$D:$D,SL_Income_Log!$B:$B,TEXT(B92,"0000")&"-"&TEXT(A92,"00"),SL_Income_Log!$C:$C,"youtube"),MIN(Assumptions!$B$49+FLOOR((ROW()-2)/6,1)*Assumptions!$B$50,Assumptions!$B$51)) -> 16000 | AH92: =AG92*Assumptions!$B$104 -> 7088 | AI92: =AG92-AH92 -> 8912 | AJ92: =SUMIFS(SL_Income_Log!$D:$D,SL_Income_Log!$B:$B,TEXT(B92,"0000")&"-"&TEXT(A92,"00"),SL_Income_Log!$C:$C,"other") -> 0 | AK92: =AN91 -> 10000 | AL92: =L92+M92+T92+U92+AI92+AJ92-Y92-Z92-AB92-AC92+IF((Debt_Register!$C$2+Debt_Register!$C$6+Debt_Register!$C$7+Debt_Register!$C$8+Debt_Register!$C$9)>5,X92,0) -> 25298.079 | AM92: =AK92+AL92 -> 35298.079 | AN92: =MAX(Assumptions!$B$94,MIN(Assumptions!$B$93,AM92-AP92-BE92-BO92-BQ92)) -> 10000 | AO92: =AT91 -> 143522.38 | AP92: 0 | AQ92: 0 | AR92: 0 | AS92: =AO92 -> 143522.38 | AT92: =MAX(0,AO92-AP92-AR92-AS92) -> 0 | AU92: =IF(AV91>0,MIN(AV91,MAX(300,AM92-AP92-BO92-BQ92-AW92-AY92-BA92-BC92)),0) -> 0 | AV92: =MAX(0,AV91-AU92) -> 0 | AW92: =IF(AX91>0,MIN(250,AX91),0) -> 0 | AX92: =MAX(0,AX91-AW92) -> 0 | AY92: =IF(AZ91>0,MIN(200,AZ91),0) -> 0 | AZ92: =MAX(0,AZ91-AY92) -> 0 | BA92: =IF(AND(AV91<5,BB91>0),MIN(BB91,MAX(0,AM92-AP92-BO92-BQ92-AW92-AY92-BC92)),0) -> 0 | BB92: =MAX(0,BB91-BA92) -> 0 | BC92: =IF(BD91>0,MIN(50,BD91),0) -> 0 | BD92: =MAX(0,BD91-BC92) -> 0 | BE92: =AU92+AW92+AY92+BA92+BC92 -> 0 | BF92: 0 | BG92: =MAX(0,BG91-BF92) -> 5500 | BH92: 0 | BI92: =MAX(0,BI91-BH92) -> 5000 | BJ92: =IF(OR(B92<Assumptions!$B$111,AND(B92=Assumptions!$B$111,A92<=Assumptions!$B$112)),Assumptions!$B$110,0) -> 0 | BK92: =IF(B92<2027,Assumptions!$B$116+IF(OR(A92=4,A92=10),Assumptions!$B$117,0),IF(AND(B92=2027,A92<=4),IF(A92=4,MIN(950,Assumptions!$B$116+Assumptions!$B$117),Assumptions!$B$116),0)) -> 0 | BL92: =IF(OR(B92<2030,AND(B92=2030,A92<8)),Assumptions!$B$118,IF(AND(B92=2030,A92=8),MOD(11000,200),0)) -> 0 | BM92: =IF(OR(B92<Assumptions!$B$120,AND(B92=Assumptions!$B$120,A92<=Assumptions!$B$121)),Assumptions!$B$119,0) -> 0 | BN92: =IF(AND(B92<=Assumptions!$B$123,A92<=Assumptions!$B$124),Assumptions!$B$122,0) -> 0 | BO92: =BF92+BH92+BJ92+BK92+BL92+BM92+BN92 -> 0 | BP92: =SUMIFS(SL_Budget!$B:$B,SL_Budget!$C:$C,"'"&TEXT(DATE(B92,A92,1),"YYYY-MM")) -> 5053 | BQ92: =MAX(BP92, IFERROR(SUMIFS(ShadowLedger!D:D, ShadowLedger!C:C, ">="&DATE(B92,A92,1), ShadowLedger!C:C, "<"&EOMONTH(DATE(B92,A92,1),0)+1), 0)) -> 5053 | BR92: =BV91 -> 980719.56 | BS92: =IF((AV91+AX91+BB91+AZ91+BD91)>5,0,X92) -> 2594.7074 | BT92: =-MAX(0,AS92-MAX(0,(AM92-AP92-BE92-BO92-BQ92)-Assumptions!$B$93)-MAX(0,BY91-Assumptions!$B$91)) -> -109563.82 | BU92: =(BR92+BS92+MAX(0,BT92))*(Assumptions!$B$43-1) -> 6704.2367 | BV92: =BR92+BS92+BT92+BU92 -> 880454.69 | BW92: =BY91 -> 18713.476 | BX92: =-MIN(MAX(0,AS92-MAX(0,(AM92-AP92-BE92-BO92-BQ92)-Assumptions!$B$93)),MAX(0,BW92-Assumptions!$B$91)) -> -13713.476 | BY92: =BW92+BX92 -> 5000 | BZ92: =IF(A92=1,0,CB91) -> 39870 | CA92: =AH92 -> 7088 | CB92: =BZ92+CA92 -> 46958 | CC92: =CC91+(G92+J92)/(Salary_Schedule!E92*12/208) -> 1801.3573 | CD92: =CD91+(O92+R92)/(Salary_Schedule!G92*12/208) -> 130.28274 | CE92: =BV92 -> 880454.69 | CF92: =Assumptions!$B$55*(1+Assumptions!$B$56)^((B92-2025)+(A92-1)/12) -> 590153.11 | CG92: =-AT92 -> 0 | CH92: =-(AV92+AX92+BB92+AZ92+BD92+AF92+BG92+BI92) -> -10500 | CI92: =CC92*(Salary_Schedule!E92/173.33)*(1-Assumptions!$B$28)+CD92*(Salary_Schedule!G92/173.33)*(1-Assumptions!$B$28) -> 73871.023 | CJ92: =CE92+CF92+CG92+CH92+CI92 -> 1533978.8
A93: 8 | B93: 2033 | C93: 08/2033 | D93: =C92 -> 07/2033 | E93: =IF(I93>0,"FAT_BONUS",IF(M93+U93>0,"FAT_RSU","LEAN")) -> LEAN | F93: =Salary_Schedule!E93 -> 10365.29 | G93: =Assumptions!$B$8 -> 200 | H93: =F93*Assumptions!$B$58 -> 1036.529 | I93: =Salary_Schedule!F93 -> 0 | J93: =I93*Assumptions!$B$9 -> 0 | K93: =F93-G93-H93+I93-J93 -> 9128.761 | L93: =IF(COUNTIFS(SL_Income_Log!$B:$B,TEXT(B93,"0000")&"-"&TEXT(A93,"00"),SL_Income_Log!$C:$C,"salary",SL_Income_Log!$E:$E,"H")>0,SUMIFS(SL_Income_Log!$D:$D,SL_Income_Log!$B:$B,TEXT(B93,"0000")&"-"&TEXT(A93,"00"),SL_Income_Log!$C:$C,"salary",SL_Income_Log!$E:$E,"H"),K93*(1-Assumptions!$B$102)-Z93-Y93) -> 5477.2566 | M93: =RSU_Schedule!H92 -> 0 | N93: =Salary_Schedule!G93 -> 7882.62 | O93: =Assumptions!$B$19 -> 200 | P93: =N93*Assumptions!$B$59 -> 788.262 | Q93: =Salary_Schedule!H93 -> 0 | R93: =Q93*Assumptions!$B$20 -> 0 | S93: =N93-O93-P93+Q93-R93 -> 6894.358 | T93: =IF(COUNTIFS(SL_Income_Log!$B:$B,TEXT(B93,"0000")&"-"&TEXT(A93,"00"),SL_Income_Log!$C:$C,"salary",SL_Income_Log!$E:$E,"W")>0,SUMIFS(SL_Income_Log!$D:$D,SL_Income_Log!$B:$B,TEXT(B93,"0000")&"-"&TEXT(A93,"00"),SL_Income_Log!$C:$C,"salary",SL_Income_Log!$E:$E,"W"),S93*(1-Assumptions!$B$102)-AC93-AB93) -> 4136.6148 | U93: =RSU_Schedule!M92 -> 0 | V93: =H93*(1+Assumptions!$B$60)+Assumptions!$B$61 -> 1471.1406 | W93: =P93*(1+Assumptions!$B$60)+Assumptions!$B$61 -> 1123.5668 | X93: =V93+W93 -> 2594.7074 | Y93: 0 | Z93: 0 | AA93: 0 | AB93: 0 | AC93: 0 | AD93: 0 | AE93: =Z93+AC93 -> 0 | AF93: =AA93+AD93 -> 0 | AG93: =IF(COUNTIFS(SL_Income_Log!$B:$B,TEXT(B93,"0000")&"-"&TEXT(A93,"00"),SL_Income_Log!$C:$C,"youtube")>0,SUMIFS(SL_Income_Log!$D:$D,SL_Income_Log!$B:$B,TEXT(B93,"0000")&"-"&TEXT(A93,"00"),SL_Income_Log!$C:$C,"youtube"),MIN(Assumptions!$B$49+FLOOR((ROW()-2)/6,1)*Assumptions!$B$50,Assumptions!$B$51)) -> 16000 | AH93: =AG93*Assumptions!$B$104 -> 7088 | AI93: =AG93-AH93 -> 8912 | AJ93: =SUMIFS(SL_Income_Log!$D:$D,SL_Income_Log!$B:$B,TEXT(B93,"0000")&"-"&TEXT(A93,"00"),SL_Income_Log!$C:$C,"other") -> 0 | AK93: =AN92 -> 10000 | AL93: =L93+M93+T93+U93+AI93+AJ93-Y93-Z93-AB93-AC93+IF((Debt_Register!$C$2+Debt_Register!$C$6+Debt_Register!$C$7+Debt_Register!$C$8+Debt_Register!$C$9)>5,X93,0) -> 21120.579 | AM93: =AK93+AL93 -> 31120.579 | AN93: =MAX(Assumptions!$B$94,MIN(Assumptions!$B$93,AM93-AP93-BE93-BO93-BQ93)) -> 10000 | AO93: 0 | AP93: 0 | AQ93: 0 | AR93: 0 | AS93: 0 | AT93: 0 | AU93: =IF(AV92>0,MIN(AV92,MAX(300,AM93-AP93-BO93-BQ93-AW93-AY93-BA93-BC93)),0) -> 0 | AV93: =MAX(0,AV92-AU93) -> 0 | AW93: =IF(AX92>0,MIN(250,AX92),0) -> 0 | AX93: =MAX(0,AX92-AW93) -> 0 | AY93: =IF(AZ92>0,MIN(200,AZ92),0) -> 0 | AZ93: =MAX(0,AZ92-AY93) -> 0 | BA93: =IF(AND(AV92<5,BB92>0),MIN(BB92,MAX(0,AM93-AP93-BO93-BQ93-AW93-AY93-BC93)),0) -> 0 | BB93: =MAX(0,BB92-BA93) -> 0 | BC93: =IF(BD92>0,MIN(50,BD92),0) -> 0 | BD93: =MAX(0,BD92-BC93) -> 0 | BE93: =AU93+AW93+AY93+BA93+BC93 -> 0 | BF93: 0 | BG93: =MAX(0,BG92-BF93) -> 5500 | BH93: 0 | BI93: =MAX(0,BI92-BH93) -> 5000 | BJ93: =IF(OR(B93<Assumptions!$B$111,AND(B93=Assumptions!$B$111,A93<=Assumptions!$B$112)),Assumptions!$B$110,0) -> 0 | BK93: =IF(B93<2027,Assumptions!$B$116+IF(OR(A93=4,A93=10),Assumptions!$B$117,0),IF(AND(B93=2027,A93<=4),IF(A93=4,MIN(950,Assumptions!$B$116+Assumptions!$B$117),Assumptions!$B$116),0)) -> 0 | BL93: =IF(OR(B93<2030,AND(B93=2030,A93<8)),Assumptions!$B$118,IF(AND(B93=2030,A93=8),MOD(11000,200),0)) -> 0 | BM93: =IF(OR(B93<Assumptions!$B$120,AND(B93=Assumptions!$B$120,A93<=Assumptions!$B$121)),Assumptions!$B$119,0) -> 0 | BN93: =IF(AND(B93<=Assumptions!$B$123,A93<=Assumptions!$B$124),Assumptions!$B$122,0) -> 0 | BO93: =BF93+BH93+BJ93+BK93+BL93+BM93+BN93 -> 0 | BP93: =SUMIFS(SL_Budget!$B:$B,SL_Budget!$C:$C,"'"&TEXT(DATE(B93,A93,1),"YYYY-MM")) -> 5053 | BQ93: =MAX(BP93, IFERROR(SUMIFS(ShadowLedger!D:D, ShadowLedger!C:C, ">="&DATE(B93,A93,1), ShadowLedger!C:C, "<"&EOMONTH(DATE(B93,A93,1),0)+1), 0)) -> 5053 | BR93: =BV92 -> 880454.69 | BS93: =IF((AV92+AX92+BB92+AZ92+BD92)>5,0,X93) -> 2594.7074 | BT93: =IF(BY92>=Assumptions!$B$92,MAX(0,(AM93-BE93-BO93-BQ93)-Assumptions!$B$93),MAX(0,(AM93-BE93-BO93-BQ93)-Assumptions!$B$93)*Assumptions!$B$99) -> 12854.063 | BU93: =(BR93+BS93+MAX(0,BT93))*(Assumptions!$B$43-1) -> 6108.2698 | BV93: =BR93+BS93+BT93+BU93 -> 902011.73 | BW93: =BY92 -> 5000 | BX93: =IF(BY92<Assumptions!$B$92,MAX(0,(AM93-BE93-BO93-BQ93)-Assumptions!$B$93)*Assumptions!$B$98,0) -> 3213.5158 | BY93: =BW93+BX93 -> 8213.5158 | BZ93: =IF(A93=1,0,CB92) -> 46958 | CA93: =AH93 -> 7088 | CB93: =BZ93+CA93 -> 54046 | CC93: =CC92+(G93+J93)/(Salary_Schedule!E93*12/208) -> 1801.6918 | CD93: =CD92+(O93+R93)/(Salary_Schedule!G93*12/208) -> 130.72252 | CE93: =BV93 -> 902011.73 | CF93: =Assumptions!$B$55*(1+Assumptions!$B$56)^((B93-2025)+(A93-1)/12) -> 590885.78 | CG93: =-AT93 -> 0 | CH93: =-(AV93+AX93+BB93+AZ93+BD93+AF93+BG93+BI93) -> -10500 | CI93: =CC93*(Salary_Schedule!E93/173.33)*(1-Assumptions!$B$28)+CD93*(Salary_Schedule!G93/173.33)*(1-Assumptions!$B$28) -> 73897.023 | CJ93: =CE93+CF93+CG93+CH93+CI93 -> 1556294.5
A94: 9 | B94: 2033 | C94: 09/2033 | D94: =C93 -> 08/2033 | E94: =IF(I94>0,"FAT_BONUS",IF(M94+U94>0,"FAT_RSU","LEAN")) -> LEAN | F94: =Salary_Schedule!E94 -> 10365.29 | G94: =Assumptions!$B$8 -> 200 | H94: =F94*Assumptions!$B$58 -> 1036.529 | I94: =Salary_Schedule!F94 -> 0 | J94: =I94*Assumptions!$B$9 -> 0 | K94: =F94-G94-H94+I94-J94 -> 9128.761 | L94: =IF(COUNTIFS(SL_Income_Log!$B:$B,TEXT(B94,"0000")&"-"&TEXT(A94,"00"),SL_Income_Log!$C:$C,"salary",SL_Income_Log!$E:$E,"H")>0,SUMIFS(SL_Income_Log!$D:$D,SL_Income_Log!$B:$B,TEXT(B94,"0000")&"-"&TEXT(A94,"00"),SL_Income_Log!$C:$C,"salary",SL_Income_Log!$E:$E,"H"),K94*(1-Assumptions!$B$102)-Z94-Y94) -> 5477.2566 | M94: =RSU_Schedule!H93 -> 0 | N94: =Salary_Schedule!G94 -> 7882.62 | O94: =Assumptions!$B$19 -> 200 | P94: =N94*Assumptions!$B$59 -> 788.262 | Q94: =Salary_Schedule!H94 -> 0 | R94: =Q94*Assumptions!$B$20 -> 0 | S94: =N94-O94-P94+Q94-R94 -> 6894.358 | T94: =IF(COUNTIFS(SL_Income_Log!$B:$B,TEXT(B94,"0000")&"-"&TEXT(A94,"00"),SL_Income_Log!$C:$C,"salary",SL_Income_Log!$E:$E,"W")>0,SUMIFS(SL_Income_Log!$D:$D,SL_Income_Log!$B:$B,TEXT(B94,"0000")&"-"&TEXT(A94,"00"),SL_Income_Log!$C:$C,"salary",SL_Income_Log!$E:$E,"W"),S94*(1-Assumptions!$B$102)-AC94-AB94) -> 4136.6148 | U94: =RSU_Schedule!M93 -> 0 | V94: =H94*(1+Assumptions!$B$60)+Assumptions!$B$61 -> 1471.1406 | W94: =P94*(1+Assumptions!$B$60)+Assumptions!$B$61 -> 1123.5668 | X94: =V94+W94 -> 2594.7074 | Y94: 0 | Z94: 0 | AA94: 0 | AB94: 0 | AC94: 0 | AD94: 0 | AE94: =Z94+AC94 -> 0 | AF94: =AA94+AD94 -> 0 | AG94: =IF(COUNTIFS(SL_Income_Log!$B:$B,TEXT(B94,"0000")&"-"&TEXT(A94,"00"),SL_Income_Log!$C:$C,"youtube")>0,SUMIFS(SL_Income_Log!$D:$D,SL_Income_Log!$B:$B,TEXT(B94,"0000")&"-"&TEXT(A94,"00"),SL_Income_Log!$C:$C,"youtube"),MIN(Assumptions!$B$49+FLOOR((ROW()-2)/6,1)*Assumptions!$B$50,Assumptions!$B$51)) -> 16000 | AH94: =AG94*Assumptions!$B$104 -> 7088 | AI94: =AG94-AH94 -> 8912 | AJ94: =SUMIFS(SL_Income_Log!$D:$D,SL_Income_Log!$B:$B,TEXT(B94,"0000")&"-"&TEXT(A94,"00"),SL_Income_Log!$C:$C,"other") -> 0 | AK94: =AN93 -> 10000 | AL94: =L94+M94+T94+U94+AI94+AJ94-Y94-Z94-AB94-AC94+IF((Debt_Register!$C$2+Debt_Register!$C$6+Debt_Register!$C$7+Debt_Register!$C$8+Debt_Register!$C$9)>5,X94,0) -> 21120.579 | AM94: =AK94+AL94 -> 31120.579 | AN94: =MAX(Assumptions!$B$94,MIN(Assumptions!$B$93,AM94-AP94-BE94-BO94-BQ94)) -> 10000 | AO94: 0 | AP94: 0 | AQ94: 0 | AR94: 0 | AS94: 0 | AT94: 0 | AU94: =IF(AV93>0,MIN(AV93,MAX(300,AM94-AP94-BO94-BQ94-AW94-AY94-BA94-BC94)),0) -> 0 | AV94: =MAX(0,AV93-AU94) -> 0 | AW94: =IF(AX93>0,MIN(250,AX93),0) -> 0 | AX94: =MAX(0,AX93-AW94) -> 0 | AY94: =IF(AZ93>0,MIN(200,AZ93),0) -> 0 | AZ94: =MAX(0,AZ93-AY94) -> 0 | BA94: =IF(AND(AV93<5,BB93>0),MIN(BB93,MAX(0,AM94-AP94-BO94-BQ94-AW94-AY94-BC94)),0) -> 0 | BB94: =MAX(0,BB93-BA94) -> 0 | BC94: =IF(BD93>0,MIN(50,BD93),0) -> 0 | BD94: =MAX(0,BD93-BC94) -> 0 | BE94: =AU94+AW94+AY94+BA94+BC94 -> 0 | BF94: 0 | BG94: =MAX(0,BG93-BF94) -> 5500 | BH94: 0 | BI94: =MAX(0,BI93-BH94) -> 5000 | BJ94: =IF(OR(B94<Assumptions!$B$111,AND(B94=Assumptions!$B$111,A94<=Assumptions!$B$112)),Assumptions!$B$110,0) -> 0 | BK94: =IF(B94<2027,Assumptions!$B$116+IF(OR(A94=4,A94=10),Assumptions!$B$117,0),IF(AND(B94=2027,A94<=4),IF(A94=4,MIN(950,Assumptions!$B$116+Assumptions!$B$117),Assumptions!$B$116),0)) -> 0 | BL94: =IF(OR(B94<2030,AND(B94=2030,A94<8)),Assumptions!$B$118,IF(AND(B94=2030,A94=8),MOD(11000,200),0)) -> 0 | BM94: =IF(OR(B94<Assumptions!$B$120,AND(B94=Assumptions!$B$120,A94<=Assumptions!$B$121)),Assumptions!$B$119,0) -> 0 | BN94: =IF(AND(B94<=Assumptions!$B$123,A94<=Assumptions!$B$124),Assumptions!$B$122,0) -> 0 | BO94: =BF94+BH94+BJ94+BK94+BL94+BM94+BN94 -> 0 | BP94: =SUMIFS(SL_Budget!$B:$B,SL_Budget!$C:$C,"'"&TEXT(DATE(B94,A94,1),"YYYY-MM")) -> 5053 | BQ94: =MAX(BP94, IFERROR(SUMIFS(ShadowLedger!D:D, ShadowLedger!C:C, ">="&DATE(B94,A94,1), ShadowLedger!C:C, "<"&EOMONTH(DATE(B94,A94,1),0)+1), 0)) -> 5053 | BR94: =BV93 -> 902011.73 | BS94: =IF((AV93+AX93+BB93+AZ93+BD93)>5,0,X94) -> 2594.7074 | BT94: =IF(BY93>=Assumptions!$B$92,MAX(0,(AM94-BE94-BO94-BQ94)-Assumptions!$B$93),MAX(0,(AM94-BE94-BO94-BQ94)-Assumptions!$B$93)*Assumptions!$B$99) -> 12854.063 | BU94: =(BR94+BS94+MAX(0,BT94))*(Assumptions!$B$43-1) -> 6255.2457 | BV94: =BR94+BS94+BT94+BU94 -> 923715.74 | BW94: =BY93 -> 8213.5158 | BX94: =IF(BY93<Assumptions!$B$92,MAX(0,(AM94-BE94-BO94-BQ94)-Assumptions!$B$93)*Assumptions!$B$98,0) -> 3213.5158 | BY94: =BW94+BX94 -> 11427.032 | BZ94: =IF(A94=1,0,CB93) -> 54046 | CA94: =AH94 -> 7088 | CB94: =BZ94+CA94 -> 61134 | CC94: =CC93+(G94+J94)/(Salary_Schedule!E94*12/208) -> 1802.0262 | CD94: =CD93+(O94+R94)/(Salary_Schedule!G94*12/208) -> 131.16231 | CE94: =BV94 -> 923715.74 | CF94: =Assumptions!$B$55*(1+Assumptions!$B$56)^((B94-2025)+(A94-1)/12) -> 591619.36 | CG94: =-AT94 -> 0 | CH94: =-(AV94+AX94+BB94+AZ94+BD94+AF94+BG94+BI94) -> -10500 | CI94: =CC94*(Salary_Schedule!E94/173.33)*(1-Assumptions!$B$28)+CD94*(Salary_Schedule!G94/173.33)*(1-Assumptions!$B$28) -> 73923.024 | CJ94: =CE94+CF94+CG94+CH94+CI94 -> 1578758.1
A95: 10 | B95: 2033 | C95: 10/2033 | D95: =C94 -> 09/2033 | E95: =IF(I95>0,"FAT_BONUS",IF(M95+U95>0,"FAT_RSU","LEAN")) -> FAT_RSU | F95: =Salary_Schedule!E95 -> 10365.29 | G95: =Assumptions!$B$8 -> 200 | H95: =F95*Assumptions!$B$58 -> 1036.529 | I95: =Salary_Schedule!F95 -> 0 | J95: =I95*Assumptions!$B$9 -> 0 | K95: =F95-G95-H95+I95-J95 -> 9128.761 | L95: =IF(COUNTIFS(SL_Income_Log!$B:$B,TEXT(B95,"0000")&"-"&TEXT(A95,"00"),SL_Income_Log!$C:$C,"salary",SL_Income_Log!$E:$E,"H")>0,SUMIFS(SL_Income_Log!$D:$D,SL_Income_Log!$B:$B,TEXT(B95,"0000")&"-"&TEXT(A95,"00"),SL_Income_Log!$C:$C,"salary",SL_Income_Log!$E:$E,"H"),K95*(1-Assumptions!$B$102)-Z95-Y95) -> 5477.2566 | M95: =RSU_Schedule!H94 -> 2784.99 | N95: =Salary_Schedule!G95 -> 7882.62 | O95: =Assumptions!$B$19 -> 200 | P95: =N95*Assumptions!$B$59 -> 788.262 | Q95: =Salary_Schedule!H95 -> 0 | R95: =Q95*Assumptions!$B$20 -> 0 | S95: =N95-O95-P95+Q95-R95 -> 6894.358 | T95: =IF(COUNTIFS(SL_Income_Log!$B:$B,TEXT(B95,"0000")&"-"&TEXT(A95,"00"),SL_Income_Log!$C:$C,"salary",SL_Income_Log!$E:$E,"W")>0,SUMIFS(SL_Income_Log!$D:$D,SL_Income_Log!$B:$B,TEXT(B95,"0000")&"-"&TEXT(A95,"00"),SL_Income_Log!$C:$C,"salary",SL_Income_Log!$E:$E,"W"),S95*(1-Assumptions!$B$102)-AC95-AB95) -> 4136.6148 | U95: =RSU_Schedule!M94 -> 1392.51 | V95: =H95*(1+Assumptions!$B$60)+Assumptions!$B$61 -> 1471.1406 | W95: =P95*(1+Assumptions!$B$60)+Assumptions!$B$61 -> 1123.5668 | X95: =V95+W95 -> 2594.7074 | Y95: 0 | Z95: 0 | AA95: 0 | AB95: 0 | AC95: 0 | AD95: 0 | AE95: =Z95+AC95 -> 0 | AF95: =AA95+AD95 -> 0 | AG95: =IF(COUNTIFS(SL_Income_Log!$B:$B,TEXT(B95,"0000")&"-"&TEXT(A95,"00"),SL_Income_Log!$C:$C,"youtube")>0,SUMIFS(SL_Income_Log!$D:$D,SL_Income_Log!$B:$B,TEXT(B95,"0000")&"-"&TEXT(A95,"00"),SL_Income_Log!$C:$C,"youtube"),MIN(Assumptions!$B$49+FLOOR((ROW()-2)/6,1)*Assumptions!$B$50,Assumptions!$B$51)) -> 16000 | AH95: =AG95*Assumptions!$B$104 -> 7088 | AI95: =AG95-AH95 -> 8912 | AJ95: =SUMIFS(SL_Income_Log!$D:$D,SL_Income_Log!$B:$B,TEXT(B95,"0000")&"-"&TEXT(A95,"00"),SL_Income_Log!$C:$C,"other") -> 0 | AK95: =AN94 -> 10000 | AL95: =L95+M95+T95+U95+AI95+AJ95-Y95-Z95-AB95-AC95+IF((Debt_Register!$C$2+Debt_Register!$C$6+Debt_Register!$C$7+Debt_Register!$C$8+Debt_Register!$C$9)>5,X95,0) -> 25298.079 | AM95: =AK95+AL95 -> 35298.079 | AN95: =MAX(Assumptions!$B$94,MIN(Assumptions!$B$93,AM95-AP95-BE95-BO95-BQ95)) -> 10000 | AO95: 0 | AP95: 0 | AQ95: 0 | AR95: 0 | AS95: 0 | AT95: 0 | AU95: =IF(AV94>0,MIN(AV94,MAX(300,AM95-AP95-BO95-BQ95-AW95-AY95-BA95-BC95)),0) -> 0 | AV95: =MAX(0,AV94-AU95) -> 0 | AW95: =IF(AX94>0,MIN(250,AX94),0) -> 0 | AX95: =MAX(0,AX94-AW95) -> 0 | AY95: =IF(AZ94>0,MIN(200,AZ94),0) -> 0 | AZ95: =MAX(0,AZ94-AY95) -> 0 | BA95: =IF(AND(AV94<5,BB94>0),MIN(BB94,MAX(0,AM95-AP95-BO95-BQ95-AW95-AY95-BC95)),0) -> 0 | BB95: =MAX(0,BB94-BA95) -> 0 | BC95: =IF(BD94>0,MIN(50,BD94),0) -> 0 | BD95: =MAX(0,BD94-BC95) -> 0 | BE95: =AU95+AW95+AY95+BA95+BC95 -> 0 | BF95: 0 | BG95: =MAX(0,BG94-BF95) -> 5500 | BH95: 0 | BI95: =MAX(0,BI94-BH95) -> 5000 | BJ95: =IF(OR(B95<Assumptions!$B$111,AND(B95=Assumptions!$B$111,A95<=Assumptions!$B$112)),Assumptions!$B$110,0) -> 0 | BK95: =IF(B95<2027,Assumptions!$B$116+IF(OR(A95=4,A95=10),Assumptions!$B$117,0),IF(AND(B95=2027,A95<=4),IF(A95=4,MIN(950,Assumptions!$B$116+Assumptions!$B$117),Assumptions!$B$116),0)) -> 0 | BL95: =IF(OR(B95<2030,AND(B95=2030,A95<8)),Assumptions!$B$118,IF(AND(B95=2030,A95=8),MOD(11000,200),0)) -> 0 | BM95: =IF(OR(B95<Assumptions!$B$120,AND(B95=Assumptions!$B$120,A95<=Assumptions!$B$121)),Assumptions!$B$119,0) -> 0 | BN95: =IF(AND(B95<=Assumptions!$B$123,A95<=Assumptions!$B$124),Assumptions!$B$122,0) -> 0 | BO95: =BF95+BH95+BJ95+BK95+BL95+BM95+BN95 -> 0 | BP95: =SUMIFS(SL_Budget!$B:$B,SL_Budget!$C:$C,"'"&TEXT(DATE(B95,A95,1),"YYYY-MM")) -> 5053 | BQ95: =MAX(BP95, IFERROR(SUMIFS(ShadowLedger!D:D, ShadowLedger!C:C, ">="&DATE(B95,A95,1), ShadowLedger!C:C, "<"&EOMONTH(DATE(B95,A95,1),0)+1), 0)) -> 5053 | BR95: =BV94 -> 923715.74 | BS95: =IF((AV94+AX94+BB94+AZ94+BD94)>5,0,X95) -> 2594.7074 | BT95: =IF(BY94>=Assumptions!$B$92,MAX(0,(AM95-BE95-BO95-BQ95)-Assumptions!$B$93),MAX(0,(AM95-BE95-BO95-BQ95)-Assumptions!$B$93)*Assumptions!$B$99) -> 16196.063 | BU95: =(BR95+BS95+MAX(0,BT95))*(Assumptions!$B$43-1) -> 6426.0094 | BV95: =BR95+BS95+BT95+BU95 -> 948932.52 | BW95: =BY94 -> 11427.032 | BX95: =IF(BY94<Assumptions!$B$92,MAX(0,(AM95-BE95-BO95-BQ95)-Assumptions!$B$93)*Assumptions!$B$98,0) -> 4049.0158 | BY95: =BW95+BX95 -> 15476.047 | BZ95: =IF(A95=1,0,CB94) -> 61134 | CA95: =AH95 -> 7088 | CB95: =BZ95+CA95 -> 68222 | CC95: =CC94+(G95+J95)/(Salary_Schedule!E95*12/208) -> 1802.3607 | CD95: =CD94+(O95+R95)/(Salary_Schedule!G95*12/208) -> 131.6021 | CE95: =BV95 -> 948932.52 | CF95: =Assumptions!$B$55*(1+Assumptions!$B$56)^((B95-2025)+(A95-1)/12) -> 592353.85 | CG95: =-AT95 -> 0 | CH95: =-(AV95+AX95+BB95+AZ95+BD95+AF95+BG95+BI95) -> -10500 | CI95: =CC95*(Salary_Schedule!E95/173.33)*(1-Assumptions!$B$28)+CD95*(Salary_Schedule!G95/173.33)*(1-Assumptions!$B$28) -> 73949.024 | CJ95: =CE95+CF95+CG95+CH95+CI95 -> 1604735.4
A96: 11 | B96: 2033 | C96: 11/2033 | D96: =C95 -> 10/2033 | E96: =IF(I96>0,"FAT_BONUS",IF(M96+U96>0,"FAT_RSU","LEAN")) -> LEAN | F96: =Salary_Schedule!E96 -> 10365.29 | G96: =Assumptions!$B$8 -> 200 | H96: =F96*Assumptions!$B$58 -> 1036.529 | I96: =Salary_Schedule!F96 -> 0 | J96: =I96*Assumptions!$B$9 -> 0 | K96: =F96-G96-H96+I96-J96 -> 9128.761 | L96: =IF(COUNTIFS(SL_Income_Log!$B:$B,TEXT(B96,"0000")&"-"&TEXT(A96,"00"),SL_Income_Log!$C:$C,"salary",SL_Income_Log!$E:$E,"H")>0,SUMIFS(SL_Income_Log!$D:$D,SL_Income_Log!$B:$B,TEXT(B96,"0000")&"-"&TEXT(A96,"00"),SL_Income_Log!$C:$C,"salary",SL_Income_Log!$E:$E,"H"),K96*(1-Assumptions!$B$102)-Z96-Y96) -> 5477.2566 | M96: =RSU_Schedule!H95 -> 0 | N96: =Salary_Schedule!G96 -> 7882.62 | O96: =Assumptions!$B$19 -> 200 | P96: =N96*Assumptions!$B$59 -> 788.262 | Q96: =Salary_Schedule!H96 -> 0 | R96: =Q96*Assumptions!$B$20 -> 0 | S96: =N96-O96-P96+Q96-R96 -> 6894.358 | T96: =IF(COUNTIFS(SL_Income_Log!$B:$B,TEXT(B96,"0000")&"-"&TEXT(A96,"00"),SL_Income_Log!$C:$C,"salary",SL_Income_Log!$E:$E,"W")>0,SUMIFS(SL_Income_Log!$D:$D,SL_Income_Log!$B:$B,TEXT(B96,"0000")&"-"&TEXT(A96,"00"),SL_Income_Log!$C:$C,"salary",SL_Income_Log!$E:$E,"W"),S96*(1-Assumptions!$B$102)-AC96-AB96) -> 4136.6148 | U96: =RSU_Schedule!M95 -> 0 | V96: =H96*(1+Assumptions!$B$60)+Assumptions!$B$61 -> 1471.1406 | W96: =P96*(1+Assumptions!$B$60)+Assumptions!$B$61 -> 1123.5668 | X96: =V96+W96 -> 2594.7074 | Y96: 0 | Z96: 0 | AA96: 0 | AB96: 0 | AC96: 0 | AD96: 0 | AE96: =Z96+AC96 -> 0 | AF96: =AA96+AD96 -> 0 | AG96: =IF(COUNTIFS(SL_Income_Log!$B:$B,TEXT(B96,"0000")&"-"&TEXT(A96,"00"),SL_Income_Log!$C:$C,"youtube")>0,SUMIFS(SL_Income_Log!$D:$D,SL_Income_Log!$B:$B,TEXT(B96,"0000")&"-"&TEXT(A96,"00"),SL_Income_Log!$C:$C,"youtube"),MIN(Assumptions!$B$49+FLOOR((ROW()-2)/6,1)*Assumptions!$B$50,Assumptions!$B$51)) -> 16000 | AH96: =AG96*Assumptions!$B$104 -> 7088 | AI96: =AG96-AH96 -> 8912 | AJ96: =SUMIFS(SL_Income_Log!$D:$D,SL_Income_Log!$B:$B,TEXT(B96,"0000")&"-"&TEXT(A96,"00"),SL_Income_Log!$C:$C,"other") -> 0 | AK96: =AN95 -> 10000 | AL96: =L96+M96+T96+U96+AI96+AJ96-Y96-Z96-AB96-AC96+IF((Debt_Register!$C$2+Debt_Register!$C$6+Debt_Register!$C$7+Debt_Register!$C$8+Debt_Register!$C$9)>5,X96,0) -> 21120.579 | AM96: =AK96+AL96 -> 31120.579 | AN96: =MAX(Assumptions!$B$94,MIN(Assumptions!$B$93,AM96-AP96-BE96-BO96-BQ96)) -> 10000 | AO96: 0 | AP96: 0 | AQ96: 0 | AR96: 0 | AS96: 0 | AT96: 0 | AU96: =IF(AV95>0,MIN(AV95,MAX(300,AM96-AP96-BO96-BQ96-AW96-AY96-BA96-BC96)),0) -> 0 | AV96: =MAX(0,AV95-AU96) -> 0 | AW96: =IF(AX95>0,MIN(250,AX95),0) -> 0 | AX96: =MAX(0,AX95-AW96) -> 0 | AY96: =IF(AZ95>0,MIN(200,AZ95),0) -> 0 | AZ96: =MAX(0,AZ95-AY96) -> 0 | BA96: =IF(AND(AV95<5,BB95>0),MIN(BB95,MAX(0,AM96-AP96-BO96-BQ96-AW96-AY96-BC96)),0) -> 0 | BB96: =MAX(0,BB95-BA96) -> 0 | BC96: =IF(BD95>0,MIN(50,BD95),0) -> 0 | BD96: =MAX(0,BD95-BC96) -> 0 | BE96: =AU96+AW96+AY96+BA96+BC96 -> 0 | BF96: 0 | BG96: =MAX(0,BG95-BF96) -> 5500 | BH96: 0 | BI96: =MAX(0,BI95-BH96) -> 5000 | BJ96: =IF(OR(B96<Assumptions!$B$111,AND(B96=Assumptions!$B$111,A96<=Assumptions!$B$112)),Assumptions!$B$110,0) -> 0 | BK96: =IF(B96<2027,Assumptions!$B$116+IF(OR(A96=4,A96=10),Assumptions!$B$117,0),IF(AND(B96=2027,A96<=4),IF(A96=4,MIN(950,Assumptions!$B$116+Assumptions!$B$117),Assumptions!$B$116),0)) -> 0 | BL96: =IF(OR(B96<2030,AND(B96=2030,A96<8)),Assumptions!$B$118,IF(AND(B96=2030,A96=8),MOD(11000,200),0)) -> 0 | BM96: =IF(OR(B96<Assumptions!$B$120,AND(B96=Assumptions!$B$120,A96<=Assumptions!$B$121)),Assumptions!$B$119,0) -> 0 | BN96: =IF(AND(B96<=Assumptions!$B$123,A96<=Assumptions!$B$124),Assumptions!$B$122,0) -> 0 | BO96: =BF96+BH96+BJ96+BK96+BL96+BM96+BN96 -> 0 | BP96: =SUMIFS(SL_Budget!$B:$B,SL_Budget!$C:$C,"'"&TEXT(DATE(B96,A96,1),"YYYY-MM")) -> 5053 | BQ96: =MAX(BP96, IFERROR(SUMIFS(ShadowLedger!D:D, ShadowLedger!C:C, ">="&DATE(B96,A96,1), ShadowLedger!C:C, "<"&EOMONTH(DATE(B96,A96,1),0)+1), 0)) -> 5053 | BR96: =BV95 -> 948932.52 | BS96: =IF((AV95+AX95+BB95+AZ95+BD95)>5,0,X96) -> 2594.7074 | BT96: =IF(BY95>=Assumptions!$B$92,MAX(0,(AM96-BE96-BO96-BQ96)-Assumptions!$B$93),MAX(0,(AM96-BE96-BO96-BQ96)-Assumptions!$B$93)*Assumptions!$B$99) -> 16067.579 | BU96: =(BR96+BS96+MAX(0,BT96))*(Assumptions!$B$43-1) -> 6597.0614 | BV96: =BR96+BS96+BT96+BU96 -> 974191.87 | BW96: =BY95 -> 15476.047 | BX96: =IF(BY95<Assumptions!$B$92,MAX(0,(AM96-BE96-BO96-BQ96)-Assumptions!$B$93)*Assumptions!$B$98,0) -> 0 | BY96: =BW96+BX96 -> 15476.047 | BZ96: =IF(A96=1,0,CB95) -> 68222 | CA96: =AH96 -> 7088 | CB96: =BZ96+CA96 -> 75310 | CC96: =CC95+(G96+J96)/(Salary_Schedule!E96*12/208) -> 1802.6951 | CD96: =CD95+(O96+R96)/(Salary_Schedule!G96*12/208) -> 132.04188 | CE96: =BV96 -> 974191.87 | CF96: =Assumptions!$B$55*(1+Assumptions!$B$56)^((B96-2025)+(A96-1)/12) -> 593089.25 | CG96: =-AT96 -> 0 | CH96: =-(AV96+AX96+BB96+AZ96+BD96+AF96+BG96+BI96) -> -10500 | CI96: =CC96*(Salary_Schedule!E96/173.33)*(1-Assumptions!$B$28)+CD96*(Salary_Schedule!G96/173.33)*(1-Assumptions!$B$28) -> 73975.025 | CJ96: =CE96+CF96+CG96+CH96+CI96 -> 1630756.1
A97: 12 | B97: 2033 | C97: 12/2033 | D97: =C96 -> 11/2033 | E97: =IF(I97>0,"FAT_BONUS",IF(M97+U97>0,"FAT_RSU","LEAN")) -> LEAN | F97: =Salary_Schedule!E97 -> 10365.29 | G97: =Assumptions!$B$8 -> 200 | H97: =F97*Assumptions!$B$58 -> 1036.529 | I97: =Salary_Schedule!F97 -> 0 | J97: =I97*Assumptions!$B$9 -> 0 | K97: =F97-G97-H97+I97-J97 -> 9128.761 | L97: =IF(COUNTIFS(SL_Income_Log!$B:$B,TEXT(B97,"0000")&"-"&TEXT(A97,"00"),SL_Income_Log!$C:$C,"salary",SL_Income_Log!$E:$E,"H")>0,SUMIFS(SL_Income_Log!$D:$D,SL_Income_Log!$B:$B,TEXT(B97,"0000")&"-"&TEXT(A97,"00"),SL_Income_Log!$C:$C,"salary",SL_Income_Log!$E:$E,"H"),K97*(1-Assumptions!$B$102)-Z97-Y97) -> 5477.2566 | M97: =RSU_Schedule!H96 -> 0 | N97: =Salary_Schedule!G97 -> 7882.62 | O97: =Assumptions!$B$19 -> 200 | P97: =N97*Assumptions!$B$59 -> 788.262 | Q97: =Salary_Schedule!H97 -> 0 | R97: =Q97*Assumptions!$B$20 -> 0 | S97: =N97-O97-P97+Q97-R97 -> 6894.358 | T97: =IF(COUNTIFS(SL_Income_Log!$B:$B,TEXT(B97,"0000")&"-"&TEXT(A97,"00"),SL_Income_Log!$C:$C,"salary",SL_Income_Log!$E:$E,"W")>0,SUMIFS(SL_Income_Log!$D:$D,SL_Income_Log!$B:$B,TEXT(B97,"0000")&"-"&TEXT(A97,"00"),SL_Income_Log!$C:$C,"salary",SL_Income_Log!$E:$E,"W"),S97*(1-Assumptions!$B$102)-AC97-AB97) -> 4136.6148 | U97: =RSU_Schedule!M96 -> 0 | V97: =H97*(1+Assumptions!$B$60)+Assumptions!$B$61 -> 1471.1406 | W97: =P97*(1+Assumptions!$B$60)+Assumptions!$B$61 -> 1123.5668 | X97: =V97+W97 -> 2594.7074 | Y97: 0 | Z97: 0 | AA97: 0 | AB97: 0 | AC97: 0 | AD97: 0 | AE97: =Z97+AC97 -> 0 | AF97: =AA97+AD97 -> 0 | AG97: =IF(COUNTIFS(SL_Income_Log!$B:$B,TEXT(B97,"0000")&"-"&TEXT(A97,"00"),SL_Income_Log!$C:$C,"youtube")>0,SUMIFS(SL_Income_Log!$D:$D,SL_Income_Log!$B:$B,TEXT(B97,"0000")&"-"&TEXT(A97,"00"),SL_Income_Log!$C:$C,"youtube"),MIN(Assumptions!$B$49+FLOOR((ROW()-2)/6,1)*Assumptions!$B$50,Assumptions!$B$51)) -> 16000 | AH97: =AG97*Assumptions!$B$104 -> 7088 | AI97: =AG97-AH97 -> 8912 | AJ97: =SUMIFS(SL_Income_Log!$D:$D,SL_Income_Log!$B:$B,TEXT(B97,"0000")&"-"&TEXT(A97,"00"),SL_Income_Log!$C:$C,"other") -> 0 | AK97: =AN96 -> 10000 | AL97: =L97+M97+T97+U97+AI97+AJ97-Y97-Z97-AB97-AC97+IF((Debt_Register!$C$2+Debt_Register!$C$6+Debt_Register!$C$7+Debt_Register!$C$8+Debt_Register!$C$9)>5,X97,0) -> 21120.579 | AM97: =AK97+AL97 -> 31120.579 | AN97: =MAX(Assumptions!$B$94,MIN(Assumptions!$B$93,AM97-AP97-BE97-BO97-BQ97)) -> 10000 | AO97: 0 | AP97: 0 | AQ97: 0 | AR97: 0 | AS97: 0 | AT97: 0 | AU97: =IF(AV96>0,MIN(AV96,MAX(300,AM97-AP97-BO97-BQ97-AW97-AY97-BA97-BC97)),0) -> 0 | AV97: =MAX(0,AV96-AU97) -> 0 | AW97: =IF(AX96>0,MIN(250,AX96),0) -> 0 | AX97: =MAX(0,AX96-AW97) -> 0 | AY97: =IF(AZ96>0,MIN(200,AZ96),0) -> 0 | AZ97: =MAX(0,AZ96-AY97) -> 0 | BA97: =IF(AND(AV96<5,BB96>0),MIN(BB96,MAX(0,AM97-AP97-BO97-BQ97-AW97-AY97-BC97)),0) -> 0 | BB97: =MAX(0,BB96-BA97) -> 0 | BC97: =IF(BD96>0,MIN(50,BD96),0) -> 0 | BD97: =MAX(0,BD96-BC97) -> 0 | BE97: =AU97+AW97+AY97+BA97+BC97 -> 0 | BF97: 0 | BG97: =MAX(0,BG96-BF97) -> 5500 | BH97: 0 | BI97: =MAX(0,BI96-BH97) -> 5000 | BJ97: =IF(OR(B97<Assumptions!$B$111,AND(B97=Assumptions!$B$111,A97<=Assumptions!$B$112)),Assumptions!$B$110,0) -> 0 | BK97: =IF(B97<2027,Assumptions!$B$116+IF(OR(A97=4,A97=10),Assumptions!$B$117,0),IF(AND(B97=2027,A97<=4),IF(A97=4,MIN(950,Assumptions!$B$116+Assumptions!$B$117),Assumptions!$B$116),0)) -> 0 | BL97: =IF(OR(B97<2030,AND(B97=2030,A97<8)),Assumptions!$B$118,IF(AND(B97=2030,A97=8),MOD(11000,200),0)) -> 0 | BM97: =IF(OR(B97<Assumptions!$B$120,AND(B97=Assumptions!$B$120,A97<=Assumptions!$B$121)),Assumptions!$B$119,0) -> 0 | BN97: =IF(AND(B97<=Assumptions!$B$123,A97<=Assumptions!$B$124),Assumptions!$B$122,0) -> 0 | BO97: =BF97+BH97+BJ97+BK97+BL97+BM97+BN97 -> 0 | BP97: =SUMIFS(SL_Budget!$B:$B,SL_Budget!$C:$C,"'"&TEXT(DATE(B97,A97,1),"YYYY-MM")) -> 5053 | BQ97: =MAX(BP97, IFERROR(SUMIFS(ShadowLedger!D:D, ShadowLedger!C:C, ">="&DATE(B97,A97,1), ShadowLedger!C:C, "<"&EOMONTH(DATE(B97,A97,1),0)+1), 0)) -> 5053 | BR97: =BV96 -> 974191.87 | BS97: =IF((AV96+AX96+BB96+AZ96+BD96)>5,0,X97) -> 2594.7074 | BT97: =IF(BY96>=Assumptions!$B$92,MAX(0,(AM97-BE97-BO97-BQ97)-Assumptions!$B$93),MAX(0,(AM97-BE97-BO97-BQ97)-Assumptions!$B$93)*Assumptions!$B$99) -> 16067.579 | BU97: =(BR97+BS97+MAX(0,BT97))*(Assumptions!$B$43-1) -> 6769.2796 | BV97: =BR97+BS97+BT97+BU97 -> 999623.43 | BW97: =BY96 -> 15476.047 | BX97: =IF(BY96<Assumptions!$B$92,MAX(0,(AM97-BE97-BO97-BQ97)-Assumptions!$B$93)*Assumptions!$B$98,0) -> 0 | BY97: =BW97+BX97 -> 15476.047 | BZ97: =IF(A97=1,0,CB96) -> 75310 | CA97: =AH97 -> 7088 | CB97: =BZ97+CA97 -> 82398 | CC97: =CC96+(G97+J97)/(Salary_Schedule!E97*12/208) -> 1803.0296 | CD97: =CD96+(O97+R97)/(Salary_Schedule!G97*12/208) -> 132.48167 | CE97: =BV97 -> 999623.43 | CF97: =Assumptions!$B$55*(1+Assumptions!$B$56)^((B97-2025)+(A97-1)/12) -> 593825.56 | CG97: =-AT97 -> 0 | CH97: =-(AV97+AX97+BB97+AZ97+BD97+AF97+BG97+BI97) -> -10500 | CI97: =CC97*(Salary_Schedule!E97/173.33)*(1-Assumptions!$B$28)+CD97*(Salary_Schedule!G97/173.33)*(1-Assumptions!$B$28) -> 74001.025 | CJ97: =CE97+CF97+CG97+CH97+CI97 -> 1656950
A98: 1 | B98: 2034 | C98: 01/2034 | D98: =C97 -> 12/2033 | E98: =IF(I98>0,"FAT_BONUS",IF(M98+U98>0,"FAT_RSU","LEAN")) -> FAT_RSU | F98: =Salary_Schedule!E98 -> 10883.55 | G98: =Assumptions!$B$8 -> 200 | H98: =F98*Assumptions!$B$58 -> 1088.355 | I98: =Salary_Schedule!F98 -> 0 | J98: =I98*Assumptions!$B$9 -> 0 | K98: =F98-G98-H98+I98-J98 -> 9595.195 | L98: =IF(COUNTIFS(SL_Income_Log!$B:$B,TEXT(B98,"0000")&"-"&TEXT(A98,"00"),SL_Income_Log!$C:$C,"salary",SL_Income_Log!$E:$E,"H")>0,SUMIFS(SL_Income_Log!$D:$D,SL_Income_Log!$B:$B,TEXT(B98,"0000")&"-"&TEXT(A98,"00"),SL_Income_Log!$C:$C,"salary",SL_Income_Log!$E:$E,"H"),K98*(1-Assumptions!$B$102)-Z98-Y98) -> 5757.117 | M98: =RSU_Schedule!H97 -> 2784.99 | N98: =Salary_Schedule!G98 -> 8158.51 | O98: =Assumptions!$B$19 -> 200 | P98: =N98*Assumptions!$B$59 -> 815.851 | Q98: =Salary_Schedule!H98 -> 0 | R98: =Q98*Assumptions!$B$20 -> 0 | S98: =N98-O98-P98+Q98-R98 -> 7142.659 | T98: =IF(COUNTIFS(SL_Income_Log!$B:$B,TEXT(B98,"0000")&"-"&TEXT(A98,"00"),SL_Income_Log!$C:$C,"salary",SL_Income_Log!$E:$E,"W")>0,SUMIFS(SL_Income_Log!$D:$D,SL_Income_Log!$B:$B,TEXT(B98,"0000")&"-"&TEXT(A98,"00"),SL_Income_Log!$C:$C,"salary",SL_Income_Log!$E:$E,"W"),S98*(1-Assumptions!$B$102)-AC98-AB98) -> 4285.5954 | U98: =RSU_Schedule!M97 -> 1392.51 | V98: =H98*(1+Assumptions!$B$60)+Assumptions!$B$61 -> 1543.697 | W98: =P98*(1+Assumptions!$B$60)+Assumptions!$B$61 -> 1162.1914 | X98: =V98+W98 -> 2705.8884 | Y98: 0 | Z98: 0 | AA98: 0 | AB98: 0 | AC98: 0 | AD98: 0 | AE98: =Z98+AC98 -> 0 | AF98: =AA98+AD98 -> 0 | AG98: =IF(COUNTIFS(SL_Income_Log!$B:$B,TEXT(B98,"0000")&"-"&TEXT(A98,"00"),SL_Income_Log!$C:$C,"youtube")>0,SUMIFS(SL_Income_Log!$D:$D,SL_Income_Log!$B:$B,TEXT(B98,"0000")&"-"&TEXT(A98,"00"),SL_Income_Log!$C:$C,"youtube"),MIN(Assumptions!$B$49+FLOOR((ROW()-2)/6,1)*Assumptions!$B$50,Assumptions!$B$51)) -> 17000 | AH98: =AG98*Assumptions!$B$104 -> 7531 | AI98: =AG98-AH98 -> 9469 | AJ98: =SUMIFS(SL_Income_Log!$D:$D,SL_Income_Log!$B:$B,TEXT(B98,"0000")&"-"&TEXT(A98,"00"),SL_Income_Log!$C:$C,"other") -> 0 | AK98: =AN97 -> 10000 | AL98: =L98+M98+T98+U98+AI98+AJ98-Y98-Z98-AB98-AC98+IF((Debt_Register!$C$2+Debt_Register!$C$6+Debt_Register!$C$7+Debt_Register!$C$8+Debt_Register!$C$9)>5,X98,0) -> 26395.101 | AM98: =AK98+AL98 -> 36395.101 | AN98: =MAX(Assumptions!$B$94,MIN(Assumptions!$B$93,AM98-AP98-BE98-BO98-BQ98)) -> 10000 | AO98: 0 | AP98: 0 | AQ98: 0 | AR98: 0 | AS98: 0 | AT98: 0 | AU98: =IF(AV97>0,MIN(AV97,MAX(300,AM98-AP98-BO98-BQ98-AW98-AY98-BA98-BC98)),0) -> 0 | AV98: =MAX(0,AV97-AU98) -> 0 | AW98: =IF(AX97>0,MIN(250,AX97),0) -> 0 | AX98: =MAX(0,AX97-AW98) -> 0 | AY98: =IF(AZ97>0,MIN(200,AZ97),0) -> 0 | AZ98: =MAX(0,AZ97-AY98) -> 0 | BA98: =IF(AND(AV97<5,BB97>0),MIN(BB97,MAX(0,AM98-AP98-BO98-BQ98-AW98-AY98-BC98)),0) -> 0 | BB98: =MAX(0,BB97-BA98) -> 0 | BC98: =IF(BD97>0,MIN(50,BD97),0) -> 0 | BD98: =MAX(0,BD97-BC98) -> 0 | BE98: =AU98+AW98+AY98+BA98+BC98 -> 0 | BF98: 0 | BG98: =MAX(0,BG97-BF98) -> 5500 | BH98: 0 | BI98: =MAX(0,BI97-BH98) -> 5000 | BJ98: =IF(OR(B98<Assumptions!$B$111,AND(B98=Assumptions!$B$111,A98<=Assumptions!$B$112)),Assumptions!$B$110,0) -> 0 | BK98: =IF(B98<2027,Assumptions!$B$116+IF(OR(A98=4,A98=10),Assumptions!$B$117,0),IF(AND(B98=2027,A98<=4),IF(A98=4,MIN(950,Assumptions!$B$116+Assumptions!$B$117),Assumptions!$B$116),0)) -> 0 | BL98: =IF(OR(B98<2030,AND(B98=2030,A98<8)),Assumptions!$B$118,IF(AND(B98=2030,A98=8),MOD(11000,200),0)) -> 0 | BM98: =IF(OR(B98<Assumptions!$B$120,AND(B98=Assumptions!$B$120,A98<=Assumptions!$B$121)),Assumptions!$B$119,0) -> 0 | BN98: =IF(AND(B98<=Assumptions!$B$123,A98<=Assumptions!$B$124),Assumptions!$B$122,0) -> 0 | BO98: =BF98+BH98+BJ98+BK98+BL98+BM98+BN98 -> 0 | BP98: =SUMIFS(SL_Budget!$B:$B,SL_Budget!$C:$C,"'"&TEXT(DATE(B98,A98,1),"YYYY-MM")) -> 5205 | BQ98: =MAX(BP98, IFERROR(SUMIFS(ShadowLedger!D:D, ShadowLedger!C:C, ">="&DATE(B98,A98,1), ShadowLedger!C:C, "<"&EOMONTH(DATE(B98,A98,1),0)+1), 0)) -> 5205 | BR98: =BV97 -> 999623.43 | BS98: =IF((AV97+AX97+BB97+AZ97+BD97)>5,0,X98) -> 2705.8884 | BT98: =IF(BY97>=Assumptions!$B$92,MAX(0,(AM98-BE98-BO98-BQ98)-Assumptions!$B$93),MAX(0,(AM98-BE98-BO98-BQ98)-Assumptions!$B$93)*Assumptions!$B$99) -> 21190.101 | BU98: =(BR98+BS98+MAX(0,BT98))*(Assumptions!$B$43-1) -> 6978.3554 | BV98: =BR98+BS98+BT98+BU98 -> 1030497.8 | BW98: =BY97 -> 15476.047 | BX98: =IF(BY97<Assumptions!$B$92,MAX(0,(AM98-BE98-BO98-BQ98)-Assumptions!$B$93)*Assumptions!$B$98,0) -> 0 | BY98: =BW98+BX98 -> 15476.047 | BZ98: =IF(A98=1,0,CB97) -> 0 | CA98: =AH98 -> 7531 | CB98: =BZ98+CA98 -> 7531 | CC98: =CC97+(G98+J98)/(Salary_Schedule!E98*12/208) -> 1803.3481 | CD98: =CD97+(O98+R98)/(Salary_Schedule!G98*12/208) -> 132.90658 | CE98: =BV98 -> 1030497.8 | CF98: =Assumptions!$B$55*(1+Assumptions!$B$56)^((B98-2025)+(A98-1)/12) -> 594562.79 | CG98: =-AT98 -> 0 | CH98: =-(AV98+AX98+BB98+AZ98+BD98+AF98+BG98+BI98) -> -10500 | CI98: =CC98*(Salary_Schedule!E98/173.33)*(1-Assumptions!$B$28)+CD98*(Salary_Schedule!G98/173.33)*(1-Assumptions!$B$28) -> 77668.303 | CJ98: =CE98+CF98+CG98+CH98+CI98 -> 1692228.9
